computing_cascade/AC_PH/fft/serial_fft_fsm/serial_fft_fsm.sv
module arithmetic_right_shift
# (
    parameter N = 32, 
    parameter S = 10
)
(
    input  [N - 1:0] a, 
    output [N - 1:0] res
);
  assign res = { {S{a[N-1]}}, a[N-1:S]};
endmodule



module serial_fft_fsm
#(
    parameter W_WIDTH      = 16,
    parameter X_WIDTH      = 16,
    parameter S_WIDTH      = 32,
    parameter WF           = 10,

    parameter FRAME_LENGTH = 3,
    parameter CHANELS      = 2
)
(
    input  logic                                    clk,
    input  logic                                    rstn,

    input  logic signed [W_WIDTH-1:0]               w_re,
    input  logic signed [W_WIDTH-1:0]               w_im,

    input  logic                                    valid_i,
    input  logic signed [CHANELS-1:0] [X_WIDTH-1:0] x,
    
    output logic signed [CHANELS-1:0] [S_WIDTH-1:0] re,
    output logic signed [CHANELS-1:0] [S_WIDTH-1:0] im,
    output logic                                    valid_o,
    output logic                                    finish
);
    logic [$clog2(FRAME_LENGTH):0] cnt;
    logic cnt_enable;
    assign cnt_enable = cnt == FRAME_LENGTH-1;
    assign finish = cnt_enable & valid_i;
    always_ff @(posedge clk) begin
        if (!rstn)          cnt <= 'b0;
        if (valid_i) begin
            if (cnt_enable) cnt <= 'b0;
            else            cnt <= cnt + 'b1;
        end
    end

    always_ff @(posedge clk) begin
        if (!rstn)                     valid_o <= 'b0;
        else if(cnt_enable) valid_o <= valid_i;
        else                           valid_o <= 'b0;
    end

    genvar i;
    generate
        for (i=0; i<CHANELS; i++) begin : CHANEL
            logic signed [S_WIDTH-1:0] sn;
            logic signed [S_WIDTH-1:0] sn1;

            wire signed [S_WIDTH-1:0] s_mul;
            arithmetic_right_shift#(
                .N(S_WIDTH),
                .S(WF)
            ) mul_sn (
                .a(sn * (w_re << 1)),
                .res(s_mul)
            );

            always_ff @(posedge clk) begin
                if (valid_i) begin
                    if (|cnt) begin
                        sn <= s_mul - sn1 + (x[i] << WF);
                        sn1 <= sn;
                    end
                    else begin
                        sn <= x[i] <<< WF;
                        sn1 <= 'b0;
                    end
                end
            end

            logic signed [S_WIDTH-1:0] re_mul;
            arithmetic_right_shift#(
                .N(S_WIDTH),
                .S(WF)
            ) mul_re (
                .a(sn * w_re),
                .res(re_mul)
            );
            assign re[i] = re_mul - sn1;

            logic signed [S_WIDTH-1:0] im_mul;
            arithmetic_right_shift#(
                .N(S_WIDTH),
                .S(WF)
            ) mul_im (
                .a(sn * w_im),
                .res(im_mul)
            );
            assign im[i] = im_mul;
        end
    endgenerate
endmodule

computing_cascade/AC_PH/fft/serial_fft_fsm/testbench.sv
`timescale 1ns/1ps

module a
#(
    parameter W_WIDTH  = 16,
    parameter X_WIDTH  = 16,
    parameter S_WIDTH  = 32,

    parameter FRAME_LENGTH = 10,
    parameter CHANELS = 2
)
(
    input  logic                                       clk,
    input  logic                                       arstn,

    input  logic                                       valid_i,
    input  logic signed [CHANELS-1:0] [X_WIDTH-1:0]    x,
    
    output logic signed [CHANELS-1:0][S_WIDTH-1:0]     re,
    output logic signed [CHANELS-1:0][S_WIDTH-1:0]     im,
    output logic                                       valid_o,
    output logic                                       finish
);
    logic signed [W_WIDTH-1:0] w_re;
    logic signed [W_WIDTH-1:0] w_im;

    assign w_re = 'd65376;
    assign w_im = -'d4572;
    
    serial_fft_fsm #(
        .W_WIDTH  (W_WIDTH),
        .X_WIDTH  (X_WIDTH),
        .S_WIDTH  (S_WIDTH),
        .FRAME_LENGTH (FRAME_LENGTH),
        .WF(16)

    ) core (
        .clk           (clk   ),
        .rstn         (arstn ),

        .w_re          (w_re  ),
        .w_im          (w_im  ),

        .valid_i       (valid_i),
        .x            (x      ),

        .re            (re),
        .im            (im),
        .valid_o       (valid_o),
        .finish        (finish)
    );
endmodule

module testbench;
    // Подключение
    localparam W_WIDTH  = 17;
    localparam X_WIDTH  = 16;
    localparam S_WIDTH  = 64;
    localparam FRAME_LENGTH = 360;
    localparam CHANELS = 2;

    logic                                        clk;
    logic                                        arstn;

    logic                                        valid_i;
    logic signed [CHANELS-1:0][X_WIDTH-1:0]      x;
    logic signed [X_WIDTH-1:0]                   x1;
    logic signed [X_WIDTH-1:0]                   x2;
    assign x = {x2, x1};

    logic signed [CHANELS-1:0][S_WIDTH-1:0]      re;
    logic signed [S_WIDTH-1:0] re1;
    logic signed [CHANELS-1:0][S_WIDTH-1:0]      im;
    logic signed [S_WIDTH-1:0] im1;
    logic                                        valid_o;
    logic                                        finish;
    assign re1 = re[0];
    assign im1 = im[0];

    a #(
        .W_WIDTH  (W_WIDTH),
        .X_WIDTH  (X_WIDTH),
        .S_WIDTH  (S_WIDTH),
        .FRAME_LENGTH (FRAME_LENGTH),
        .CHANELS (CHANELS)
    ) test (
        .clk           (clk   ),
        .arstn         (arstn ),

        .valid_i       (valid_i),
        .x            (x     ),

        .re            (re),
        .im            (im),
        .valid_o       (valid_o),
        .finish        (finish)
    );

    initial begin
        $dumpfile("serial_fft_fsm.vcd");
        $dumpvars;
    end
    // Запись значений в веса

    // Генерация clk
    parameter CLK_PERIOD = 20; // 50 МГц
    initial begin
        clk <= 0;
        forever begin
            #(CLK_PERIOD / 2); clk <= ~clk;
        end
    end

    //Генерация rst
    initial begin
        arstn <= 0;
        @(posedge clk);
        @(posedge clk);
        @(posedge clk);
        arstn <= 1;
    end

    // Генерация входных сигналов
    initial begin
        valid_i <= 'b0;

        wait(arstn);
        @(posedge clk);
    //---------------------------------------------------------------------------------------------
        //1
        @(posedge clk);
        @(posedge clk);
        valid_i <= 'b1;
x1       <= 'd2047;
@(posedge clk);
x1       <= 'd2188;
@(posedge clk);
x1       <= 'd2328;
@(posedge clk);
x1       <= 'd2466;
@(posedge clk);
x1       <= 'd2603;
@(posedge clk);
x1       <= 'd2737;
@(posedge clk);
x1       <= 'd2868;
@(posedge clk);
x1       <= 'd2994;
@(posedge clk);
x1       <= 'd3117;
@(posedge clk);
x1       <= 'd3234;
@(posedge clk);
x1       <= 'd3346;
@(posedge clk);
x1       <= 'd3452;
@(posedge clk);
x1       <= 'd3551;
@(posedge clk);
x1       <= 'd3642;
@(posedge clk);
x1       <= 'd3727;
@(posedge clk);
x1       <= 'd3803;
@(posedge clk);
x1       <= 'd3871;
@(posedge clk);
x1       <= 'd3931;
@(posedge clk);
x1       <= 'd3981;
@(posedge clk);
x1       <= 'd4023;
@(posedge clk);
x1       <= 'd4055;
@(posedge clk);
x1       <= 'd4078;
@(posedge clk);
x1       <= 'd4091;
@(posedge clk);
x1       <= 'd4094;
@(posedge clk);
x1       <= 'd4088;
@(posedge clk);
x1       <= 'd4072;
@(posedge clk);
x1       <= 'd4047;
@(posedge clk);
x1       <= 'd4012;
@(posedge clk);
x1       <= 'd3968;
@(posedge clk);
x1       <= 'd3915;
@(posedge clk);
x1       <= 'd3853;
@(posedge clk);
x1       <= 'd3782;
@(posedge clk);
x1       <= 'd3703;
@(posedge clk);
x1       <= 'd3617;
@(posedge clk);
x1       <= 'd3523;
@(posedge clk);
x1       <= 'd3422;
@(posedge clk);
x1       <= 'd3315;
@(posedge clk);
x1       <= 'd3201;
@(posedge clk);
x1       <= 'd3082;
@(posedge clk);
x1       <= 'd2959;
@(posedge clk);
x1       <= 'd2831;
@(posedge clk);
x1       <= 'd2699;
@(posedge clk);
x1       <= 'd2564;
@(posedge clk);
x1       <= 'd2427;
@(posedge clk);
x1       <= 'd2288;
@(posedge clk);
x1       <= 'd2147;
@(posedge clk);
x1       <= 'd2007;
@(posedge clk);
x1       <= 'd1866;
@(posedge clk);
x1       <= 'd1727;
@(posedge clk);
x1       <= 'd1589;
@(posedge clk);
x1       <= 'd1453;
@(posedge clk);
x1       <= 'd1319;
@(posedge clk);
x1       <= 'd1190;
@(posedge clk);
x1       <= 'd1064;
@(posedge clk);
x1       <= 'd943;
@(posedge clk);
x1       <= 'd827;
@(posedge clk);
x1       <= 'd717;
@(posedge clk);
x1       <= 'd613;
@(posedge clk);
x1       <= 'd516;
@(posedge clk);
x1       <= 'd427;
@(posedge clk);
x1       <= 'd345;
@(posedge clk);
x1       <= 'd270;
@(posedge clk);
x1       <= 'd205;
@(posedge clk);
x1       <= 'd148;
@(posedge clk);
x1       <= 'd100;
@(posedge clk);
x1       <= 'd61;
@(posedge clk);
x1       <= 'd31;
@(posedge clk);
x1       <= 'd11;
@(posedge clk);
x1       <= 'd1;
@(posedge clk);
x1       <= 'd0;
@(posedge clk);
x1       <= 'd9;
@(posedge clk);
x1       <= 'd28;
@(posedge clk);
x1       <= 'd56;
@(posedge clk);
x1       <= 'd94;
@(posedge clk);
x1       <= 'd140;
@(posedge clk);
x1       <= 'd196;
@(posedge clk);
x1       <= 'd261;
@(posedge clk);
x1       <= 'd334;
@(posedge clk);
x1       <= 'd415;
@(posedge clk);
x1       <= 'd503;
@(posedge clk);
x1       <= 'd599;
@(posedge clk);
x1       <= 'd702;
@(posedge clk);
x1       <= 'd811;
@(posedge clk);
x1       <= 'd926;
@(posedge clk);
x1       <= 'd1047;
@(posedge clk);
x1       <= 'd1172;
@(posedge clk);
x1       <= 'd1301;
@(posedge clk);
x1       <= 'd1434;
@(posedge clk);
x1       <= 'd1569;
@(posedge clk);
x1       <= 'd1707;
@(posedge clk);
x1       <= 'd1846;
@(posedge clk);
x1       <= 'd1987;
@(posedge clk);
x1       <= 'd2127;
@(posedge clk);
x1       <= 'd2268;
@(posedge clk);
x1       <= 'd2407;
@(posedge clk);
x1       <= 'd2545;
@(posedge clk);
x1       <= 'd2680;
@(posedge clk);
x1       <= 'd2812;
@(posedge clk);
x1       <= 'd2941;
@(posedge clk);
x1       <= 'd3065;
@(posedge clk);
x1       <= 'd3185;
@(posedge clk);
x1       <= 'd3299;
@(posedge clk);
x1       <= 'd3407;
@(posedge clk);
x1       <= 'd3509;
@(posedge clk);
x1       <= 'd3604;
@(posedge clk);
x1       <= 'd3692;
@(posedge clk);
x1       <= 'd3771;
@(posedge clk);
x1       <= 'd3843;
@(posedge clk);
x1       <= 'd3906;
@(posedge clk);
x1       <= 'd3961;
@(posedge clk);
x1       <= 'd4006;
@(posedge clk);
x1       <= 'd4043;
@(posedge clk);
x1       <= 'd4069;
@(posedge clk);
x1       <= 'd4087;
@(posedge clk);
x1       <= 'd4094;
@(posedge clk);
x1       <= 'd4092;
@(posedge clk);
x1       <= 'd4080;
@(posedge clk);
x1       <= 'd4059;
@(posedge clk);
x1       <= 'd4028;
@(posedge clk);
x1       <= 'd3988;
@(posedge clk);
x1       <= 'd3939;
@(posedge clk);
x1       <= 'd3880;
@(posedge clk);
x1       <= 'd3813;
@(posedge clk);
x1       <= 'd3738;
@(posedge clk);
x1       <= 'd3655;
@(posedge clk);
x1       <= 'd3564;
@(posedge clk);
x1       <= 'd3466;
@(posedge clk);
x1       <= 'd3361;
@(posedge clk);
x1       <= 'd3250;
@(posedge clk);
x1       <= 'd3134;
@(posedge clk);
x1       <= 'd3012;
@(posedge clk);
x1       <= 'd2886;
@(posedge clk);
x1       <= 'd2756;
@(posedge clk);
x1       <= 'd2622;
@(posedge clk);
x1       <= 'd2486;
@(posedge clk);
x1       <= 'd2347;
@(posedge clk);
x1       <= 'd2208;
@(posedge clk);
x1       <= 'd2067;
@(posedge clk);
x1       <= 'd1926;
@(posedge clk);
x1       <= 'd1786;
@(posedge clk);
x1       <= 'd1647;
@(posedge clk);
x1       <= 'd1510;
@(posedge clk);
x1       <= 'd1376;
@(posedge clk);
x1       <= 'd1245;
@(posedge clk);
x1       <= 'd1117;
@(posedge clk);
x1       <= 'd994;
@(posedge clk);
x1       <= 'd876;
@(posedge clk);
x1       <= 'd764;
@(posedge clk);
x1       <= 'd657;
@(posedge clk);
x1       <= 'd557;
@(posedge clk);
x1       <= 'd464;
@(posedge clk);
x1       <= 'd379;
@(posedge clk);
x1       <= 'd301;
@(posedge clk);
x1       <= 'd232;
@(posedge clk);
x1       <= 'd171;
@(posedge clk);
x1       <= 'd119;
@(posedge clk);
x1       <= 'd76;
@(posedge clk);
x1       <= 'd43;
@(posedge clk);
x1       <= 'd19;
@(posedge clk);
x1       <= 'd4;
@(posedge clk);
x1       <= 'd0;
@(posedge clk);
x1       <= 'd4;
@(posedge clk);
x1       <= 'd19;
@(posedge clk);
x1       <= 'd43;
@(posedge clk);
x1       <= 'd76;
@(posedge clk);
x1       <= 'd119;
@(posedge clk);
x1       <= 'd171;
@(posedge clk);
x1       <= 'd232;
@(posedge clk);
x1       <= 'd301;
@(posedge clk);
x1       <= 'd379;
@(posedge clk);
x1       <= 'd464;
@(posedge clk);
x1       <= 'd557;
@(posedge clk);
x1       <= 'd657;
@(posedge clk);
x1       <= 'd764;
@(posedge clk);
x1       <= 'd876;
@(posedge clk);
x1       <= 'd995;
@(posedge clk);
x1       <= 'd1118;
@(posedge clk);
x1       <= 'd1245;
@(posedge clk);
x1       <= 'd1376;
@(posedge clk);
x1       <= 'd1511;
@(posedge clk);
x1       <= 'd1648;
@(posedge clk);
x1       <= 'd1787;
@(posedge clk);
x1       <= 'd1927;
@(posedge clk);
x1       <= 'd2067;
@(posedge clk);
x1       <= 'd2208;
@(posedge clk);
x1       <= 'd2348;
@(posedge clk);
x1       <= 'd2486;
@(posedge clk);
x1       <= 'd2622;
@(posedge clk);
x1       <= 'd2756;
@(posedge clk);
x1       <= 'd2886;
@(posedge clk);
x1       <= 'd3012;
@(posedge clk);
x1       <= 'd3134;
@(posedge clk);
x1       <= 'd3251;
@(posedge clk);
x1       <= 'd3362;
@(posedge clk);
x1       <= 'd3466;
@(posedge clk);
x1       <= 'd3564;
@(posedge clk);
x1       <= 'd3655;
@(posedge clk);
x1       <= 'd3738;
@(posedge clk);
x1       <= 'd3814;
@(posedge clk);
x1       <= 'd3880;
@(posedge clk);
x1       <= 'd3939;
@(posedge clk);
x1       <= 'd3988;
@(posedge clk);
x1       <= 'd4028;
@(posedge clk);
x1       <= 'd4059;
@(posedge clk);
x1       <= 'd4080;
@(posedge clk);
x1       <= 'd4092;
@(posedge clk);
x1       <= 'd4094;
@(posedge clk);
x1       <= 'd4086;
@(posedge clk);
x1       <= 'd4069;
@(posedge clk);
x1       <= 'd4042;
@(posedge clk);
x1       <= 'd4006;
@(posedge clk);
x1       <= 'd3961;
@(posedge clk);
x1       <= 'd3906;
@(posedge clk);
x1       <= 'd3843;
@(posedge clk);
x1       <= 'd3771;
@(posedge clk);
x1       <= 'd3691;
@(posedge clk);
x1       <= 'd3604;
@(posedge clk);
x1       <= 'd3509;
@(posedge clk);
x1       <= 'd3407;
@(posedge clk);
x1       <= 'd3299;
@(posedge clk);
x1       <= 'd3184;
@(posedge clk);
x1       <= 'd3065;
@(posedge clk);
x1       <= 'd2940;
@(posedge clk);
x1       <= 'd2812;
@(posedge clk);
x1       <= 'd2680;
@(posedge clk);
x1       <= 'd2544;
@(posedge clk);
x1       <= 'd2407;
@(posedge clk);
x1       <= 'd2267;
@(posedge clk);
x1       <= 'd2127;
@(posedge clk);
x1       <= 'd1987;
@(posedge clk);
x1       <= 'd1846;
@(posedge clk);
x1       <= 'd1707;
@(posedge clk);
x1       <= 'd1569;
@(posedge clk);
x1       <= 'd1433;
@(posedge clk);
x1       <= 'd1301;
@(posedge clk);
x1       <= 'd1171;
@(posedge clk);
x1       <= 'd1046;
@(posedge clk);
x1       <= 'd926;
@(posedge clk);
x1       <= 'd811;
@(posedge clk);
x1       <= 'd702;
@(posedge clk);
x1       <= 'd599;
@(posedge clk);
x1       <= 'd503;
@(posedge clk);
x1       <= 'd414;
@(posedge clk);
x1       <= 'd333;
@(posedge clk);
x1       <= 'd260;
@(posedge clk);
x1       <= 'd196;
@(posedge clk);
x1       <= 'd140;
@(posedge clk);
x1       <= 'd94;
@(posedge clk);
x1       <= 'd56;
@(posedge clk);
x1       <= 'd28;
@(posedge clk);
x1       <= 'd9;
@(posedge clk);
x1       <= 'd0;
@(posedge clk);
x1       <= 'd1;
@(posedge clk);
x1       <= 'd11;
@(posedge clk);
x1       <= 'd31;
@(posedge clk);
x1       <= 'd61;
@(posedge clk);
x1       <= 'd100;
@(posedge clk);
x1       <= 'd148;
@(posedge clk);
x1       <= 'd205;
@(posedge clk);
x1       <= 'd271;
@(posedge clk);
x1       <= 'd345;
@(posedge clk);
x1       <= 'd427;
@(posedge clk);
x1       <= 'd517;
@(posedge clk);
x1       <= 'd614;
@(posedge clk);
x1       <= 'd717;
@(posedge clk);
x1       <= 'd827;
@(posedge clk);
x1       <= 'd943;
@(posedge clk);
x1       <= 'd1064;
@(posedge clk);
x1       <= 'd1190;
@(posedge clk);
x1       <= 'd1320;
@(posedge clk);
x1       <= 'd1453;
@(posedge clk);
x1       <= 'd1589;
@(posedge clk);
x1       <= 'd1727;
@(posedge clk);
x1       <= 'd1867;
@(posedge clk);
x1       <= 'd2007;
@(posedge clk);
x1       <= 'd2148;
@(posedge clk);
x1       <= 'd2288;
@(posedge clk);
x1       <= 'd2427;
@(posedge clk);
x1       <= 'd2564;
@(posedge clk);
x1       <= 'd2699;
@(posedge clk);
x1       <= 'd2831;
@(posedge clk);
x1       <= 'd2959;
@(posedge clk);
x1       <= 'd3083;
@(posedge clk);
x1       <= 'd3201;
@(posedge clk);
x1       <= 'd3315;
@(posedge clk);
x1       <= 'd3422;
@(posedge clk);
x1       <= 'd3523;
@(posedge clk);
x1       <= 'd3617;
@(posedge clk);
x1       <= 'd3704;
@(posedge clk);
x1       <= 'd3782;
@(posedge clk);
x1       <= 'd3853;
@(posedge clk);
x1       <= 'd3915;
@(posedge clk);
x1       <= 'd3968;
@(posedge clk);
x1       <= 'd4012;
@(posedge clk);
x1       <= 'd4047;
@(posedge clk);
x1       <= 'd4072;
@(posedge clk);
x1       <= 'd4088;
@(posedge clk);
x1       <= 'd4094;
@(posedge clk);
x1       <= 'd4091;
@(posedge clk);
x1       <= 'd4078;
@(posedge clk);
x1       <= 'd4055;
@(posedge clk);
x1       <= 'd4023;
@(posedge clk);
x1       <= 'd3981;
@(posedge clk);
x1       <= 'd3931;
@(posedge clk);
x1       <= 'd3871;
@(posedge clk);
x1       <= 'd3803;
@(posedge clk);
x1       <= 'd3727;
@(posedge clk);
x1       <= 'd3642;
@(posedge clk);
x1       <= 'd3550;
@(posedge clk);
x1       <= 'd3451;
@(posedge clk);
x1       <= 'd3346;
@(posedge clk);
x1       <= 'd3234;
@(posedge clk);
x1       <= 'd3117;
@(posedge clk);
x1       <= 'd2994;
@(posedge clk);
x1       <= 'd2867;
@(posedge clk);
x1       <= 'd2737;
@(posedge clk);
x1       <= 'd2603;
@(posedge clk);
x1       <= 'd2466;
@(posedge clk);
x1       <= 'd2327;
@(posedge clk);
x1       <= 'd2187;
@(posedge clk);
x1       <= 'd2047;
@(posedge clk);
x1       <= 'd1906;
@(posedge clk);
x1       <= 'd1766;
@(posedge clk);
x1       <= 'd1628;
@(posedge clk);
x1       <= 'd1491;
@(posedge clk);
x1       <= 'd1357;
@(posedge clk);
x1       <= 'd1226;
@(posedge clk);
x1       <= 'd1099;
@(posedge clk);
x1       <= 'd977;
@(posedge clk);
x1       <= 'd860;
@(posedge clk);
x1       <= 'd748;
@(posedge clk);
x1       <= 'd642;
@(posedge clk);
x1       <= 'd543;
@(posedge clk);
x1       <= 'd451;
@(posedge clk);
x1       <= 'd367;
@(posedge clk);
x1       <= 'd291;
@(posedge clk);
x1       <= 'd223;
@(posedge clk);
x1       <= 'd163;
@(posedge clk);
x1       <= 'd112;
@(posedge clk);
x1       <= 'd71;
@(posedge clk);
x1       <= 'd39;
@(posedge clk);
x1       <= 'd16;
@(posedge clk);
x1       <= 'd3;
@(posedge clk);
x1       <= 'd0;
@(posedge clk);
x1       <= 'd6;
@(posedge clk);
x1       <= 'd22;
@(posedge clk);
x1       <= 'd47;
@(posedge clk);
x1       <= 'd82;
@(posedge clk);
x1       <= 'd126;
@(posedge clk);
x1       <= 'd179;
@(posedge clk);
x1       <= 'd241;
@(posedge clk);
x1       <= 'd312;
@(posedge clk);
x1       <= 'd391;
@(posedge clk);
x1       <= 'd477;
@(posedge clk);
x1       <= 'd571;
@(posedge clk);
x1       <= 'd672;
@(posedge clk);
x1       <= 'd780;
@(posedge clk);
x1       <= 'd893;
@(posedge clk);
x1       <= 'd1012;
@(posedge clk);
x1       <= 'd1136;

@(posedge clk);
@(posedge clk);
@(posedge clk);
@(posedge clk);
@(posedge clk);
@(posedge clk);


        $finish;
    end
    
endmodule

computing_cascade/AC_PH/fft/serial_fft_fsm.vcd
$date
	Sat Mar 29 21:43:38 2025
$end
$version
	Icarus Verilog
$end
$timescale
	1ps
$end
$scope module testbench $end
$var wire 32 ! x [31:0] $end
$var wire 1 " valid_o $end
$var wire 64 # re1 [63:0] $end
$var wire 128 $ re [127:0] $end
$var wire 64 % im1 [63:0] $end
$var wire 128 & im [127:0] $end
$var wire 1 ' finish $end
$var reg 1 ( arstn $end
$var reg 1 ) clk $end
$var reg 1 * valid_i $end
$var reg 16 + x1 [15:0] $end
$var reg 16 , x2 [15:0] $end
$scope module test $end
$var wire 1 ( arstn $end
$var wire 1 ) clk $end
$var wire 1 * valid_i $end
$var wire 17 - w_im [16:0] $end
$var wire 17 . w_re [16:0] $end
$var wire 32 / x [31:0] $end
$var wire 1 " valid_o $end
$var wire 128 0 re [127:0] $end
$var wire 128 1 im [127:0] $end
$var wire 1 ' finish $end
$scope module core $end
$var wire 1 ) clk $end
$var wire 1 ' finish $end
$var wire 1 ( rstn $end
$var wire 1 * valid_i $end
$var wire 17 2 w_im [16:0] $end
$var wire 17 3 w_re [16:0] $end
$var wire 32 4 x [31:0] $end
$var wire 128 5 re [127:0] $end
$var wire 128 6 im [127:0] $end
$var wire 1 7 cnt_enable $end
$var reg 10 8 cnt [9:0] $end
$var reg 1 " valid_o $end
$scope begin CHANEL[0] $end
$var wire 64 9 s_mul [63:0] $end
$var wire 64 : re_mul [63:0] $end
$var wire 64 ; im_mul [63:0] $end
$var reg 64 < sn [63:0] $end
$var reg 64 = sn1 [63:0] $end
$scope module mul_im $end
$var wire 64 > a [63:0] $end
$var wire 64 ? res [63:0] $end
$upscope $end
$scope module mul_re $end
$var wire 64 @ a [63:0] $end
$var wire 64 A res [63:0] $end
$upscope $end
$scope module mul_sn $end
$var wire 64 B a [63:0] $end
$var wire 64 C res [63:0] $end
$upscope $end
$upscope $end
$scope begin CHANEL[1] $end
$var wire 64 D s_mul [63:0] $end
$var wire 64 E re_mul [63:0] $end
$var wire 64 F im_mul [63:0] $end
$var reg 64 G sn [63:0] $end
$var reg 64 H sn1 [63:0] $end
$scope module mul_im $end
$var wire 64 I a [63:0] $end
$var wire 64 J res [63:0] $end
$upscope $end
$scope module mul_re $end
$var wire 64 K a [63:0] $end
$var wire 64 L res [63:0] $end
$upscope $end
$scope module mul_sn $end
$var wire 64 M a [63:0] $end
$var wire 64 N res [63:0] $end
$upscope $end
$upscope $end
$upscope $end
$upscope $end
$upscope $end
$enddefinitions $end
#0
$dumpvars
bx N
bx M
bx L
bx K
bx J
bx I
bx H
bx G
bx F
bx E
bx D
bx C
bx B
bx A
bx @
bx ?
bx >
bx =
bx <
bx ;
bx :
bx 9
bx 8
x7
bx 6
bx 5
bx 4
b1111111101100000 3
b11110111000100100 2
bx 1
bx 0
bx /
b1111111101100000 .
b11110111000100100 -
bx ,
bx +
0*
0)
0(
0'
bx &
bx %
bx $
bx #
x"
bx !
$end
#10000
07
b0 8
0"
1)
#20000
0)
#30000
1)
#40000
0)
#50000
1(
1)
#60000
0)
#70000
1)
#80000
0)
#90000
1)
#100000
0)
#110000
bx0000011111111111 !
bx0000011111111111 /
bx0000011111111111 4
b11111111111 +
1*
1)
#120000
0)
#130000
b111111110100000000010100000 #
b1111111111111111111111111111111111111111011100010011000111011100 %
b1111111101000000000101000000 9
b1111111101000000000101000000 C
bx0000000000000000000000000000000000000111111110100000000010100000 $
bx0000000000000000000000000000000000000111111110100000000010100000 0
bx0000000000000000000000000000000000000111111110100000000010100000 5
b111111110100000000010100000 :
b111111110100000000010100000 A
bx1111111111111111111111111111111111111111011100010011000111011100 &
bx1111111111111111111111111111111111111111011100010011000111011100 1
bx1111111111111111111111111111111111111111011100010011000111011100 6
b1111111111111111111111111111111111111111011100010011000111011100 ;
b1111111111111111111111111111111111111111011100010011000111011100 ?
bx0000100010001100 !
bx0000100010001100 /
bx0000100010001100 4
b100010001100 +
b0 =
b11111111010000000001010000000000000000000000 B
b1111111101000000000101000000000000000000000 @
b1111111111111111111111110111000100110001110111000000000000000000 >
b111111111110000000000000000 <
b0 H
bx0000000000000000 G
b1 8
1)
#140000
0)
#150000
b1111111111111111111111111111111111111110010010100111000111101001 %
b10000011100011011000100111111 #
b110000111000010110001001111110 9
b110000111000010110001001111110 C
b11000011100001011000100111111 :
b11000011100001011000100111111 A
bx1111111111111111111111111111111111111110010010100111000111101001 &
bx1111111111111111111111111111111111111110010010100111000111101001 1
bx1111111111111111111111111111111111111110010010100111000111101001 6
b1111111111111111111111111111111111111110010010100111000111101001 ;
b1111111111111111111111111111111111111110010010100111000111101001 ?
b10 8
bx0000000000000000 H
bx G
bx0000000000000000000000000000000000010000011100011011000100111111 $
bx0000000000000000000000000000000000010000011100011011000100111111 0
bx0000000000000000000000000000000000010000011100011011000100111111 5
b111111111110000000000000000 =
b1100001110000101100010011111100111000000000000 B
b110000111000010110001001111110011100000000000 @
b1111111111111111111111100100101001110001111010011010110100000000 >
b11000100000000000000101000000 <
bx0000100100011000 !
bx0000100100011000 /
bx0000100100011000 4
b100100011000 +
1)
#160000
0)
#170000
b1111111111111111111111111111111111111100100000110110110001001000 %
b11001010110110010010011000000 #
b1100011101101100100110000000000 9
b1100011101101100100110000000000 C
b110001110110110010011000000000 :
b110001110110110010011000000000 A
bx1111111111111111111111111111111111111100100000110110110001001000 &
bx1111111111111111111111111111111111111100100000110110110001001000 1
bx1111111111111111111111111111111111111100100000110110110001001000 6
b1111111111111111111111111111111111111100100000110110110001001000 ;
b1111111111111111111111111111111111111100100000110110110001001000 ?
bx0000100110100010 !
bx0000100110100010 /
bx0000100110100010 4
b100110100010 +
bx0000000000000000000000000000000000011001010110110010010011000000 $
bx0000000000000000000000000000000000011001010110110010010011000000 0
bx0000000000000000000000000000000000011001010110110010010011000000 5
b11000100000000000000101000000 =
b11000111011011001001100000000001110001010000000 B
b1100011101101100100110000000000111000101000000 @
b1111111111111111111111001000001101101100010010001111110110111000 >
b110001111110100110001001111110 <
bx H
b11 8
1)
#180000
0)
#190000
b1111111111111111111111111111111111111010000101001011100100101001 %
b100010101010001110000100010011 #
b10101001010001101000011100100010 9
b10101001010001101000011100100010 C
b1010100101000110100001110010001 :
b1010100101000110100001110010001 A
bx1111111111111111111111111111111111111010000101001011100100101001 &
bx1111111111111111111111111111111111111010000101001011100100101001 1
bx1111111111111111111111111111111111111010000101001011100100101001 6
b1111111111111111111111111111111111111010000101001011100100101001 ;
b1111111111111111111111111111111111111010000101001011100100101001 ?
b100 8
bx0000000000000000000000000000000000100010101010001110000100010011 $
bx0000000000000000000000000000000000100010101010001110000100010011 0
bx0000000000000000000000000000000000100010101010001110000100010011 5
b110001111110100110001001111110 =
b101010010100011010000111001000101001000000000000 B
b10101001010001101000011100100010100100000000000 @
b1111111111111111111110100001010010111001001010010000001100000000 >
b1010100110110000100101011000000 <
bx0000101000101011 !
bx0000101000101011 /
bx0000101000101011 4
b101000101011 +
1)
#200000
0)
#210000
b1111111111111111111111111111111111110110111101111101010000101101 %
b101100010011011110111101101101 #
b100000010010011000111010001011010 9
b100000010010011000111010001011010 C
b10000001001001100011101000101101 :
b10000001001001100011101000101101 A
bx1111111111111111111111111111111111110110111101111101010000101101 &
bx1111111111111111111111111111111111110110111101111101010000101101 1
bx1111111111111111111111111111111111110110111101111101010000101101 6
b1111111111111111111111111111111111110110111101111101010000101101 ;
b1111111111111111111111111111111111110110111101111101010000101101 ?
bx0000101010110001 !
bx0000101010110001 /
bx0000101010110001 4
b101010110001 +
bx0000000000000000000000000000000000101100010011011110111101101101 $
bx0000000000000000000000000000000000101100010011011110111101101101 0
bx0000000000000000000000000000000000101100010011011110111101101101 5
b1010100110110000100101011000000 =
b1000000100100110001110100010110100011001100000000 B
b100000010010011000111010001011010001100110000000 @
b1111111111111111111101101111011111010100001011011001111100010000 >
b10000001011101110010010010100100 <
b101 8
1)
#220000
0)
#230000
b1111111111111111111111111111111111110011001001110100100001001101 %
b110110001110101110110110111011 #
b101101111011001000010010010111111 9
b101101111011001000010010010111111 C
b10110111101100100001001001011111 :
b10110111101100100001001001011111 A
bx1111111111111111111111111111111111110011001001110100100001001101 &
bx1111111111111111111111111111111111110011001001110100100001001101 1
bx1111111111111111111111111111111111110011001001110100100001001101 6
b1111111111111111111111111111111111110011001001110100100001001101 ;
b1111111111111111111111111111111111110011001001110100100001001101 ?
b110 8
bx0000000000000000000000000000000000110110001110101110110110111011 $
bx0000000000000000000000000000000000110110001110101110110110111011 0
bx0000000000000000000000000000000000110110001110101110110110111011 5
b10000001011101110010010010100100 =
b1011011110110010000100100101111111111111110000000 B
b101101111011001000010010010111111111111111000000 @
b1111111111111111111100110010011101001000010011010000010110101000 >
b10111000001001010010100110011010 <
bx0000101100110100 !
bx0000101100110100 /
bx0000101100110100 4
b101100110100 +
1)
#240000
0)
