shift_reg/shift_reg.sv
module shift_reg
#(
    parameter LENGTH  = 3
)
(
    input  logic              clk,
    input  logic              arstn,
    input  logic              enable,
    
    output logic [LENGTH-1:0] register
);
    always_ff @ (posedge clk or negedge arstn)
       if (~arstn) begin
           register[LENGTH-2:0] <= 'b0;
           register[LENGTH-1]   <= 'b1;
       end
       else if (enable)
           register <= { register[0], register[LENGTH-1:1] };

endmodule

shift_reg/testbench.sv
`timescale 1ns/1ps

module test;
    // Подключение
    localparam LENGTH = 4;

    logic              clk;
    logic              arstn;
    logic              enable;
    logic [LENGTH-1:0] register;

    shift_reg #(
        .LENGTH  (LENGTH)
    ) r (
        .clk           (clk   ),
        .arstn         (arstn ),
        .enable        (enable),
        .register      (register)
    );

    initial begin
        $dumpfile("shift_reg.vcd");
        $dumpvars;
    end

    // Генерация clk
    parameter CLK_PERIOD = 20; // 50 МГц
    initial begin
        clk <= 0;
        forever begin
            #(CLK_PERIOD / 2); clk <= ~clk;
        end
    end

    //Генерация rst
    initial begin
        arstn <= 0;
        @(posedge clk);
        @(posedge clk);
        @(posedge clk);
        arstn <= 1;
    end

    // Генерация входных сигналов
    initial begin
        wait(arstn);
        @(posedge clk);
    //---------------------------------------------------------------------------------------------
        @(posedge clk);
        enable <= 'b1;
        @(posedge clk);
        @(posedge clk);
        @(posedge clk);
        @(posedge clk);
        @(posedge clk);
        enable <= 'b0;
        @(posedge clk);
        @(posedge clk);
        enable <= 'b1;
        @(posedge clk);
        @(posedge clk);
        @(posedge clk);
        $finish;
    end
    
    // Проверка
    // initial begin
    //     wait(~arstn);
    //     @(posedge clk);
    //     @(posedge clk);
    // //---------------------------------------------------------------------------------------------
    //     repeat (32)
    //     begin
    //         @(posedge clk);
    //         if ($signed(psumm_o) != ($signed(psumm_i) + $signed(weight_i) * $signed(x_i) )) begin
    //             $display($signed(psumm_o));
    //             $display(($signed(psumm_i) + $signed(weight_i) * $signed(x_i)));
    //             $display($signed(psumm_i));
    //             $display($signed(weight_i));
    //             $display($signed(x_i));
    //             $error("BAD");
    //         end
    //         else begin
    //             $display("PASS");
    //             // $display($signed(psumm_o));
    //             // $display($signed(psumm_i));
    //             // $display($signed(weight_i));
    //             // $display($signed(x_i));
    //         end
    //     end
    // //---------------------------------------------------------------------------------------------
    //     @(posedge clk);
    //     @(posedge clk);
    //     @(posedge clk);
    //     $finish;
    // end
endmodule

shift_reg.vcd
$date
	Fri Feb 28 11:35:03 2025
$end
$version
	Icarus Verilog
$end
$timescale
	1ps
$end
$scope module test $end
$var wire 4 ! register [3:0] $end
$var reg 1 " arstn $end
$var reg 1 # clk $end
$var reg 1 $ enable $end
$scope module r $end
$var wire 1 " arstn $end
$var wire 1 # clk $end
$var wire 1 $ enable $end
$var reg 4 % register [3:0] $end
$upscope $end
$upscope $end
$enddefinitions $end
#0
$dumpvars
b1000 %
x$
0#
0"
b1000 !
$end
#10000
1#
#20000
0#
#30000
1#
#40000
0#
#50000
1"
1#
#60000
0#
#70000
1#
#80000
0#
#90000
1$
1#
#100000
0#
#110000
b100 !
b100 %
1#
#120000
0#
#130000
b10 !
b10 %
1#
#140000
0#
#150000
b1 !
b1 %
1#
#160000
0#
#170000
b1000 !
b1000 %
1#
#180000
0#
#190000
b100 !
b100 %
0$
1#
#200000
0#
#210000
1#
#220000
0#
#230000
1$
1#
#240000
0#
#250000
b10 !
b10 %
1#
#260000
0#
#270000
b1 !
b1 %
1#
#280000
0#
#290000
b1000 !
b1000 %
1#
