custom_fifo/custom_fifo_valid_ready.sv
module custom_fifo
#(
    parameter WIDTH = 8, // fifo width
    parameter DEPTH = 4  // fifo depth
)
(
    input                clk,
    input                arstn,

    input                valid_i,
    input logic [DEPTH-1:0][WIDTH - 1:0] data_i,  // Эллементы буфера

    input                pop,               
    output [WIDTH - 1:0] read_data,           // Эллемент для чтения

    output               empty
);

   //------------------------------------------------------------------------
    localparam pointer_width = $clog2 (DEPTH),
               counter_width = $clog2 (DEPTH + 1);

    localparam [counter_width - 1:0] max_ptr = counter_width' (DEPTH - 1);

    //------------------------------------------------------------------------

    logic [pointer_width - 1:0] wr_ptr, rd_ptr;
    logic wr_ptr_odd_circle, rd_ptr_odd_circle;

    logic [DEPTH-1:0][WIDTH - 1:0] data;

    //------------------------------------------------------------------------

    always_ff @ (posedge clk or negedge arstn)
        if (!arstn)
        begin
            wr_ptr <= '0;
            wr_ptr_odd_circle <= 1'b0;
        end
        else if (valid_i)
        begin
            wr_ptr <= '0;
            wr_ptr_odd_circle <= ~ wr_ptr_odd_circle;
        end

    //------------------------------------------------------------------------

    always_ff @ (posedge clk or negedge arstn)
        if (!arstn)
        begin
            rd_ptr <= '0;
            rd_ptr_odd_circle <= 1'b0;
        end
        else if (pop)
        begin
            if (rd_ptr == max_ptr)
            begin
                rd_ptr <= '0;
                rd_ptr_odd_circle <= ~ rd_ptr_odd_circle;
            end
            else
            begin
                rd_ptr <= rd_ptr + 1'b1;
            end
        end

    //------------------------------------------------------------------------

    always_ff @ (posedge clk)
        if (valid_i)
            data <= data_i;

    assign read_data = data[rd_ptr];

    //------------------------------------------------------------------------

    wire equal_ptrs = (wr_ptr == rd_ptr);

    assign empty = equal_ptrs & wr_ptr_odd_circle == rd_ptr_odd_circle;
    
endmodule

module custom_fifo_valid_ready
# (
    parameter WIDTH = 8, 
    parameter DEPTH = 4
)
(
    input                clk,
    input                arstn,

    input                up_valid,    // upstream
    output               up_ready,
    input logic [DEPTH-1:0][WIDTH - 1:0] data_i,  // Эллементы буфера

    output               down_valid,  // downstream
    input                down_ready,
    output [WIDTH - 1:0] down_data
);

    wire fifo_push;
    wire fifo_pop;
    wire fifo_empty;
    wire fifo_full;

    assign up_ready   = fifo_empty;
    assign valid_i    = up_valid & up_ready;

    assign down_valid = ~ fifo_empty;
    assign pop        = down_valid & down_ready;

    custom_fifo
    # (.WIDTH (WIDTH), .DEPTH (DEPTH))
    fifo
    (
        .clk        ( clk        ),
        .arstn      ( arstn      ),

        .valid_i    ( valid_i    ),
        .pop        ( pop        ),
        .data_i     ( data_i     ),
        .read_data  ( down_data  ),
        .empty      ( fifo_empty )
    );

endmodule

custom_fifo/testbench.sv
`timescale 1ns/1ps

module testbench;
    // Подключение
    localparam WIDTH = 8; // fifo width
    localparam DEPTH = 4;  // fifo depth

    logic                clk;
    logic                arstn;
    logic                up_valid;    // upstream
    logic               up_ready;
    logic [DEPTH-1:0][WIDTH - 1:0] data_i;  // Эллементы буфера
    logic               down_valid;  // downstream
    logic                down_ready;
    logic [WIDTH - 1:0] down_data;

    custom_fifo_valid_ready #(
        .WIDTH  (WIDTH),
        .DEPTH  (DEPTH)
    ) node (
        .clk           (clk   ),
        .arstn         (arstn ),

        .up_valid      (up_valid),
        .up_ready      (up_ready),
        .data_i        (data_i ),

        .down_valid    (down_valid),
        .down_ready    (down_ready),
        .down_data     (down_data)
    );

    initial begin
        $dumpfile("test.vcd");
        $dumpvars;
    end
    // Запись значений в веса

    // Генерация clk
    parameter CLK_PERIOD = 20; // 50 МГц
    initial begin
        clk <= 0;
        forever begin
            #(CLK_PERIOD / 2); clk <= ~clk;
        end
    end

    //Генерация rst
    initial begin
        arstn <= 0;
        @(posedge clk);
        @(posedge clk);
        @(posedge clk);
        arstn <= 1;
    end

    // Генерация входных сигналов
    initial begin
        up_valid   <= 'b0;
        down_ready <= 'b1;

        wait(arstn);
        @(posedge clk);
    //---------------------------------------------------------------------------------------------
        //1
        @(posedge clk);
        up_valid <= 'b1;
        data_i[0] <= 'd1;
        data_i[1] <= 'd2;
        data_i[2] <= 'd3;
        data_i[3] <= 'd4;
        
        @(posedge clk);
        @(posedge clk);
        @(posedge clk);
        @(posedge clk);
        @(posedge clk);
        @(posedge clk);
        @(posedge clk);

        @(posedge clk);
        @(posedge clk);
        @(posedge clk);
        @(posedge clk);
        @(posedge clk);
        @(posedge clk);
        @(posedge clk);

        @(posedge clk);
        @(posedge clk);
        @(posedge clk);
        @(posedge clk);
        @(posedge clk);
        @(posedge clk);
        @(posedge clk);

        $finish;
    end
    
    // Проверка
    // initial begin
    //     wait(~arstn);
    //     @(posedge clk);
    //     @(posedge clk);
    // //---------------------------------------------------------------------------------------------
    //     repeat (32)
    //     begin
    //         @(posedge clk);
    //         if ($signed(psumm_o) != ($signed(psumm_i) + $signed(weight_i) * $signed(x_i) )) begin
    //             $display($signed(psumm_o));
    //             $display(($signed(psumm_i) + $signed(weight_i) * $signed(x_i)));
    //             $display($signed(psumm_i));
    //             $display($signed(weight_i));
    //             $display($signed(x_i));
    //             $error("BAD");
    //         end
    //         else begin
    //             $display("PASS");
    //             // $display($signed(psumm_o));
    //             // $display($signed(psumm_i));
    //             // $display($signed(weight_i));
    //             // $display($signed(x_i));
    //         end
    //     end
    // //---------------------------------------------------------------------------------------------
    //     @(posedge clk);
    //     @(posedge clk);
    //     @(posedge clk);
    //     $finish;
    // end
endmodule

test.vcd
$date
	Sun Mar 02 16:34:34 2025
$end
$version
	Icarus Verilog
$end
$timescale
	1ps
$end
$scope module testbench $end
$var wire 1 ! up_ready $end
$var wire 1 " down_valid $end
$var wire 8 # down_data [7:0] $end
$var reg 1 $ arstn $end
$var reg 1 % clk $end
$var reg 32 & data_i [31:0] $end
$var reg 1 ' down_ready $end
$var reg 1 ( up_valid $end
$scope module node $end
$var wire 1 $ arstn $end
$var wire 1 % clk $end
$var wire 32 ) data_i [31:0] $end
$var wire 1 ' down_ready $end
$var wire 1 " down_valid $end
$var wire 1 * pop $end
$var wire 1 ! up_ready $end
$var wire 1 ( up_valid $end
$var wire 1 + valid_i $end
$var wire 1 , fifo_empty $end
$var wire 8 - down_data [7:0] $end
$scope module fifo $end
$var wire 1 $ arstn $end
$var wire 1 % clk $end
$var wire 32 . data_i [31:0] $end
$var wire 1 , empty $end
$var wire 1 * pop $end
$var wire 1 + valid_i $end
$var wire 8 / read_data [7:0] $end
$var wire 1 0 equal_ptrs $end
$var reg 32 1 data [31:0] $end
$var reg 2 2 rd_ptr [1:0] $end
$var reg 1 3 rd_ptr_odd_circle $end
$var reg 2 4 wr_ptr [1:0] $end
$var reg 1 5 wr_ptr_odd_circle $end
$upscope $end
$upscope $end
$upscope $end
$enddefinitions $end
#0
$dumpvars
05
b0 4
03
b0 2
bx 1
10
bx /
bx .
bx -
1,
0+
0*
bx )
0(
1'
bx &
0%
0$
bx #
0"
1!
$end
#10000
1%
#20000
0%
#30000
1%
#40000
0%
#50000
1$
1%
#60000
0%
#70000
1%
#80000
0%
#90000
1+
b100000000110000001000000001 &
b100000000110000001000000001 )
b100000000110000001000000001 .
1(
1%
#100000
0%
#110000
1*
1"
0+
0!
0,
b1 #
b1 -
b1 /
b100000000110000001000000001 1
15
1%
#120000
0%
#130000
b10 #
b10 -
b10 /
00
b1 2
1%
#140000
0%
#150000
b11 #
b11 -
b11 /
b10 2
1%
#160000
0%
#170000
b100 #
b100 -
b100 /
b11 2
1%
#180000
0%
#190000
0*
0"
1+
1!
1,
13
b1 #
b1 -
b1 /
10
b0 2
1%
#200000
0%
#210000
1*
1"
0+
0!
0,
05
1%
#220000
0%
#230000
b10 #
b10 -
b10 /
00
b1 2
1%
#240000
0%
#250000
b11 #
b11 -
b11 /
b10 2
1%
#260000
0%
#270000
b100 #
b100 -
b100 /
b11 2
1%
#280000
0%
#290000
0*
0"
1+
1!
1,
03
b1 #
b1 -
b1 /
10
b0 2
1%
#300000
0%
#310000
1*
1"
0+
0!
0,
15
1%
#320000
0%
#330000
b10 #
b10 -
b10 /
00
b1 2
1%
#340000
0%
#350000
b11 #
b11 -
b11 /
b10 2
1%
#360000
0%
#370000
b100 #
b100 -
b100 /
b11 2
1%
#380000
0%
#390000
0*
0"
1+
1!
1,
13
b1 #
b1 -
b1 /
10
b0 2
1%
#400000
0%
#410000
1*
1"
0+
0!
0,
05
1%
#420000
0%
#430000
b10 #
b10 -
b10 /
00
b1 2
1%
#440000
0%
#450000
b11 #
b11 -
b11 /
b10 2
1%
#460000
0%
#470000
b100 #
b100 -
b100 /
b11 2
1%
#480000
0%
#490000
0*
0"
1+
1!
1,
03
b1 #
b1 -
b1 /
10
b0 2
1%
#500000
0%
#510000
1*
1"
0+
0!
0,
15
1%
