fft/syst_node/syst_node.sv
module syst_node
#(
    parameter W_WIDTH  = 16,
    parameter X_WIDTH  = 16,
    parameter SI_WIDTH = 32,
    parameter SO_WIDTH = 32
)
(
    input  logic                       clk,
    input  logic                       rstn,
    input  logic                       enable,
    input  logic signed [W_WIDTH -1:0] weight_i,

    input  logic signed [SI_WIDTH-1:0] psumm_i,
    input  logic                       valid_psumm_i,

    input  logic signed [X_WIDTH -1:0] x_i,
    input  logic                       valid_x_i,

    output logic signed [SO_WIDTH-1:0] psumm_o,
    output logic                       valid_o,

    output logic signed [X_WIDTH -1:0] x_o,
    output logic                       valid_x_o
);

    logic signed [SO_WIDTH       -1:0] psumm_reg;
    logic signed [X_WIDTH+W_WIDTH-1:0] weight_mult;

    logic valid_o_logic;
    assign valid_o_logic = valid_x_i & valid_psumm_i;

    // Расчёт результата
    logic en;
    assign en = enable & valid_o_logic;
    assign weight_mult = x_i * weight_i;
    logic signed [SO_WIDTH - 1:0] psumm_o_logic;
    assign psumm_o_logic = psumm_i + weight_mult;
    always_ff @(posedge clk) begin
        if (~rstn)   psumm_reg <= weight_mult;
        else if (en) psumm_reg <= psumm_o_logic;
    end

    // Расчёт валидности
    always_ff @(posedge clk) begin
        if (~rstn)       valid_o <= 'b0;
        else if (enable) valid_o <= valid_o_logic;
    end

    assign psumm_o = psumm_reg;
    assign valid_x_o = valid_x_i;
    assign x_o = x_i;

endmodule

fft/serial_fft_coral/serial_fft_coral.sv
`include ".\syst_node\syst_node.sv"

module serial_fft_coral
#(
    parameter W_WIDTH  = 16,
    parameter X_WIDTH  = 16,
    parameter S_WIDTH  = 32,

    parameter FRAME_LENGTH = 3,
    parameter CHANELS = 2
)
(
    input  logic                                       clk,
    input  logic                                       rstn,

    output logic [$clog2(FRAME_LENGTH) - 1:0] counter,
    input logic signed [W_WIDTH-1:0] w_re,
    input logic signed [W_WIDTH-1:0] w_im,

    input  logic                                       valid_i,
    input  logic signed [CHANELS-1:0][X_WIDTH-1:0]     x,
    
    output logic signed [CHANELS-1:0] [S_WIDTH-1:0]    re,
    output logic signed [CHANELS-1:0] [S_WIDTH-1:0]    im,
    output logic signed                                valid_o
);
    //------------------------------------------------------------------------

    //------------------------------------------------------------------------

    // Счётчик для мультиплексирования
    logic counter_enable;
    assign counter_enable = counter == (FRAME_LENGTH - 1);
    always_ff @ (posedge clk)
        if (!rstn)
        begin
            counter <= 'b0;
            valid_o <= 'b0;
        end
        else if (valid_i)
        begin
            if (counter_enable)
            begin
                counter <= '0;
                valid_o <= 'b1;
            end
            else
            begin
                counter <= counter + 1'b1;
                valid_o <= 'b0;
            end
        end
    
    logic reset_node;
    assign reset_node = |counter;

    //------------------------------------------------------------------------
    // RE
    genvar i;
    generate
        for (i = 0; i<CHANELS; i++) begin : RE
            logic signed [S_WIDTH-1:0] psumm_i_re;
            logic                valid_psumm_i_re;

            logic signed [S_WIDTH-1:0] psumm_o_re;
            logic                valid_psumm_o_re;

            assign valid_psumm_i_re = 'b1;

            syst_node #(
                .W_WIDTH  (W_WIDTH),
                .X_WIDTH  (X_WIDTH),
                .SI_WIDTH (S_WIDTH),
                .SO_WIDTH (S_WIDTH)
            ) re_node1 (
                .clk           (clk),
                .rstn          (reset_node),
                .enable        (valid_i),
                .weight_i      (w_re),

                .psumm_i       (psumm_o_re),
                .valid_psumm_i (valid_psumm_i_re),

                .x_i           (x[i]),
                .valid_x_i     (valid_i),

                .psumm_o       (psumm_o_re),
                .valid_o       (valid_psumm_o_re)
            );
            assign re[i] = psumm_o_re;
        end
    endgenerate

    //------------------------------------------------------------------------

    // IM
    genvar j;
    generate
        for (j = 0; j<CHANELS; j++) begin : IM
            logic signed [S_WIDTH-1:0] psumm_i_im;
            logic                valid_psumm_i_im;

            logic signed [S_WIDTH-1:0] psumm_o_im;
            logic                valid_psumm_o_im;

            assign valid_psumm_i_im = 'b1;

            syst_node #(
                .W_WIDTH  (W_WIDTH),
                .X_WIDTH  (X_WIDTH),
                .SI_WIDTH (S_WIDTH),
                .SO_WIDTH (S_WIDTH)
            ) im_node1 (
                .clk           (clk),
                .rstn          (reset_node),
                .enable        (valid_i),
                .weight_i      (w_im),

                .psumm_i       (psumm_o_im),
                .valid_psumm_i (valid_psumm_i_im),

                .x_i           (x[j]),
                .valid_x_i     (valid_i),

                .psumm_o       (psumm_o_im),
                .valid_o       (valid_psumm_o_im)
            );
            assign im[j] = psumm_o_im;
        end
    endgenerate

endmodule

fft/RAM_fft/RAM_w_im.sv
module RAM_w_im
#(
    parameter WIDTH = 32,
    parameter DEPTH = 360
)
(
    input                        clk,         
    input                        write_enable,
    input [$clog2 (DEPTH) - 1:0] address,     
    input [WIDTH-1:0]            data_in,     
    output [WIDTH-1:0]           data_out
);

  reg [WIDTH-1:0] w_im [0:DEPTH-1];          // here is the array; make this the size you need
  initial $readmemb(".\\weigths\\w_im.txt", w_im);

  always @(posedge clk)
    if (write_enable)
      w_im[address] <= data_in;

  assign data_out = w_im[address];

endmodule

fft/RAM_fft/RAM_w_re.sv
module RAM_w_re
#(
    parameter WIDTH = 32,
    parameter DEPTH = 360
)
(
    input        clk,            // best to make it synchronous
    input        write_enable,     // a simple active high write enable
    input [$clog2 (DEPTH) - 1:0]  address,          // a single address bus in this example
    input [WIDTH-1:0]  data_in,          // input data
    output [WIDTH-1:0] data_out
);        // output data

  logic [WIDTH-1:0] w_re [0:DEPTH-1];          // here is the array; make this the size you need
  initial $readmemb(".\\weigths\\w_re.txt", w_re);

  always @(posedge clk)
    if (write_enable)
      w_re[address] <= data_in;

  assign data_out = w_re[address];

endmodule

fft/serial_fft_coral/testbench.sv
`timescale 1ns/1ps
`include ".\RAM_fft\RAM_w_re.sv"
`include ".\RAM_fft\RAM_w_im.sv"

module a
#(
    parameter W_WIDTH  = 16,
    parameter X_WIDTH  = 16,
    parameter S_WIDTH  = 32,

    parameter FRAME_LENGTH = 10,
    parameter CHANELS = 2
)
(
    input  logic                                       clk,
    input  logic                                       arstn,

    input  logic                                       valid_i,
    input  logic signed [CHANELS-1:0] [X_WIDTH-1:0]    x,
    
    output logic signed [CHANELS-1:0][S_WIDTH-1:0]                  re,
    output logic signed [CHANELS-1:0][S_WIDTH-1:0]                  im,
    output logic signed                                valid_o
);
    logic signed [W_WIDTH-1:0] w_re;
    logic signed [W_WIDTH-1:0] w_im;
    logic [$clog2(FRAME_LENGTH) - 1:0]  counter;

    RAM_w_re
    #(
        .WIDTH(W_WIDTH),
        .DEPTH(FRAME_LENGTH)
    ) ram1 (
        .clk(clk),
        .address (counter),
        .data_out (w_re)
    );

    RAM_w_im
    #(
        .WIDTH(W_WIDTH),
        .DEPTH(FRAME_LENGTH)
    ) ram2 (
        .clk(clk),
        .address (counter),
        .data_out (w_im)
    );
    
    serial_fft_coral #(
        .W_WIDTH  (W_WIDTH),
        .X_WIDTH  (X_WIDTH),
        .S_WIDTH  (S_WIDTH),
        .FRAME_LENGTH (FRAME_LENGTH)
    ) core (
        .clk           (clk   ),
        .rstn         (arstn ),

        .counter (counter),
        .w_re          (w_re  ),
        .w_im          (w_im  ),

        .valid_i       (valid_i),
        .x            (x      ),

        .re            (re),
        .im            (im),
        .valid_o       (valid_o)
    );
endmodule

module testbench;
    // Подключение
    localparam W_WIDTH  = 16;
    localparam X_WIDTH  = 16;
    localparam S_WIDTH  = 32;
    localparam FRAME_LENGTH = 4;
    localparam CHANELS = 2;

    logic                                        clk;
    logic                                        arstn;

    logic                                        valid_i;
    logic signed [CHANELS-1:0][X_WIDTH-1:0]      x;
    logic signed [X_WIDTH-1:0]                   x1;
    logic signed [X_WIDTH-1:0]                   x2;
    assign x = {x2, x1};

    logic signed [CHANELS-1:0][S_WIDTH-1:0]      re;
    logic signed [S_WIDTH-1:0] re1;
    logic signed [CHANELS-1:0][S_WIDTH-1:0]      im;
    logic signed [S_WIDTH-1:0] im1;
    logic                                        valid_o;
    assign re1 = re[0];
    assign im1 = im[0];

    a #(
        .W_WIDTH  (W_WIDTH),
        .X_WIDTH  (X_WIDTH),
        .S_WIDTH  (S_WIDTH),
        .FRAME_LENGTH (FRAME_LENGTH),
        .CHANELS (CHANELS)
    ) test (
        .clk           (clk   ),
        .arstn         (arstn ),

        .valid_i       (valid_i),
        .x            (x     ),

        .re            (re),
        .im            (im),
        .valid_o       (valid_o)
    );

    initial begin
        $dumpfile("serial_fft_coral.vcd");
        $dumpvars;
    end
    // Запись значений в веса

    // Генерация clk
    parameter CLK_PERIOD = 20; // 50 МГц
    initial begin
        clk <= 0;
        forever begin
            #(CLK_PERIOD / 2); clk <= ~clk;
        end
    end

    //Генерация rst
    initial begin
        arstn <= 0;
        @(posedge clk);
        @(posedge clk);
        @(posedge clk);
        arstn <= 1;
    end

    // Генерация входных сигналов
    initial begin
        valid_i <= 'b0;

        wait(arstn);
        @(posedge clk);
    //---------------------------------------------------------------------------------------------
        //1
        @(posedge clk);
        valid_i <= 'b1;
        x1 <= 'd1;
        x2 <= 'd2;

        @(posedge clk);
        x1 <= 'd3;
        x2 <= 'd4;

        @(posedge clk);
        x1 <= 'd5;
        x2 <= 'd6;

        @(posedge clk);
        x1 <= 'd7;
        x2 <= 'd8;

        @(posedge clk);
        @(posedge clk);
        @(posedge clk);
        @(posedge clk);
        @(posedge clk);

        $finish;
    end
    
    // Проверка
    // initial begin
    //     wait(~arstn);
    //     @(posedge clk);
    //     @(posedge clk);
    // //---------------------------------------------------------------------------------------------
    //     repeat (32)
    //     begin
    //         @(posedge clk);
    //         if ($signed(psumm_o) != ($signed(psumm_i) + $signed(weight_i) * $signed(x_i) )) begin
    //             $display($signed(psumm_o));
    //             $display(($signed(psumm_i) + $signed(weight_i) * $signed(x_i)));
    //             $display($signed(psumm_i));
    //             $display($signed(weight_i));
    //             $display($signed(x_i));
    //             $error("BAD");
    //         end
    //         else begin
    //             $display("PASS");
    //             // $display($signed(psumm_o));
    //             // $display($signed(psumm_i));
    //             // $display($signed(weight_i));
    //             // $display($signed(x_i));
    //         end
    //     end
    // //---------------------------------------------------------------------------------------------
    //     @(posedge clk);
    //     @(posedge clk);
    //     @(posedge clk);
    //     $finish;
    // end
endmodule

fft/serial_fft_coral.vcd
$date
	Mon Mar 24 20:00:25 2025
$end
$version
	Icarus Verilog
$end
$timescale
	1ps
$end
$scope module testbench $end
$var wire 32 ! x [31:0] $end
$var wire 1 " valid_o $end
$var wire 32 # re1 [31:0] $end
$var wire 64 $ re [63:0] $end
$var wire 32 % im1 [31:0] $end
$var wire 64 & im [63:0] $end
$var reg 1 ' arstn $end
$var reg 1 ( clk $end
$var reg 1 ) valid_i $end
$var reg 16 * x1 [15:0] $end
$var reg 16 + x2 [15:0] $end
$scope module test $end
$var wire 1 ' arstn $end
$var wire 1 ( clk $end
$var wire 1 ) valid_i $end
$var wire 32 , x [31:0] $end
$var wire 16 - w_re [15:0] $end
$var wire 16 . w_im [15:0] $end
$var wire 1 " valid_o $end
$var wire 64 / re [63:0] $end
$var wire 64 0 im [63:0] $end
$var wire 2 1 counter [1:0] $end
$scope module core $end
$var wire 1 ( clk $end
$var wire 1 ' rstn $end
$var wire 1 ) valid_i $end
$var wire 32 2 x [31:0] $end
$var wire 16 3 w_re [15:0] $end
$var wire 16 4 w_im [15:0] $end
$var wire 1 5 reset_node $end
$var wire 64 6 re [63:0] $end
$var wire 64 7 im [63:0] $end
$var wire 1 8 counter_enable $end
$var reg 2 9 counter [1:0] $end
$var reg 1 " valid_o $end
$scope begin IM[0] $end
$var wire 1 : valid_psumm_i_im $end
$var wire 1 ; valid_psumm_o_im $end
$var wire 32 < psumm_o_im [31:0] $end
$scope module im_node1 $end
$var wire 1 ( clk $end
$var wire 1 = en $end
$var wire 1 ) enable $end
$var wire 1 5 rstn $end
$var wire 1 > valid_o_logic $end
$var wire 1 : valid_psumm_i $end
$var wire 1 ) valid_x_i $end
$var wire 1 ? valid_x_o $end
$var wire 16 @ x_i [15:0] $end
$var wire 16 A x_o [15:0] $end
$var wire 32 B weight_mult [31:0] $end
$var wire 16 C weight_i [15:0] $end
$var wire 32 D psumm_o_logic [31:0] $end
$var wire 32 E psumm_o [31:0] $end
$var wire 32 F psumm_i [31:0] $end
$var reg 32 G psumm_reg [31:0] $end
$var reg 1 ; valid_o $end
$upscope $end
$upscope $end
$scope begin IM[1] $end
$var wire 1 H valid_psumm_i_im $end
$var wire 1 I valid_psumm_o_im $end
$var wire 32 J psumm_o_im [31:0] $end
$scope module im_node1 $end
$var wire 1 ( clk $end
$var wire 1 K en $end
$var wire 1 ) enable $end
$var wire 1 5 rstn $end
$var wire 1 L valid_o_logic $end
$var wire 1 H valid_psumm_i $end
$var wire 1 ) valid_x_i $end
$var wire 1 M valid_x_o $end
$var wire 16 N x_i [15:0] $end
$var wire 16 O x_o [15:0] $end
$var wire 32 P weight_mult [31:0] $end
$var wire 16 Q weight_i [15:0] $end
$var wire 32 R psumm_o_logic [31:0] $end
$var wire 32 S psumm_o [31:0] $end
$var wire 32 T psumm_i [31:0] $end
$var reg 32 U psumm_reg [31:0] $end
$var reg 1 I valid_o $end
$upscope $end
$upscope $end
$scope begin RE[0] $end
$var wire 1 V valid_psumm_i_re $end
$var wire 1 W valid_psumm_o_re $end
$var wire 32 X psumm_o_re [31:0] $end
$scope module re_node1 $end
$var wire 1 ( clk $end
$var wire 1 Y en $end
$var wire 1 ) enable $end
$var wire 1 5 rstn $end
$var wire 1 Z valid_o_logic $end
$var wire 1 V valid_psumm_i $end
$var wire 1 ) valid_x_i $end
$var wire 1 [ valid_x_o $end
$var wire 16 \ x_i [15:0] $end
$var wire 16 ] x_o [15:0] $end
$var wire 32 ^ weight_mult [31:0] $end
$var wire 16 _ weight_i [15:0] $end
$var wire 32 ` psumm_o_logic [31:0] $end
$var wire 32 a psumm_o [31:0] $end
$var wire 32 b psumm_i [31:0] $end
$var reg 32 c psumm_reg [31:0] $end
$var reg 1 W valid_o $end
$upscope $end
$upscope $end
$scope begin RE[1] $end
$var wire 1 d valid_psumm_i_re $end
$var wire 1 e valid_psumm_o_re $end
$var wire 32 f psumm_o_re [31:0] $end
$scope module re_node1 $end
$var wire 1 ( clk $end
$var wire 1 g en $end
$var wire 1 ) enable $end
$var wire 1 5 rstn $end
$var wire 1 h valid_o_logic $end
$var wire 1 d valid_psumm_i $end
$var wire 1 ) valid_x_i $end
$var wire 1 i valid_x_o $end
$var wire 16 j x_i [15:0] $end
$var wire 16 k x_o [15:0] $end
$var wire 32 l weight_mult [31:0] $end
$var wire 16 m weight_i [15:0] $end
$var wire 32 n psumm_o_logic [31:0] $end
$var wire 32 o psumm_o [31:0] $end
$var wire 32 p psumm_i [31:0] $end
$var reg 32 q psumm_reg [31:0] $end
$var reg 1 e valid_o $end
$upscope $end
$upscope $end
$upscope $end
$scope module ram1 $end
$var wire 2 r address [1:0] $end
$var wire 1 ( clk $end
$var wire 16 s data_in [15:0] $end
$var wire 16 t data_out [15:0] $end
$var wire 1 u write_enable $end
$upscope $end
$scope module ram2 $end
$var wire 2 v address [1:0] $end
$var wire 1 ( clk $end
$var wire 16 w data_in [15:0] $end
$var wire 16 x data_out [15:0] $end
$var wire 1 y write_enable $end
$upscope $end
$upscope $end
$upscope $end
$enddefinitions $end
#0
$dumpvars
zy
bx x
bz w
bx v
zu
bx t
bz s
bx r
bx q
bx p
bx o
bx n
bx m
bx l
bx k
bx j
0i
0h
0g
bx f
xe
1d
bx c
bx b
bx a
bx `
bx _
bx ^
bx ]
bx \
0[
0Z
0Y
bx X
xW
1V
bx U
bx T
bx S
bx R
bx Q
bx P
bx O
bx N
0M
0L
0K
bx J
xI
1H
bx G
bx F
bx E
bx D
bx C
bx B
bx A
bx @
0?
0>
0=
bx <
x;
1:
bx 9
x8
bx 7
bx 6
x5
bx 4
bx 3
bx 2
bx 1
bx 0
bx /
bx .
bx -
bx ,
bx +
bx *
0)
0(
0'
bx &
bx %
bx $
bx #
x"
bx !
$end
#10000
0"
08
05
b10000000000 -
b10000000000 3
b10000000000 _
b10000000000 m
b10000000000 t
b0 .
b0 4
b0 C
b0 Q
b0 x
b0 1
b0 9
b0 r
b0 v
1(
#20000
0(
#30000
0I
0;
0e
0W
1(
#40000
0(
#50000
1'
1(
#60000
0(
#70000
1(
#80000
0(
#90000
1=
1K
1Y
1g
b10 k
b100000000000 l
b10 j
b10 O
b0 P
b10 N
b1 ]
b10000000000 ^
b1 \
b1 A
b0 B
b1 @
1>
1L
1Z
1h
b10 +
b100000000000000001 !
b100000000000000001 ,
b100000000000000001 2
b1 *
1?
1M
1[
1i
1)
1(
#100000
0(
#110000
b0 %
b10000000000 #
b100 k
b100 j
b100 O
b100 N
b11 ]
b11 \
b11 A
b11 @
15
b111111111000 l
b101111111010 ^
b1111111110 -
b1111111110 3
b1111111110 _
b1111111110 m
b1111111110 t
b100011100 P
b11010101 B
b1000111 .
b1000111 4
b1000111 C
b1000111 Q
b1000111 x
b1 1
b1 9
b1 r
b1 v
b100011100 R
b0 J
b0 S
b0 T
b0 U
b11010101 D
b0 &
b0 0
b0 7
b0 <
b0 E
b0 F
b0 G
b1011111111000 n
b100000000000 f
b100000000000 o
b100000000000 p
b100000000000 q
b111111111010 `
b10000000000000000000000000000000010000000000 $
b10000000000000000000000000000000010000000000 /
b10000000000000000000000000000000010000000000 6
b10000000000 X
b10000000000 a
b10000000000 b
b10000000000 c
b100 +
b1000000000000000011 !
b1000000000000000011 ,
b1000000000000000011 2
b11 *
1(
#120000
0(
#130000
b110 k
b110 j
b110 O
b110 N
b101 ]
b101 \
b101 A
b101 @
b111111111010 #
b11010101 %
b110 +
b1100000000000000101 !
b1100000000000000101 ,
b1100000000000000101 2
b101 *
b111111111010 X
b111111111010 a
b111111111010 b
b111111111010 c
1W
b101111111100000000000000000000000111111111010 $
b101111111100000000000000000000000111111111010 /
b101111111100000000000000000000000111111111010 6
b1011111111000 f
b1011111111000 o
b1011111111000 p
b1011111111000 q
1e
b11010101 <
b11010101 E
b11010101 F
b11010101 G
1;
b10001110000000000000000000000000011010101 &
b10001110000000000000000000000000011010101 0
b10001110000000000000000000000000011010101 7
b100011100 J
b100011100 S
b100011100 T
b100011100 U
1I
b10111110111100 n
b1011111000100 l
b10001111001000 `
b1001111001110 ^
b1111110110 -
b1111110110 3
b1111110110 _
b1111110110 m
b1111110110 t
b10001110110 R
b1101011010 P
b1110100000 D
b1011001011 B
b10001111 .
b10001111 4
b10001111 C
b10001111 Q
b10001111 x
b10 1
b10 9
b10 r
b10 v
1(
#140000
0(
#150000
b1110100000 %
b10001111001000 #
b1000 k
b1000 j
b1000 O
b1000 N
b111 ]
b111 \
b111 A
b111 @
18
b1111101010000 l
b1101101100110 ^
b1111101010 -
b1111101010 3
b1111101010 _
b1111101010 m
b1111101010 t
b11010101000 P
b10111010011 B
b11010101 .
b11010101 4
b11010101 C
b11010101 Q
b11010101 x
b11 1
b11 9
b11 r
b11 v
b101100011110 R
b10001110110 J
b10001110110 S
b10001110110 T
b10001110110 U
b100101110011 D
b1000111011000000000000000000000001110100000 &
b1000111011000000000000000000000001110100000 0
b1000111011000000000000000000000001110100000 7
b1110100000 <
b1110100000 E
b1110100000 F
b1110100000 G
b100111100001100 n
b10111110111100 f
b10111110111100 o
b10111110111100 p
b10111110111100 q
b11111100101110 `
b1011111011110000000000000000000010001111001000 $
b1011111011110000000000000000000010001111001000 /
b1011111011110000000000000000000010001111001000 6
b10001111001000 X
b10001111001000 a
b10001111001000 b
b10001111001000 c
b1000 +
b10000000000000000111 !
b10000000000000000111 ,
b10000000000000000111 2
b111 *
1(
#160000
0(
#170000
b11111100101110 #
b100101110011 %
b11111100101110 X
b11111100101110 a
b11111100101110 b
b11111100101110 c
b10011110000110000000000000000000011111100101110 $
b10011110000110000000000000000000011111100101110 /
b10011110000110000000000000000000011111100101110 6
b100111100001100 f
b100111100001100 o
b100111100001100 p
b100111100001100 q
b100101110011 <
b100101110011 E
b100101110011 F
b100101110011 G
b10110001111000000000000000000000100101110011 &
b10110001111000000000000000000000100101110011 0
b10110001111000000000000000000000100101110011 7
b101100011110 J
b101100011110 S
b101100011110 T
b101100011110 U
1"
08
05
b110111100001100 n
b10000000000000 l
b101101100101110 `
b1110000000000 ^
b10000000000 -
b10000000000 3
b10000000000 _
b10000000000 m
b10000000000 t
b101100011110 R
b0 P
b100101110011 D
b0 B
b0 .
b0 4
b0 C
b0 Q
b0 x
b0 1
b0 9
b0 r
b0 v
1(
#180000
0(
#190000
b0 %
b1110000000000 #
0"
15
b1111111110000 l
b1101111110010 ^
b1111111110 -
b1111111110 3
b1111111110 _
b1111111110 m
b1111111110 t
b1000111000 P
b111110001 B
b1000111 .
b1000111 4
b1000111 C
b1000111 Q
b1000111 x
b1 1
b1 9
b1 r
b1 v
0I
b1000111000 R
b0 J
b0 S
b0 T
b0 U
0;
b111110001 D
b0 &
b0 0
b0 7
b0 <
b0 E
b0 F
b0 G
0e
b11111111110000 n
b10000000000000 f
b10000000000000 o
b10000000000000 p
b10000000000000 q
0W
b11011111110010 `
b1000000000000000000000000000000001110000000000 $
b1000000000000000000000000000000001110000000000 /
b1000000000000000000000000000000001110000000000 6
b1110000000000 X
b1110000000000 a
b1110000000000 b
b1110000000000 c
1(
#200000
0(
#210000
b11011111110010 #
b111110001 %
b11011111110010 X
b11011111110010 a
b11011111110010 b
b11011111110010 c
1W
b1111111111000000000000000000000011011111110010 $
b1111111111000000000000000000000011011111110010 /
b1111111111000000000000000000000011011111110010 6
b11111111110000 f
b11111111110000 o
b11111111110000 p
b11111111110000 q
1e
b111110001 <
b111110001 E
b111110001 F
b111110001 G
1;
b100011100000000000000000000000000111110001 &
b100011100000000000000000000000000111110001 0
b100011100000000000000000000000000111110001 7
b1000111000 J
b1000111000 S
b1000111000 T
b1000111000 U
1I
b101111110100000 n
b1111110110000 l
b101001110101100 `
b1101110111010 ^
b1111110110 -
b1111110110 3
b1111110110 _
b1111110110 m
b1111110110 t
b11010110000 R
b10001111000 P
b10111011010 D
b1111101001 B
b10001111 .
b10001111 4
b10001111 C
b10001111 Q
b10001111 x
b10 1
b10 9
b10 r
b10 v
1(
#220000
0(
#230000
b10111011010 %
b101001110101100 #
18
b1111101010000 l
b1101101100110 ^
b1111101010 -
b1111101010 3
b1111101010 _
b1111101010 m
b1111101010 t
b11010101000 P
b10111010011 B
b11010101 .
b11010101 4
b11010101 C
b11010101 Q
b11010101 x
b11 1
b11 9
b11 r
b11 v
b110101011000 R
b11010110000 J
b11010110000 S
b11010110000 T
b11010110000 U
b101110101101 D
b1101011000000000000000000000000010111011010 &
b1101011000000000000000000000000010111011010 0
b1101011000000000000000000000000010111011010 7
b10111011010 <
b10111011010 E
b10111011010 F
b10111011010 G
b111111011110000 n
b101111110100000 f
b101111110100000 o
b101111110100000 p
b101111110100000 q
b110111100010010 `
b10111111010000000000000000000000101001110101100 $
b10111111010000000000000000000000101001110101100 /
b10111111010000000000000000000000101001110101100 6
b101001110101100 X
b101001110101100 a
b101001110101100 b
b101001110101100 c
1(
#240000
0(
#250000
b110111100010010 #
b101110101101 %
b110111100010010 X
b110111100010010 a
b110111100010010 b
b110111100010010 c
b11111101111000000000000000000000110111100010010 $
b11111101111000000000000000000000110111100010010 /
b11111101111000000000000000000000110111100010010 6
b111111011110000 f
b111111011110000 o
b111111011110000 p
b111111011110000 q
b101110101101 <
b101110101101 E
b101110101101 F
b101110101101 G
b11010101100000000000000000000000101110101101 &
b11010101100000000000000000000000101110101101 0
b11010101100000000000000000000000101110101101 7
b110101011000 J
b110101011000 S
b110101011000 T
b110101011000 U
1"
08
05
b1001111011110000 n
b10000000000000 l
b1000101100010010 `
b1110000000000 ^
b10000000000 -
b10000000000 3
b10000000000 _
b10000000000 m
b10000000000 t
b110101011000 R
b0 P
b101110101101 D
b0 B
b0 .
b0 4
b0 C
b0 Q
b0 x
b0 1
b0 9
b0 r
b0 v
1(
