fft/syst_node/syst_node.sv
module syst_node
#(
    parameter W_WIDTH  = 16,
    parameter X_WIDTH  = 16,
    parameter SI_WIDTH = 32,
    parameter SO_WIDTH = 32
)
(
    input  logic                       clk,
    input  logic                       arstn,
    input  logic                       enable,
    input  logic signed [W_WIDTH -1:0] weight_i,

    input  logic signed [SI_WIDTH-1:0] psumm_i,
    input  logic                       valid_psumm_i,

    input  logic signed [X_WIDTH -1:0] x_i,
    input  logic                       valid_x_i,

    output logic signed [SO_WIDTH-1:0] psumm_o,
    output logic                       valid_o,

    output logic signed [X_WIDTH -1:0] x_o,
    output logic                       valid_x_o
);

    logic signed [SO_WIDTH       -1:0] psumm_reg;
    logic signed [X_WIDTH+W_WIDTH-1:0] weight_mult;

    logic valid;
    assign valid = valid_x_i & valid_psumm_i;

    // Расчёт результата
    logic en;
    assign en = enable & valid;
    assign weight_mult = x_i * weight_i;
    always_ff @(posedge clk) begin
        if (en)
            psumm_reg <= psumm_i + weight_mult;
    end

    // Расчёт валидности
    always_ff @(posedge clk or negedge arstn) begin
        if (~arstn)
            valid_o <= '0;
        else
            if (enable)
                valid_o <= valid;
    end

    assign psumm_o = psumm_reg;
    assign valid_x_o = valid_x_i;
    assign x_o = x_i;

endmodule

fft/serial_fft_coral/serial_fft_coral.sv
`include ".\syst_node\syst_node.sv"

module serial_fft_coral
#(
    parameter W_WIDTH  = 16,
    parameter X_WIDTH  = 16,
    parameter S_WIDTH  = 32,

    parameter FRAME_LENGTH = 3
)
(
    input  logic                                       clk,
    input  logic                                       arstn,
    input logic signed [W_WIDTH-1:0] w_re [FRAME_LENGTH-1:0],
    input logic signed [W_WIDTH-1:0] w_im [FRAME_LENGTH-1:0],

    input  logic                                       valid_i,
    input  logic signed [X_WIDTH-1:0]                  x1,
    input  logic signed [X_WIDTH-1:0]                  x2,
    
    output logic signed [S_WIDTH-1:0]                  re1,
    output logic signed [S_WIDTH-1:0]                  im1,
    output logic signed [S_WIDTH-1:0]                  re2,
    output logic signed [S_WIDTH-1:0]                  im2,
    output logic signed                                valid_o
);
    //------------------------------------------------------------------------

    localparam pointer_width = $clog2 (FRAME_LENGTH);

    //------------------------------------------------------------------------

    // Счётчик для мультиплексирования
    logic [pointer_width - 1:0] counter;
    always_ff @ (posedge clk or negedge arstn)
        if (!arstn)
        begin
            counter <= 'b0;
            valid_o <= 'b0;
        end
        else if (valid_i)
        begin
            if (counter == (FRAME_LENGTH - 1))
            begin
                counter <= '0;
                valid_o <= 'b1;
            end
            else
            begin
                counter <= counter + 1'b1;
                valid_o <= 'b0;
            end
        end

    //------------------------------------------------------------------------

    // RE

    logic signed [S_WIDTH-1:0] psumm_i_re1;
    logic                valid_psumm_i_re1;

    logic signed [S_WIDTH-1:0] psumm_o_re1;
    logic                 valid_psumm_o_re1;

    assign psumm_i_re1       = (counter == 0) ? 'b0 : psumm_o_re1;
    assign valid_psumm_i_re1 = 'b1;

    logic signed [W_WIDTH-1:0] weight_re;
    assign weight_re = w_re[counter];

    syst_node #(
        .W_WIDTH  (W_WIDTH),
        .X_WIDTH  (X_WIDTH),
        .SI_WIDTH (S_WIDTH),
        .SO_WIDTH (S_WIDTH)
    ) re_node1 (
        .clk           (clk),
        .arstn         (arstn),
        .enable        (valid_i),
        .weight_i      (weight_re),

        .psumm_i       (psumm_i_re1),
        .valid_psumm_i (valid_psumm_i_re1),

        .x_i           (x1),
        .valid_x_i     (valid_i),

        .psumm_o       (psumm_o_re1),
        .valid_o       (valid_psumm_o_re1)
    );
    assign re1 = psumm_o_re1;

    //------------------------------------------------------------------------

    // IM

    logic signed [S_WIDTH-1:0] psumm_i_im1;
    logic                valid_psumm_i_im1;

    logic signed [S_WIDTH-1:0] psumm_o_im1;
    logic                 valid_psumm_o_im1;

    assign psumm_i_im1       = (counter == 0) ? 'b0 : psumm_o_im1;
    assign valid_psumm_i_im1 = 'b1;

    logic signed [W_WIDTH-1:0] weight_im;
    assign weight_im = w_im[counter];

    syst_node #(
        .W_WIDTH  (W_WIDTH),
        .X_WIDTH  (X_WIDTH),
        .SI_WIDTH (S_WIDTH),
        .SO_WIDTH (S_WIDTH)
    ) im_node1 (
        .clk           (clk),
        .arstn         (arstn),
        .enable        (valid_i),
        .weight_i      (weight_im),

        .psumm_i       (psumm_i_im1),
        .valid_psumm_i (valid_psumm_i_im1),

        .x_i           (x1),
        .valid_x_i     (valid_i),

        .psumm_o       (psumm_o_im1),
        .valid_o       (valid_psumm_o_im1)
    );
    assign im1 = psumm_o_im1;

    //------------------------------------------------------------------------

    // RE

    logic signed [S_WIDTH-1:0] psumm_i_re2;
    logic                valid_psumm_i_re2;

    logic signed [S_WIDTH-1:0] psumm_o_re2;
    logic                 valid_psumm_o_re2;

    assign psumm_i_re2       = (counter == 0) ? 'b0 : psumm_o_re2;
    assign valid_psumm_i_re2 = 'b1;

    syst_node #(
        .W_WIDTH  (W_WIDTH),
        .X_WIDTH  (X_WIDTH),
        .SI_WIDTH (S_WIDTH),
        .SO_WIDTH (S_WIDTH)
    ) re_node2 (
        .clk           (clk),
        .arstn         (arstn),
        .enable        (valid_i),
        .weight_i      (weight_re),

        .psumm_i       (psumm_i_re2),
        .valid_psumm_i (valid_psumm_i_re2),

        .x_i           (x2),
        .valid_x_i     (valid_i),

        .psumm_o       (psumm_o_re2),
        .valid_o       (valid_psumm_o_re2)
    );
    assign re2 = psumm_o_re2;

    //------------------------------------------------------------------------

    // IM

    logic signed [S_WIDTH-1:0] psumm_i_im2;
    logic                valid_psumm_i_im2;

    logic signed [S_WIDTH-1:0] psumm_o_im2;
    logic                 valid_psumm_o_im2;

    assign psumm_i_im2       = (counter == 0) ? 'b0 : psumm_o_im2;
    assign valid_psumm_i_im2 = 'b1;

    syst_node #(
        .W_WIDTH  (W_WIDTH),
        .X_WIDTH  (X_WIDTH),
        .SI_WIDTH (S_WIDTH),
        .SO_WIDTH (S_WIDTH)
    ) im_node2 (
        .clk           (clk),
        .arstn         (arstn),
        .enable        (valid_i),
        .weight_i      (weight_im),

        .psumm_i       (psumm_i_im2),
        .valid_psumm_i (valid_psumm_i_im2),

        .x_i           (x2),
        .valid_x_i     (valid_i),

        .psumm_o       (psumm_o_im2),
        .valid_o       (valid_psumm_o_im2)
    );
    assign im2 = psumm_o_im2;

    

endmodule

fft/serial_fft_coral/testbench.sv
`timescale 1ns/1ps

module a
#(
    parameter W_WIDTH  = 16,
    parameter X_WIDTH  = 16,
    parameter S_WIDTH  = 32,

    parameter FRAME_LENGTH = 10
)
(
    input  logic                                       clk,
    input  logic                                       arstn,

    input  logic                                       valid_i,
    input  logic signed [X_WIDTH-1:0]                  x1,
    input  logic signed [X_WIDTH-1:0]                  x2,
    
    output logic signed [S_WIDTH-1:0]                  re1,
    output logic signed [S_WIDTH-1:0]                  im1,
    output logic signed [S_WIDTH-1:0]                  re2,
    output logic signed [S_WIDTH-1:0]                  im2,
    output logic signed                                valid_o
);
    logic signed [W_WIDTH-1:0] w_re [FRAME_LENGTH-1:0];
    logic signed [W_WIDTH-1:0] w_im [FRAME_LENGTH-1:0];
    
    initial $readmemb(".\\weigths\\w_re.txt", w_re);
    initial $readmemb(".\\weigths\\w_im.txt", w_im);
    
    serial_fft_coral #(
        .W_WIDTH  (W_WIDTH),
        .X_WIDTH  (X_WIDTH),
        .S_WIDTH  (S_WIDTH),
        .FRAME_LENGTH (FRAME_LENGTH)
    ) node (
        .clk           (clk   ),
        .arstn         (arstn ),
        .w_re          (w_re  ),
        .w_im          (w_im  ),

        .valid_i       (valid_i),
        .x1            (x1      ),
        .x2            (x2),

        .re1            (re1),
        .im1            (im1),
        .re2            (re2),
        .im2            (im2),
        .valid_o       (valid_o)
    );
endmodule

module testbench;
    // Подключение
    localparam W_WIDTH  = 16;
    localparam X_WIDTH  = 16;
    localparam S_WIDTH  = 32;
    localparam FRAME_LENGTH = 4;

    logic                                        clk;
    logic                                        arstn;

    logic                                        valid_i;
    logic signed [X_WIDTH-1:0]                   x1;
    logic signed [X_WIDTH-1:0]                   x2;

    logic signed [S_WIDTH-1:0]                   re1;
    logic signed [S_WIDTH-1:0]                   im1;
    logic signed [S_WIDTH-1:0]                   re2;
    logic signed [S_WIDTH-1:0]                   im2;
    logic                                        valid_o;

    a #(
        .W_WIDTH  (W_WIDTH),
        .X_WIDTH  (X_WIDTH),
        .S_WIDTH  (S_WIDTH),
        .FRAME_LENGTH (FRAME_LENGTH)
    ) node (
        .clk           (clk   ),
        .arstn         (arstn ),

        .valid_i       (valid_i),
        .x1            (x1     ),
        .x2            (x2     ),

        .re1            (re1),
        .im1            (im1),
        .re2            (re2),
        .im2            (im2),
        .valid_o       (valid_o)
    );

    initial begin
        $dumpfile("serial_fft_coral.vcd");
        $dumpvars;
    end
    // Запись значений в веса

    // Генерация clk
    parameter CLK_PERIOD = 20; // 50 МГц
    initial begin
        clk <= 0;
        forever begin
            #(CLK_PERIOD / 2); clk <= ~clk;
        end
    end

    //Генерация rst
    initial begin
        arstn <= 0;
        @(posedge clk);
        @(posedge clk);
        @(posedge clk);
        arstn <= 1;
    end

    // Генерация входных сигналов
    initial begin
        valid_i <= 'b0;

        wait(arstn);
        @(posedge clk);
    //---------------------------------------------------------------------------------------------
        //1
        @(posedge clk);
        valid_i <= 'b1;
        x1 <= 'd1;
        x2 <= 'd2;

        @(posedge clk);
        x1 <= 'd3;
        x2 <= 'd4;

        @(posedge clk);
        x1 <= 'd5;
        x2 <= 'd6;

        @(posedge clk);
        x1 <= 'd7;
        x2 <= 'd8;

        @(posedge clk);
        @(posedge clk);
        @(posedge clk);

        $finish;
    end
    
    // Проверка
    // initial begin
    //     wait(~arstn);
    //     @(posedge clk);
    //     @(posedge clk);
    // //---------------------------------------------------------------------------------------------
    //     repeat (32)
    //     begin
    //         @(posedge clk);
    //         if ($signed(psumm_o) != ($signed(psumm_i) + $signed(weight_i) * $signed(x_i) )) begin
    //             $display($signed(psumm_o));
    //             $display(($signed(psumm_i) + $signed(weight_i) * $signed(x_i)));
    //             $display($signed(psumm_i));
    //             $display($signed(weight_i));
    //             $display($signed(x_i));
    //             $error("BAD");
    //         end
    //         else begin
    //             $display("PASS");
    //             // $display($signed(psumm_o));
    //             // $display($signed(psumm_i));
    //             // $display($signed(weight_i));
    //             // $display($signed(x_i));
    //         end
    //     end
    // //---------------------------------------------------------------------------------------------
    //     @(posedge clk);
    //     @(posedge clk);
    //     @(posedge clk);
    //     $finish;
    // end
endmodule

fft/serial_fft_coral.vcd
$date
	Tue Mar 11 10:03:45 2025
$end
$version
	Icarus Verilog
$end
$timescale
	1ps
$end
$scope module testbench $end
$var wire 1 ! valid_o $end
$var wire 32 " re2 [31:0] $end
$var wire 32 # re1 [31:0] $end
$var wire 32 $ im2 [31:0] $end
$var wire 32 % im1 [31:0] $end
$var reg 1 & arstn $end
$var reg 1 ' clk $end
$var reg 1 ( valid_i $end
$var reg 16 ) x1 [15:0] $end
$var reg 16 * x2 [15:0] $end
$scope module node $end
$var wire 1 & arstn $end
$var wire 1 ' clk $end
$var wire 1 ( valid_i $end
$var wire 16 + x1 [15:0] $end
$var wire 16 , x2 [15:0] $end
$var wire 1 ! valid_o $end
$var wire 32 - re2 [31:0] $end
$var wire 32 . re1 [31:0] $end
$var wire 32 / im2 [31:0] $end
$var wire 32 0 im1 [31:0] $end
$scope module node $end
$var wire 1 & arstn $end
$var wire 1 ' clk $end
$var wire 32 1 im1 [31:0] $end
$var wire 32 2 im2 [31:0] $end
$var wire 32 3 re1 [31:0] $end
$var wire 32 4 re2 [31:0] $end
$var wire 1 ( valid_i $end
$var wire 1 5 valid_psumm_i_im1 $end
$var wire 1 6 valid_psumm_i_im2 $end
$var wire 1 7 valid_psumm_i_re1 $end
$var wire 1 8 valid_psumm_i_re2 $end
$var wire 16 9 weight_im [15:0] $end
$var wire 16 : weight_re [15:0] $end
$var wire 16 ; x1 [15:0] $end
$var wire 16 < x2 [15:0] $end
$var wire 1 = valid_psumm_o_re2 $end
$var wire 1 > valid_psumm_o_re1 $end
$var wire 1 ? valid_psumm_o_im2 $end
$var wire 1 @ valid_psumm_o_im1 $end
$var wire 32 A psumm_o_re2 [31:0] $end
$var wire 32 B psumm_o_re1 [31:0] $end
$var wire 32 C psumm_o_im2 [31:0] $end
$var wire 32 D psumm_o_im1 [31:0] $end
$var wire 32 E psumm_i_re2 [31:0] $end
$var wire 32 F psumm_i_re1 [31:0] $end
$var wire 32 G psumm_i_im2 [31:0] $end
$var wire 32 H psumm_i_im1 [31:0] $end
$var reg 2 I counter [1:0] $end
$var reg 1 ! valid_o $end
$scope module im_node1 $end
$var wire 1 & arstn $end
$var wire 1 ' clk $end
$var wire 1 J en $end
$var wire 1 ( enable $end
$var wire 32 K psumm_i [31:0] $end
$var wire 1 L valid $end
$var wire 1 5 valid_psumm_i $end
$var wire 1 ( valid_x_i $end
$var wire 1 M valid_x_o $end
$var wire 16 N weight_i [15:0] $end
$var wire 16 O x_i [15:0] $end
$var wire 16 P x_o [15:0] $end
$var wire 32 Q weight_mult [31:0] $end
$var wire 32 R psumm_o [31:0] $end
$var reg 32 S psumm_reg [31:0] $end
$var reg 1 @ valid_o $end
$upscope $end
$scope module im_node2 $end
$var wire 1 & arstn $end
$var wire 1 ' clk $end
$var wire 1 T en $end
$var wire 1 ( enable $end
$var wire 32 U psumm_i [31:0] $end
$var wire 1 V valid $end
$var wire 1 6 valid_psumm_i $end
$var wire 1 ( valid_x_i $end
$var wire 1 W valid_x_o $end
$var wire 16 X weight_i [15:0] $end
$var wire 16 Y x_i [15:0] $end
$var wire 16 Z x_o [15:0] $end
$var wire 32 [ weight_mult [31:0] $end
$var wire 32 \ psumm_o [31:0] $end
$var reg 32 ] psumm_reg [31:0] $end
$var reg 1 ? valid_o $end
$upscope $end
$scope module re_node1 $end
$var wire 1 & arstn $end
$var wire 1 ' clk $end
$var wire 1 ^ en $end
$var wire 1 ( enable $end
$var wire 32 _ psumm_i [31:0] $end
$var wire 1 ` valid $end
$var wire 1 7 valid_psumm_i $end
$var wire 1 ( valid_x_i $end
$var wire 1 a valid_x_o $end
$var wire 16 b weight_i [15:0] $end
$var wire 16 c x_i [15:0] $end
$var wire 16 d x_o [15:0] $end
$var wire 32 e weight_mult [31:0] $end
$var wire 32 f psumm_o [31:0] $end
$var reg 32 g psumm_reg [31:0] $end
$var reg 1 > valid_o $end
$upscope $end
$scope module re_node2 $end
$var wire 1 & arstn $end
$var wire 1 ' clk $end
$var wire 1 h en $end
$var wire 1 ( enable $end
$var wire 32 i psumm_i [31:0] $end
$var wire 1 j valid $end
$var wire 1 8 valid_psumm_i $end
$var wire 1 ( valid_x_i $end
$var wire 1 k valid_x_o $end
$var wire 16 l weight_i [15:0] $end
$var wire 16 m x_i [15:0] $end
$var wire 16 n x_o [15:0] $end
$var wire 32 o weight_mult [31:0] $end
$var wire 32 p psumm_o [31:0] $end
$var reg 32 q psumm_reg [31:0] $end
$var reg 1 = valid_o $end
$upscope $end
$upscope $end
$upscope $end
$upscope $end
$enddefinitions $end
#0
$dumpvars
bx q
bx p
bx o
bx n
bx m
b1111101000 l
0k
0j
b0 i
0h
bx g
bx f
bx e
bx d
bx c
b1111101000 b
0a
0`
b0 _
0^
bx ]
bx \
bx [
bx Z
bx Y
b0 X
0W
0V
b0 U
0T
bx S
bx R
bx Q
bx P
bx O
b0 N
0M
0L
b0 K
0J
b0 I
b0 H
b0 G
b0 F
b0 E
bx D
bx C
bx B
bx A
0@
0?
0>
0=
bx <
bx ;
b1111101000 :
b0 9
18
17
16
15
bx 4
bx 3
bx 2
bx 1
bx 0
bx /
bx .
bx -
bx ,
bx +
bx *
bx )
0(
0'
0&
bx %
bx $
bx #
bx "
0!
$end
#10000
1'
#20000
0'
#30000
1'
#40000
0'
#50000
1&
1'
#60000
0'
#70000
1'
#80000
0'
#90000
1J
1T
1^
1h
1L
1V
1`
1j
b10 Z
b0 [
b10 n
b11111010000 o
b10 *
b10 ,
b10 <
b10 Y
b10 m
b1 P
b0 Q
b1 d
b1111101000 e
b1 )
b1 +
b1 ;
b1 O
b1 c
1M
1W
1a
1k
1(
1'
#100000
0'
#110000
b1111101000 F
b1111101000 _
b11111010000 E
b11111010000 i
1>
1@
1=
1?
b1111100110 :
b1111100110 b
b1111100110 l
b11010010 Q
b100011000 [
b1000110 9
b1000110 N
b1000110 X
b1 I
b0 $
b0 /
b0 2
b0 C
b0 \
b0 ]
b11111010000 "
b11111010000 -
b11111010000 4
b11111010000 A
b11111010000 p
b11111010000 q
b0 %
b0 0
b0 1
b0 D
b0 R
b0 S
b1111101000 #
b1111101000 .
b1111101000 3
b1111101000 B
b1111101000 f
b1111101000 g
b100 Z
b100 n
b111110011000 o
b100 *
b100 ,
b100 <
b100 Y
b100 m
b11 P
b11 d
b101110110010 e
b11 )
b11 +
b11 ;
b11 O
b11 c
1'
#120000
0'
#130000
b111110011010 F
b111110011010 _
b11010010 H
b11010010 K
b1011101101000 E
b1011101101000 i
b100011000 G
b100011000 U
b1111011110 :
b1111011110 b
b1111011110 l
b10001011 9
b10001011 N
b10001011 X
b10 I
b110 Z
b1101000010 [
b110 n
b1011100110100 o
b110 *
b110 ,
b110 <
b110 Y
b110 m
b101 P
b1010110111 Q
b101 d
b1001101010110 e
b101 )
b101 +
b101 ;
b101 O
b101 c
b111110011010 #
b111110011010 .
b111110011010 3
b111110011010 B
b111110011010 f
b111110011010 g
b11010010 %
b11010010 0
b11010010 1
b11010010 D
b11010010 R
b11010010 S
b1011101101000 "
b1011101101000 -
b1011101101000 4
b1011101101000 A
b1011101101000 p
b1011101101000 q
b100011000 $
b100011000 /
b100011000 2
b100011000 C
b100011000 \
b100011000 ]
1'
#140000
0'
#150000
b10001011010 G
b10001011010 U
b10111010011100 E
b10111010011100 i
b1110001001 H
b1110001001 K
b10001011110000 F
b10001011110000 _
b1111010010 :
b1111010010 b
b1111010010 l
b11010000 9
b11010000 N
b11010000 X
b11 I
b10001011010 $
b10001011010 /
b10001011010 2
b10001011010 C
b10001011010 \
b10001011010 ]
b10111010011100 "
b10111010011100 -
b10111010011100 4
b10111010011100 A
b10111010011100 p
b10111010011100 q
b1110001001 %
b1110001001 0
b1110001001 1
b1110001001 D
b1110001001 R
b1110001001 S
b10001011110000 #
b10001011110000 .
b10001011110000 3
b10001011110000 B
b10001011110000 f
b10001011110000 g
b1000 Z
b11010000000 [
b1000 n
b1111010010000 o
b1000 *
b1000 ,
b1000 <
b1000 Y
b1000 m
b111 P
b10110110000 Q
b111 d
b1101010111110 e
b111 )
b111 +
b111 ;
b111 O
b111 c
1'
#160000
0'
#170000
b0 F
b0 _
b0 H
b0 K
b0 E
b0 i
b0 G
b0 U
1!
b1101101011000 e
b1111101000000 o
b1111101000 :
b1111101000 b
b1111101000 l
b0 Q
b0 [
b0 9
b0 N
b0 X
b0 I
b11110110101110 #
b11110110101110 .
b11110110101110 3
b11110110101110 B
b11110110101110 f
b11110110101110 g
b100100111001 %
b100100111001 0
b100100111001 1
b100100111001 D
b100100111001 R
b100100111001 S
b100110100101100 "
b100110100101100 -
b100110100101100 4
b100110100101100 A
b100110100101100 p
b100110100101100 q
b101011011010 $
b101011011010 /
b101011011010 2
b101011011010 C
b101011011010 \
b101011011010 ]
1'
#180000
0'
#190000
b1101101011000 F
b1101101011000 _
b1111101000000 E
b1111101000000 i
0!
b1101101001010 e
b1111100110000 o
b1111100110 :
b1111100110 b
b1111100110 l
b111101010 Q
b1000110000 [
b1000110 9
b1000110 N
b1000110 X
b1 I
b0 $
b0 /
b0 2
b0 C
b0 \
b0 ]
b1111101000000 "
b1111101000000 -
b1111101000000 4
b1111101000000 A
b1111101000000 p
b1111101000000 q
b0 %
b0 0
b0 1
b0 D
b0 R
b0 S
b1101101011000 #
b1101101011000 .
b1101101011000 3
b1101101011000 B
b1101101011000 f
b1101101011000 g
1'
#200000
0'
#210000
b11011010100010 F
b11011010100010 _
b111101010 H
b111101010 K
b11111001110000 E
b11111001110000 i
b1000110000 G
b1000110000 U
b1101100010010 e
b1111011110000 o
b1111011110 :
b1111011110 b
b1111011110 l
b1111001101 Q
b10001011000 [
b10001011 9
b10001011 N
b10001011 X
b10 I
b11011010100010 #
b11011010100010 .
b11011010100010 3
b11011010100010 B
b11011010100010 f
b11011010100010 g
b111101010 %
b111101010 0
b111101010 1
b111101010 D
b111101010 R
b111101010 S
b11111001110000 "
b11111001110000 -
b11111001110000 4
b11111001110000 A
b11111001110000 p
b11111001110000 q
b1000110000 $
b1000110000 /
b1000110000 2
b1000110000 C
b1000110000 \
b1000110000 ]
1'
