fft/syst_node/syst_node.sv
module syst_node
#(
    parameter W_WIDTH  = 16,
    parameter X_WIDTH  = 16,
    parameter SI_WIDTH = 32,
    parameter SO_WIDTH = 32
)
(
    input  logic                       clk,
    input  logic                       rstn,
    input  logic                       enable,
    input  logic signed [W_WIDTH -1:0] weight_i,

    input  logic signed [SI_WIDTH-1:0] psumm_i,
    input  logic                       valid_psumm_i,

    input  logic signed [X_WIDTH -1:0] x_i,
    input  logic                       valid_x_i,

    output logic signed [SO_WIDTH-1:0] psumm_o,
    output logic                       valid_o,

    output logic signed [X_WIDTH -1:0] x_o,
    output logic                       valid_x_o
);

    logic signed [SO_WIDTH       -1:0] psumm_reg;
    logic signed [X_WIDTH+W_WIDTH-1:0] weight_mult;

    logic valid_o_logic;
    assign valid_o_logic = valid_x_i & valid_psumm_i;

    // Расчёт результата
    logic en;
    assign en = enable & valid_o_logic;
    assign weight_mult = x_i * weight_i;
    logic signed [SO_WIDTH - 1:0] psumm_o_logic;
    assign psumm_o_logic = psumm_i + weight_mult;
    always_ff @(posedge clk)
        if (en) psumm_reg <= psumm_o_logic;

    // Расчёт валидности
    always_ff @(posedge clk)
        if (~rstn)       valid_o <= 'b0;
        else if (enable) valid_o <= valid_o_logic;

    assign psumm_o = psumm_reg;
    assign valid_x_o = valid_x_i;
    assign x_o = x_i;

endmodule

fft/serial_fft_coral/serial_fft_coral.sv
`include ".\syst_node\syst_node.sv"

module serial_fft_coral
#(
    parameter W_WIDTH  = 16,
    parameter X_WIDTH  = 16,
    parameter S_WIDTH  = 32,

    parameter FRAME_LENGTH = 3,
    parameter CHANELS = 2
)
(
    input  logic                                       clk,
    input  logic                                       rstn,

    output logic [$clog2(FRAME_LENGTH) - 1:0] counter,
    input logic signed [W_WIDTH-1:0] w_re,
    input logic signed [W_WIDTH-1:0] w_im,

    input  logic                                       valid_i,
    input  logic signed [CHANELS-1:0][X_WIDTH-1:0]     x,
    
    output logic signed [CHANELS-1:0] [S_WIDTH-1:0]    re,
    output logic signed [CHANELS-1:0] [S_WIDTH-1:0]    im,
    output logic signed                                valid_o
);
    //------------------------------------------------------------------------

    //------------------------------------------------------------------------

    // Счётчик для мультиплексирования
    logic counter_enable;
    assign counter_enable = counter == (FRAME_LENGTH - 1);
    always_ff @ (posedge clk)
        if (!rstn)
        begin
            counter <= 'b0;
            valid_o <= 'b0;
        end
        else if (valid_i)
        begin
            if (counter_enable)
            begin
                counter <= '0;
                valid_o <= 'b1;
            end
            else
            begin
                counter <= counter + 1'b1;
                valid_o <= 'b0;
            end
        end
    
    logic reset_node;
    assign reset_node = |counter;

    //------------------------------------------------------------------------
    // RE
    genvar i;
    generate
        for (i = 0; i<CHANELS; i++) begin : RE
            logic signed [S_WIDTH-1:0] psumm_i_re;
            logic                valid_psumm_i_re;
            assign psumm_i_re = reset_node ? psumm_o_re : 'b0;

            logic signed [S_WIDTH-1:0] psumm_o_re;
            logic                valid_psumm_o_re;

            assign valid_psumm_i_re = 'b1;

            syst_node #(
                .W_WIDTH  (W_WIDTH),
                .X_WIDTH  (X_WIDTH),
                .SI_WIDTH (S_WIDTH),
                .SO_WIDTH (S_WIDTH)
            ) re_node1 (
                .clk           (clk),
                .rstn          (rstn),
                .enable        (valid_i),
                .weight_i      (w_re),

                .psumm_i       (psumm_i_re),
                .valid_psumm_i (valid_psumm_i_re),

                .x_i           (x[i]),
                .valid_x_i     (valid_i),

                .psumm_o       (psumm_o_re),
                .valid_o       (valid_psumm_o_re)
            );
            assign re[i] = psumm_o_re;
        end
    endgenerate

    //------------------------------------------------------------------------

    // IM
    genvar j;
    generate
        for (j = 0; j<CHANELS; j++) begin : IM
            logic signed [S_WIDTH-1:0] psumm_i_im;
            logic                valid_psumm_i_im;

            assign psumm_i_im = reset_node ? psumm_o_im : 'b0;

            logic signed [S_WIDTH-1:0] psumm_o_im;
            logic                valid_psumm_o_im;

            assign valid_psumm_i_im = 'b1;

            syst_node #(
                .W_WIDTH  (W_WIDTH),
                .X_WIDTH  (X_WIDTH),
                .SI_WIDTH (S_WIDTH),
                .SO_WIDTH (S_WIDTH)
            ) im_node1 (
                .clk           (clk),
                .rstn          (rstn),
                .enable        (valid_i),
                .weight_i      (w_im),

                .psumm_i       (psumm_i_im),
                .valid_psumm_i (valid_psumm_i_im),

                .x_i           (x[j]),
                .valid_x_i     (valid_i),

                .psumm_o       (psumm_o_im),
                .valid_o       (valid_psumm_o_im)
            );
            assign im[j] = psumm_o_im;
        end
    endgenerate

endmodule

fft/RAM_fft/RAM_w_im.sv
module RAM_w_im
#(
    parameter WIDTH = 32,
    parameter DEPTH = 360
)
(
    input                         clk,         
    input                         write_enable,
    input  [$clog2 (DEPTH) - 1:0] address,     
    input  [WIDTH-1:0]            data_in,     
    output [WIDTH-1:0]            data_out
);

  logic [WIDTH-1:0] w_im [0:DEPTH-1];
  initial $readmemb(".\\weigths\\w_im.txt", w_im);

  always @(posedge clk)
    if (write_enable)
      w_im[address] <= data_in;

  assign data_out = w_im[address];

endmodule

fft/RAM_fft/RAM_w_re.sv
module RAM_w_re
#(
    parameter WIDTH = 32,
    parameter DEPTH = 360
)
(
    input        clk,            // best to make it synchronous
    input        write_enable,     // a simple active high write enable
    input [$clog2 (DEPTH) - 1:0]  address,          // a single address bus in this example
    input [WIDTH-1:0]  data_in,          // input data
    output [WIDTH-1:0] data_out
);        // output data

  logic [WIDTH-1:0] w_re [0:DEPTH-1];          // here is the array; make this the size you need
  initial $readmemb(".\\weigths\\w_re.txt", w_re);

  always @(posedge clk)
    if (write_enable)
      w_re[address] <= data_in;

  assign data_out = w_re[address];

endmodule

fft/serial_fft_coral/testbench.sv
`timescale 1ns/1ps
`include ".\RAM_fft\RAM_w_re.sv"
`include ".\RAM_fft\RAM_w_im.sv"

module a
#(
    parameter W_WIDTH  = 16,
    parameter X_WIDTH  = 16,
    parameter S_WIDTH  = 32,

    parameter FRAME_LENGTH = 10,
    parameter CHANELS = 2
)
(
    input  logic                                       clk,
    input  logic                                       arstn,

    input  logic                                       valid_i,
    input  logic signed [CHANELS-1:0] [X_WIDTH-1:0]    x,
    
    output logic signed [CHANELS-1:0][S_WIDTH-1:0]                  re,
    output logic signed [CHANELS-1:0][S_WIDTH-1:0]                  im,
    output logic signed                                valid_o
);
    logic signed [W_WIDTH-1:0] w_re;
    logic signed [W_WIDTH-1:0] w_im;
    logic [$clog2(FRAME_LENGTH) - 1:0]  counter;

    RAM_w_re
    #(
        .WIDTH(W_WIDTH),
        .DEPTH(FRAME_LENGTH)
    ) ram1 (
        .clk(clk),
        .address (counter),
        .data_out (w_re)
    );

    RAM_w_im
    #(
        .WIDTH(W_WIDTH),
        .DEPTH(FRAME_LENGTH)
    ) ram2 (
        .clk(clk),
        .address (counter),
        .data_out (w_im)
    );
    
    serial_fft_coral #(
        .W_WIDTH  (W_WIDTH),
        .X_WIDTH  (X_WIDTH),
        .S_WIDTH  (S_WIDTH),
        .FRAME_LENGTH (FRAME_LENGTH)
    ) core (
        .clk           (clk   ),
        .rstn         (arstn ),

        .counter (counter),
        .w_re          (w_re  ),
        .w_im          (w_im  ),

        .valid_i       (valid_i),
        .x            (x      ),

        .re            (re),
        .im            (im),
        .valid_o       (valid_o)
    );
endmodule

module testbench;
    // Подключение
    localparam W_WIDTH  = 16;
    localparam X_WIDTH  = 16;
    localparam S_WIDTH  = 32;
    localparam FRAME_LENGTH = 4;
    localparam CHANELS = 2;

    logic                                        clk;
    logic                                        arstn;

    logic                                        valid_i;
    logic signed [CHANELS-1:0][X_WIDTH-1:0]      x;
    logic signed [X_WIDTH-1:0]                   x1;
    logic signed [X_WIDTH-1:0]                   x2;
    assign x = {x2, x1};

    logic signed [CHANELS-1:0][S_WIDTH-1:0]      re;
    logic signed [S_WIDTH-1:0] re1;
    logic signed [CHANELS-1:0][S_WIDTH-1:0]      im;
    logic signed [S_WIDTH-1:0] im1;
    logic                                        valid_o;
    assign re1 = re[0];
    assign im1 = im[0];

    a #(
        .W_WIDTH  (W_WIDTH),
        .X_WIDTH  (X_WIDTH),
        .S_WIDTH  (S_WIDTH),
        .FRAME_LENGTH (FRAME_LENGTH),
        .CHANELS (CHANELS)
    ) test (
        .clk           (clk   ),
        .arstn         (arstn ),

        .valid_i       (valid_i),
        .x            (x     ),

        .re            (re),
        .im            (im),
        .valid_o       (valid_o)
    );

    initial begin
        $dumpfile("serial_fft_coral.vcd");
        $dumpvars;
    end
    // Запись значений в веса

    // Генерация clk
    parameter CLK_PERIOD = 20; // 50 МГц
    initial begin
        clk <= 0;
        forever begin
            #(CLK_PERIOD / 2); clk <= ~clk;
        end
    end

    //Генерация rst
    initial begin
        arstn <= 0;
        @(posedge clk);
        @(posedge clk);
        @(posedge clk);
        arstn <= 1;
    end

    // Генерация входных сигналов
    initial begin
        valid_i <= 'b0;

        wait(arstn);
        @(posedge clk);
    //---------------------------------------------------------------------------------------------
        //1
        @(posedge clk);
        valid_i <= 'b1;
        x1 <= 'd1;
        x2 <= 'd2;

        @(posedge clk);
        x1 <= 'd3;
        x2 <= 'd4;

        @(posedge clk);
        x1 <= 'd5;
        x2 <= 'd6;

        @(posedge clk);
        x1 <= 'd7;
        x2 <= 'd8;

        @(posedge clk);
        @(posedge clk);
        @(posedge clk);
        @(posedge clk);
        @(posedge clk);

        $finish;
    end
    
    // Проверка
    // initial begin
    //     wait(~arstn);
    //     @(posedge clk);
    //     @(posedge clk);
    // //---------------------------------------------------------------------------------------------
    //     repeat (32)
    //     begin
    //         @(posedge clk);
    //         if ($signed(psumm_o) != ($signed(psumm_i) + $signed(weight_i) * $signed(x_i) )) begin
    //             $display($signed(psumm_o));
    //             $display(($signed(psumm_i) + $signed(weight_i) * $signed(x_i)));
    //             $display($signed(psumm_i));
    //             $display($signed(weight_i));
    //             $display($signed(x_i));
    //             $error("BAD");
    //         end
    //         else begin
    //             $display("PASS");
    //             // $display($signed(psumm_o));
    //             // $display($signed(psumm_i));
    //             // $display($signed(weight_i));
    //             // $display($signed(x_i));
    //         end
    //     end
    // //---------------------------------------------------------------------------------------------
    //     @(posedge clk);
    //     @(posedge clk);
    //     @(posedge clk);
    //     $finish;
    // end
endmodule

fft/serial_fft_coral.vcd
$date
	Tue Mar 25 19:52:57 2025
$end
$version
	Icarus Verilog
$end
$timescale
	1ps
$end
$scope module testbench $end
$var wire 32 ! x [31:0] $end
$var wire 1 " valid_o $end
$var wire 32 # re1 [31:0] $end
$var wire 64 $ re [63:0] $end
$var wire 32 % im1 [31:0] $end
$var wire 64 & im [63:0] $end
$var reg 1 ' arstn $end
$var reg 1 ( clk $end
$var reg 1 ) valid_i $end
$var reg 16 * x1 [15:0] $end
$var reg 16 + x2 [15:0] $end
$scope module test $end
$var wire 1 ' arstn $end
$var wire 1 ( clk $end
$var wire 1 ) valid_i $end
$var wire 32 , x [31:0] $end
$var wire 16 - w_re [15:0] $end
$var wire 16 . w_im [15:0] $end
$var wire 1 " valid_o $end
$var wire 64 / re [63:0] $end
$var wire 64 0 im [63:0] $end
$var wire 2 1 counter [1:0] $end
$scope module core $end
$var wire 1 ( clk $end
$var wire 1 ' rstn $end
$var wire 1 ) valid_i $end
$var wire 32 2 x [31:0] $end
$var wire 16 3 w_re [15:0] $end
$var wire 16 4 w_im [15:0] $end
$var wire 1 5 reset_node $end
$var wire 64 6 re [63:0] $end
$var wire 64 7 im [63:0] $end
$var wire 1 8 counter_enable $end
$var reg 2 9 counter [1:0] $end
$var reg 1 " valid_o $end
$scope begin IM[0] $end
$var wire 32 : psumm_i_im [31:0] $end
$var wire 1 ; valid_psumm_i_im $end
$var wire 1 < valid_psumm_o_im $end
$var wire 32 = psumm_o_im [31:0] $end
$scope module im_node1 $end
$var wire 1 ( clk $end
$var wire 1 > en $end
$var wire 1 ) enable $end
$var wire 32 ? psumm_i [31:0] $end
$var wire 1 ' rstn $end
$var wire 1 @ valid_o_logic $end
$var wire 1 ; valid_psumm_i $end
$var wire 1 ) valid_x_i $end
$var wire 1 A valid_x_o $end
$var wire 16 B x_i [15:0] $end
$var wire 16 C x_o [15:0] $end
$var wire 32 D weight_mult [31:0] $end
$var wire 16 E weight_i [15:0] $end
$var wire 32 F psumm_o_logic [31:0] $end
$var wire 32 G psumm_o [31:0] $end
$var reg 32 H psumm_reg [31:0] $end
$var reg 1 < valid_o $end
$upscope $end
$upscope $end
$scope begin IM[1] $end
$var wire 32 I psumm_i_im [31:0] $end
$var wire 1 J valid_psumm_i_im $end
$var wire 1 K valid_psumm_o_im $end
$var wire 32 L psumm_o_im [31:0] $end
$scope module im_node1 $end
$var wire 1 ( clk $end
$var wire 1 M en $end
$var wire 1 ) enable $end
$var wire 32 N psumm_i [31:0] $end
$var wire 1 ' rstn $end
$var wire 1 O valid_o_logic $end
$var wire 1 J valid_psumm_i $end
$var wire 1 ) valid_x_i $end
$var wire 1 P valid_x_o $end
$var wire 16 Q x_i [15:0] $end
$var wire 16 R x_o [15:0] $end
$var wire 32 S weight_mult [31:0] $end
$var wire 16 T weight_i [15:0] $end
$var wire 32 U psumm_o_logic [31:0] $end
$var wire 32 V psumm_o [31:0] $end
$var reg 32 W psumm_reg [31:0] $end
$var reg 1 K valid_o $end
$upscope $end
$upscope $end
$scope begin RE[0] $end
$var wire 32 X psumm_i_re [31:0] $end
$var wire 1 Y valid_psumm_i_re $end
$var wire 1 Z valid_psumm_o_re $end
$var wire 32 [ psumm_o_re [31:0] $end
$scope module re_node1 $end
$var wire 1 ( clk $end
$var wire 1 \ en $end
$var wire 1 ) enable $end
$var wire 32 ] psumm_i [31:0] $end
$var wire 1 ' rstn $end
$var wire 1 ^ valid_o_logic $end
$var wire 1 Y valid_psumm_i $end
$var wire 1 ) valid_x_i $end
$var wire 1 _ valid_x_o $end
$var wire 16 ` x_i [15:0] $end
$var wire 16 a x_o [15:0] $end
$var wire 32 b weight_mult [31:0] $end
$var wire 16 c weight_i [15:0] $end
$var wire 32 d psumm_o_logic [31:0] $end
$var wire 32 e psumm_o [31:0] $end
$var reg 32 f psumm_reg [31:0] $end
$var reg 1 Z valid_o $end
$upscope $end
$upscope $end
$scope begin RE[1] $end
$var wire 32 g psumm_i_re [31:0] $end
$var wire 1 h valid_psumm_i_re $end
$var wire 1 i valid_psumm_o_re $end
$var wire 32 j psumm_o_re [31:0] $end
$scope module re_node1 $end
$var wire 1 ( clk $end
$var wire 1 k en $end
$var wire 1 ) enable $end
$var wire 32 l psumm_i [31:0] $end
$var wire 1 ' rstn $end
$var wire 1 m valid_o_logic $end
$var wire 1 h valid_psumm_i $end
$var wire 1 ) valid_x_i $end
$var wire 1 n valid_x_o $end
$var wire 16 o x_i [15:0] $end
$var wire 16 p x_o [15:0] $end
$var wire 32 q weight_mult [31:0] $end
$var wire 16 r weight_i [15:0] $end
$var wire 32 s psumm_o_logic [31:0] $end
$var wire 32 t psumm_o [31:0] $end
$var reg 32 u psumm_reg [31:0] $end
$var reg 1 i valid_o $end
$upscope $end
$upscope $end
$upscope $end
$scope module ram1 $end
$var wire 2 v address [1:0] $end
$var wire 1 ( clk $end
$var wire 16 w data_in [15:0] $end
$var wire 16 x data_out [15:0] $end
$var wire 1 y write_enable $end
$upscope $end
$scope module ram2 $end
$var wire 2 z address [1:0] $end
$var wire 1 ( clk $end
$var wire 16 { data_in [15:0] $end
$var wire 16 | data_out [15:0] $end
$var wire 1 } write_enable $end
$upscope $end
$upscope $end
$upscope $end
$enddefinitions $end
#0
$dumpvars
z}
bx |
bz {
bx z
zy
bx x
bz w
bx v
bx u
bx t
bx s
bx r
bx q
bx p
bx o
0n
0m
bx l
0k
bx j
xi
1h
bx g
bx f
bx e
bx d
bx c
bx b
bx a
bx `
0_
0^
bx ]
0\
bx [
xZ
1Y
bx X
bx W
bx V
bx U
bx T
bx S
bx R
bx Q
0P
0O
bx N
0M
bx L
xK
1J
bx I
bx H
bx G
bx F
bx E
bx D
bx C
bx B
0A
0@
bx ?
0>
bx =
x<
1;
bx :
bx 9
x8
bx 7
bx 6
x5
bx 4
bx 3
bx 2
bx 1
bx 0
bx /
bx .
bx -
bx ,
bx +
bx *
0)
0(
0'
bx &
bx %
bx $
bx #
x"
bx !
$end
#10000
b0 I
b0 N
b0 :
b0 ?
b0 g
b0 l
b0 X
b0 ]
0Z
0i
0<
0K
0"
08
05
b10000000000 -
b10000000000 3
b10000000000 c
b10000000000 r
b10000000000 x
b0 .
b0 4
b0 E
b0 T
b0 |
b0 1
b0 9
b0 v
b0 z
1(
#20000
0(
#30000
1(
#40000
0(
#50000
1'
1(
#60000
0(
#70000
1(
#80000
0(
#90000
1>
1M
1\
1k
b10 p
b100000000000 s
b100000000000 q
b10 o
b10 R
b0 U
b0 S
b10 Q
b1 a
b10000000000 d
b10000000000 b
b1 `
b1 C
b0 F
b0 D
b1 B
1@
1O
1^
1m
b10 +
b100000000000000001 !
b100000000000000001 ,
b100000000000000001 2
b1 *
1A
1P
1_
1n
1)
1(
#100000
0(
#110000
b100000000000 g
b100000000000 l
b10000000000 X
b10000000000 ]
b0 %
b10000000000 #
b100 p
b100 o
b100 R
b100 Q
b11 a
b11 `
b11 C
b11 B
15
b1011111111000 s
b111111111000 q
b111111111010 d
b101111111010 b
b1111111110 -
b1111111110 3
b1111111110 c
b1111111110 r
b1111111110 x
b100011100 U
b100011100 S
b11010101 F
b11010101 D
b1000111 .
b1000111 4
b1000111 E
b1000111 T
b1000111 |
b1 1
b1 9
b1 v
b1 z
1K
b0 L
b0 V
b0 W
1<
b0 &
b0 0
b0 7
b0 =
b0 G
b0 H
1i
b100000000000 j
b100000000000 t
b100000000000 u
1Z
b10000000000000000000000000000000010000000000 $
b10000000000000000000000000000000010000000000 /
b10000000000000000000000000000000010000000000 6
b10000000000 [
b10000000000 e
b10000000000 f
b100 +
b1000000000000000011 !
b1000000000000000011 ,
b1000000000000000011 2
b11 *
1(
#120000
0(
#130000
b110 p
b110 o
b110 R
b110 Q
b101 a
b101 `
b101 C
b101 B
b111111111010 #
b111111111010 X
b111111111010 ]
b1011111111000 g
b1011111111000 l
b11010101 %
b11010101 :
b11010101 ?
b100011100 I
b100011100 N
b110 +
b1100000000000000101 !
b1100000000000000101 ,
b1100000000000000101 2
b101 *
b111111111010 [
b111111111010 e
b111111111010 f
b101111111100000000000000000000000111111111010 $
b101111111100000000000000000000000111111111010 /
b101111111100000000000000000000000111111111010 6
b1011111111000 j
b1011111111000 t
b1011111111000 u
b11010101 =
b11010101 G
b11010101 H
b10001110000000000000000000000000011010101 &
b10001110000000000000000000000000011010101 0
b10001110000000000000000000000000011010101 7
b100011100 L
b100011100 V
b100011100 W
b10111110111100 s
b1011111000100 q
b10001111001000 d
b1001111001110 b
b1111110110 -
b1111110110 3
b1111110110 c
b1111110110 r
b1111110110 x
b10001110110 U
b1101011010 S
b1110100000 F
b1011001011 D
b10001111 .
b10001111 4
b10001111 E
b10001111 T
b10001111 |
b10 1
b10 9
b10 v
b10 z
1(
#140000
0(
#150000
b10001110110 I
b10001110110 N
b1110100000 %
b1110100000 :
b1110100000 ?
b10111110111100 g
b10111110111100 l
b10001111001000 #
b10001111001000 X
b10001111001000 ]
b1000 p
b1000 o
b1000 R
b1000 Q
b111 a
b111 `
b111 C
b111 B
18
b100111100001100 s
b1111101010000 q
b11111100101110 d
b1101101100110 b
b1111101010 -
b1111101010 3
b1111101010 c
b1111101010 r
b1111101010 x
b101100011110 U
b11010101000 S
b100101110011 F
b10111010011 D
b11010101 .
b11010101 4
b11010101 E
b11010101 T
b11010101 |
b11 1
b11 9
b11 v
b11 z
b10001110110 L
b10001110110 V
b10001110110 W
b1000111011000000000000000000000001110100000 &
b1000111011000000000000000000000001110100000 0
b1000111011000000000000000000000001110100000 7
b1110100000 =
b1110100000 G
b1110100000 H
b10111110111100 j
b10111110111100 t
b10111110111100 u
b1011111011110000000000000000000010001111001000 $
b1011111011110000000000000000000010001111001000 /
b1011111011110000000000000000000010001111001000 6
b10001111001000 [
b10001111001000 e
b10001111001000 f
b1000 +
b10000000000000000111 !
b10000000000000000111 ,
b10000000000000000111 2
b111 *
1(
#160000
0(
#170000
b11111100101110 #
b100101110011 %
b0 I
b0 N
b0 :
b0 ?
b0 g
b0 l
b0 X
b0 ]
b11111100101110 [
b11111100101110 e
b11111100101110 f
b10011110000110000000000000000000011111100101110 $
b10011110000110000000000000000000011111100101110 /
b10011110000110000000000000000000011111100101110 6
b100111100001100 j
b100111100001100 t
b100111100001100 u
b100101110011 =
b100101110011 G
b100101110011 H
b10110001111000000000000000000000100101110011 &
b10110001111000000000000000000000100101110011 0
b10110001111000000000000000000000100101110011 7
b101100011110 L
b101100011110 V
b101100011110 W
1"
08
05
b10000000000000 s
b10000000000000 q
b1110000000000 d
b1110000000000 b
b10000000000 -
b10000000000 3
b10000000000 c
b10000000000 r
b10000000000 x
b0 U
b0 S
b0 F
b0 D
b0 .
b0 4
b0 E
b0 T
b0 |
b0 1
b0 9
b0 v
b0 z
1(
#180000
0(
#190000
b10000000000000 g
b10000000000000 l
b1110000000000 X
b1110000000000 ]
b0 %
b1110000000000 #
0"
15
b11111111110000 s
b1111111110000 q
b11011111110010 d
b1101111110010 b
b1111111110 -
b1111111110 3
b1111111110 c
b1111111110 r
b1111111110 x
b1000111000 U
b1000111000 S
b111110001 F
b111110001 D
b1000111 .
b1000111 4
b1000111 E
b1000111 T
b1000111 |
b1 1
b1 9
b1 v
b1 z
b0 L
b0 V
b0 W
b0 &
b0 0
b0 7
b0 =
b0 G
b0 H
b10000000000000 j
b10000000000000 t
b10000000000000 u
b1000000000000000000000000000000001110000000000 $
b1000000000000000000000000000000001110000000000 /
b1000000000000000000000000000000001110000000000 6
b1110000000000 [
b1110000000000 e
b1110000000000 f
1(
#200000
0(
#210000
b11011111110010 #
b11011111110010 X
b11011111110010 ]
b11111111110000 g
b11111111110000 l
b111110001 %
b111110001 :
b111110001 ?
b1000111000 I
b1000111000 N
b11011111110010 [
b11011111110010 e
b11011111110010 f
b1111111111000000000000000000000011011111110010 $
b1111111111000000000000000000000011011111110010 /
b1111111111000000000000000000000011011111110010 6
b11111111110000 j
b11111111110000 t
b11111111110000 u
b111110001 =
b111110001 G
b111110001 H
b100011100000000000000000000000000111110001 &
b100011100000000000000000000000000111110001 0
b100011100000000000000000000000000111110001 7
b1000111000 L
b1000111000 V
b1000111000 W
b101111110100000 s
b1111110110000 q
b101001110101100 d
b1101110111010 b
b1111110110 -
b1111110110 3
b1111110110 c
b1111110110 r
b1111110110 x
b11010110000 U
b10001111000 S
b10111011010 F
b1111101001 D
b10001111 .
b10001111 4
b10001111 E
b10001111 T
b10001111 |
b10 1
b10 9
b10 v
b10 z
1(
#220000
0(
#230000
b11010110000 I
b11010110000 N
b10111011010 %
b10111011010 :
b10111011010 ?
b101111110100000 g
b101111110100000 l
b101001110101100 #
b101001110101100 X
b101001110101100 ]
18
b111111011110000 s
b1111101010000 q
b110111100010010 d
b1101101100110 b
b1111101010 -
b1111101010 3
b1111101010 c
b1111101010 r
b1111101010 x
b110101011000 U
b11010101000 S
b101110101101 F
b10111010011 D
b11010101 .
b11010101 4
b11010101 E
b11010101 T
b11010101 |
b11 1
b11 9
b11 v
b11 z
b11010110000 L
b11010110000 V
b11010110000 W
b1101011000000000000000000000000010111011010 &
b1101011000000000000000000000000010111011010 0
b1101011000000000000000000000000010111011010 7
b10111011010 =
b10111011010 G
b10111011010 H
b101111110100000 j
b101111110100000 t
b101111110100000 u
b10111111010000000000000000000000101001110101100 $
b10111111010000000000000000000000101001110101100 /
b10111111010000000000000000000000101001110101100 6
b101001110101100 [
b101001110101100 e
b101001110101100 f
1(
#240000
0(
#250000
b110111100010010 #
b101110101101 %
b0 I
b0 N
b0 :
b0 ?
b0 g
b0 l
b0 X
b0 ]
b110111100010010 [
b110111100010010 e
b110111100010010 f
b11111101111000000000000000000000110111100010010 $
b11111101111000000000000000000000110111100010010 /
b11111101111000000000000000000000110111100010010 6
b111111011110000 j
b111111011110000 t
b111111011110000 u
b101110101101 =
b101110101101 G
b101110101101 H
b11010101100000000000000000000000101110101101 &
b11010101100000000000000000000000101110101101 0
b11010101100000000000000000000000101110101101 7
b110101011000 L
b110101011000 V
b110101011000 W
1"
08
05
b10000000000000 s
b10000000000000 q
b1110000000000 d
b1110000000000 b
b10000000000 -
b10000000000 3
b10000000000 c
b10000000000 r
b10000000000 x
b0 U
b0 S
b0 F
b0 D
b0 .
b0 4
b0 E
b0 T
b0 |
b0 1
b0 9
b0 v
b0 z
1(
