fft/syst_node/syst_node.sv
module syst_node
#(
    parameter W_WIDTH  = 16,
    parameter X_WIDTH  = 16,
    parameter SI_WIDTH = 32,
    parameter SO_WIDTH = 32
)
(
    input  logic                       clk,
    input  logic                       arstn,
    input  logic                       enable,
    input  logic signed [W_WIDTH -1:0] weight_i,

    input  logic signed [SI_WIDTH-1:0] psumm_i,
    input  logic                       valid_psumm_i,

    input  logic signed [X_WIDTH -1:0] x_i,
    input  logic                       valid_x_i,

    output logic signed [SO_WIDTH-1:0] psumm_o,
    output logic                       valid_o,

    output logic signed [X_WIDTH -1:0] x_o,
    output logic                       valid_x_o
);

    logic signed [SO_WIDTH       -1:0] psumm_reg;
    logic signed [X_WIDTH+W_WIDTH-1:0] weight_mult;

    logic valid;
    assign valid = valid_x_i & valid_psumm_i;

    // Расчёт результата
    logic en;
    assign en = enable & valid;
    assign weight_mult = x_i * weight_i;
    always_ff @(posedge clk) begin
        if (en)
            psumm_reg <= psumm_i + weight_mult;
    end

    // Расчёт валидности
    always_ff @(posedge clk or negedge arstn) begin
        if (~arstn)
            valid_o <= '0;
        else
            if (enable)
                valid_o <= valid;
    end

    assign psumm_o = psumm_reg;
    assign valid_x_o = valid_x_i;
    assign x_o = x_i;

endmodule

fft/serial_fft_coral/serial_fft_coral.sv
`include ".\syst_node\syst_node.sv"

module serial_fft_coral
#(
    parameter W_WIDTH  = 16,
    parameter X_WIDTH  = 16,
    parameter S_WIDTH  = 32,

    parameter FRAME_LENGTH = 3
)
(
    input  logic                                       clk,
    input  logic                                       arstn,
    input logic signed [W_WIDTH-1:0] w_re [FRAME_LENGTH-1:0],
    input logic signed [W_WIDTH-1:0] w_im [FRAME_LENGTH-1:0],

    input  logic                                       valid_i,
    input  logic signed [X_WIDTH-1:0]                  x1,
    input  logic signed [X_WIDTH-1:0]                  x2,
    
    output logic signed [S_WIDTH-1:0]                  re1,
    output logic signed [S_WIDTH-1:0]                  im1,
    output logic signed [S_WIDTH-1:0]                  re2,
    output logic signed [S_WIDTH-1:0]                  im2,
    output logic signed                                valid_o
);
    //------------------------------------------------------------------------

    localparam pointer_width = $clog2 (FRAME_LENGTH);

    //------------------------------------------------------------------------

    // Счётчик для мультиплексирования
    logic [pointer_width - 1:0] counter;
    always_ff @ (posedge clk or negedge arstn)
        if (!arstn)
        begin
            counter <= 'b0;
            valid_o <= 'b0;
        end
        else if (valid_i)
        begin
            if (counter == (FRAME_LENGTH - 1))
            begin
                counter <= '0;
                valid_o <= 'b1;
            end
            else
            begin
                counter <= counter + 1'b1;
                valid_o <= 'b0;
            end
        end

    //------------------------------------------------------------------------

    // RE

    logic signed [S_WIDTH-1:0] psumm_i_re1;
    logic                valid_psumm_i_re1;

    logic signed [S_WIDTH-1:0] psumm_o_re1;
    logic                 valid_psumm_o_re1;

    assign psumm_i_re1       = (counter == 0) ? 'b0 : psumm_o_re1;
    assign valid_psumm_i_re1 = 'b1;

    logic signed [W_WIDTH-1:0] weight_re;
    assign weight_re = w_re[counter];

    syst_node #(
        .W_WIDTH  (W_WIDTH),
        .X_WIDTH  (X_WIDTH),
        .SI_WIDTH (S_WIDTH),
        .SO_WIDTH (S_WIDTH)
    ) re_node1 (
        .clk           (clk),
        .arstn         (arstn),
        .enable        (valid_i),
        .weight_i      (weight_re),

        .psumm_i       (psumm_i_re1),
        .valid_psumm_i (valid_psumm_i_re1),

        .x_i           (x1),
        .valid_x_i     (valid_i),

        .psumm_o       (psumm_o_re1),
        .valid_o       (valid_psumm_o_re1)
    );
    assign re1 = psumm_o_re1;

    //------------------------------------------------------------------------

    // IM

    logic signed [S_WIDTH-1:0] psumm_i_im1;
    logic                valid_psumm_i_im1;

    logic signed [S_WIDTH-1:0] psumm_o_im1;
    logic                 valid_psumm_o_im1;

    assign psumm_i_im1       = (counter == 0) ? 'b0 : psumm_o_im1;
    assign valid_psumm_i_im1 = 'b1;

    logic signed [W_WIDTH-1:0] weight_im;
    assign weight_im = w_im[counter];

    syst_node #(
        .W_WIDTH  (W_WIDTH),
        .X_WIDTH  (X_WIDTH),
        .SI_WIDTH (S_WIDTH),
        .SO_WIDTH (S_WIDTH)
    ) im_node1 (
        .clk           (clk),
        .arstn         (arstn),
        .enable        (valid_i),
        .weight_i      (weight_im),

        .psumm_i       (psumm_i_im1),
        .valid_psumm_i (valid_psumm_i_im1),

        .x_i           (x1),
        .valid_x_i     (valid_i),

        .psumm_o       (psumm_o_im1),
        .valid_o       (valid_psumm_o_im1)
    );
    assign im1 = psumm_o_im1;

    //------------------------------------------------------------------------

    // RE

    logic signed [S_WIDTH-1:0] psumm_i_re2;
    logic                valid_psumm_i_re2;

    logic signed [S_WIDTH-1:0] psumm_o_re2;
    logic                 valid_psumm_o_re2;

    assign psumm_i_re2       = (counter == 0) ? 'b0 : psumm_o_re2;
    assign valid_psumm_i_re2 = 'b1;

    syst_node #(
        .W_WIDTH  (W_WIDTH),
        .X_WIDTH  (X_WIDTH),
        .SI_WIDTH (S_WIDTH),
        .SO_WIDTH (S_WIDTH)
    ) re_node2 (
        .clk           (clk),
        .arstn         (arstn),
        .enable        (valid_i),
        .weight_i      (weight_re),

        .psumm_i       (psumm_i_re2),
        .valid_psumm_i (valid_psumm_i_re2),

        .x_i           (x2),
        .valid_x_i     (valid_i),

        .psumm_o       (psumm_o_re2),
        .valid_o       (valid_psumm_o_re2)
    );
    assign re2 = psumm_o_re2;

    //------------------------------------------------------------------------

    // IM

    logic signed [S_WIDTH-1:0] psumm_i_im2;
    logic                valid_psumm_i_im2;

    logic signed [S_WIDTH-1:0] psumm_o_im2;
    logic                 valid_psumm_o_im2;

    assign psumm_i_im2       = (counter == 0) ? 'b0 : psumm_o_im2;
    assign valid_psumm_i_im2 = 'b1;

    syst_node #(
        .W_WIDTH  (W_WIDTH),
        .X_WIDTH  (X_WIDTH),
        .SI_WIDTH (S_WIDTH),
        .SO_WIDTH (S_WIDTH)
    ) im_node2 (
        .clk           (clk),
        .arstn         (arstn),
        .enable        (valid_i),
        .weight_i      (weight_im),

        .psumm_i       (psumm_i_im2),
        .valid_psumm_i (valid_psumm_i_im2),

        .x_i           (x2),
        .valid_x_i     (valid_i),

        .psumm_o       (psumm_o_im2),
        .valid_o       (valid_psumm_o_im2)
    );
    assign im2 = psumm_o_im2;

    

endmodule

fft/serial_fft_coral/testbench.sv
`timescale 1ns/1ps

module a
#(
    parameter W_WIDTH  = 16,
    parameter X_WIDTH  = 16,
    parameter S_WIDTH  = 32,

    parameter FRAME_LENGTH = 10
)
(
    input  logic                                       clk,
    input  logic                                       arstn,

    input  logic                                       valid_i,
    input  logic signed [X_WIDTH-1:0]                  x1,
    input  logic signed [X_WIDTH-1:0]                  x2,
    
    output logic signed [S_WIDTH-1:0]                  re1,
    output logic signed [S_WIDTH-1:0]                  im1,
    output logic signed [S_WIDTH-1:0]                  re2,
    output logic signed [S_WIDTH-1:0]                  im2,
    output logic signed                                valid_o
);
    logic signed [W_WIDTH-1:0] w_re [FRAME_LENGTH-1:0];
    logic signed [W_WIDTH-1:0] w_im [FRAME_LENGTH-1:0];
    
    initial $readmemb(".\\weigths\\w_re.txt", w_re);
    initial $readmemb(".\\weigths\\w_im.txt", w_im);
    
    serial_fft_coral #(
        .W_WIDTH  (W_WIDTH),
        .X_WIDTH  (X_WIDTH),
        .S_WIDTH  (S_WIDTH),
        .FRAME_LENGTH (FRAME_LENGTH)
    ) node (
        .clk           (clk   ),
        .arstn         (arstn ),
        .w_re          (w_re  ),
        .w_im          (w_im  ),

        .valid_i       (valid_i),
        .x1            (x1      ),
        .x2            (x2),

        .re1            (re1),
        .im1            (im1),
        .re2            (re2),
        .im2            (im2),
        .valid_o       (valid_o)
    );
endmodule

module testbench;
    // Подключение
    localparam W_WIDTH  = 16;
    localparam X_WIDTH  = 16;
    localparam S_WIDTH  = 32;
    localparam FRAME_LENGTH = 4;

    logic                                        clk;
    logic                                        arstn;

    logic                                        valid_i;
    logic signed [X_WIDTH-1:0]                   x1;
    logic signed [X_WIDTH-1:0]                   x2;

    logic signed [S_WIDTH-1:0]                   re1;
    logic signed [S_WIDTH-1:0]                   im1;
    logic signed [S_WIDTH-1:0]                   re2;
    logic signed [S_WIDTH-1:0]                   im2;
    logic                                        valid_o;

    a #(
        .W_WIDTH  (W_WIDTH),
        .X_WIDTH  (X_WIDTH),
        .S_WIDTH  (S_WIDTH),
        .FRAME_LENGTH (FRAME_LENGTH)
    ) node (
        .clk           (clk   ),
        .arstn         (arstn ),

        .valid_i       (valid_i),
        .x1            (x1     ),
        .x2            (x2     ),

        .re1            (re1),
        .im1            (im1),
        .re2            (re2),
        .im2            (im2),
        .valid_o       (valid_o)
    );

    initial begin
        $dumpfile("serial_fft_coral.vcd");
        $dumpvars;
    end
    // Запись значений в веса

    // Генерация clk
    parameter CLK_PERIOD = 20; // 50 МГц
    initial begin
        clk <= 0;
        forever begin
            #(CLK_PERIOD / 2); clk <= ~clk;
        end
    end

    //Генерация rst
    initial begin
        arstn <= 0;
        @(posedge clk);
        @(posedge clk);
        @(posedge clk);
        arstn <= 1;
    end

    // Генерация входных сигналов
    initial begin
        valid_i <= 'b0;

        wait(arstn);
        @(posedge clk);
    //---------------------------------------------------------------------------------------------
        //1
        @(posedge clk);
        valid_i <= 'b1;
        x1 <= 'd1;
        x2 <= 'd2;

        @(posedge clk);
        x1 <= 'd3;
        x2 <= 'd4;

        @(posedge clk);
        x1 <= 'd5;
        x2 <= 'd6;

        @(posedge clk);
        x1 <= 'd7;
        x2 <= 'd8;

        @(posedge clk);
        @(posedge clk);
        @(posedge clk);

        $finish;
    end
    
    // Проверка
    // initial begin
    //     wait(~arstn);
    //     @(posedge clk);
    //     @(posedge clk);
    // //---------------------------------------------------------------------------------------------
    //     repeat (32)
    //     begin
    //         @(posedge clk);
    //         if ($signed(psumm_o) != ($signed(psumm_i) + $signed(weight_i) * $signed(x_i) )) begin
    //             $display($signed(psumm_o));
    //             $display(($signed(psumm_i) + $signed(weight_i) * $signed(x_i)));
    //             $display($signed(psumm_i));
    //             $display($signed(weight_i));
    //             $display($signed(x_i));
    //             $error("BAD");
    //         end
    //         else begin
    //             $display("PASS");
    //             // $display($signed(psumm_o));
    //             // $display($signed(psumm_i));
    //             // $display($signed(weight_i));
    //             // $display($signed(x_i));
    //         end
    //     end
    // //---------------------------------------------------------------------------------------------
    //     @(posedge clk);
    //     @(posedge clk);
    //     @(posedge clk);
    //     $finish;
    // end
endmodule

fft/serial_fft_coral.vcd
$date
	Thu Mar 20 15:39:01 2025
$end
$version
	Icarus Verilog
$end
$timescale
	1ps
$end
$scope module testbench $end
$var wire 1 ! valid_o $end
$var wire 32 " re2 [31:0] $end
$var wire 32 # re1 [31:0] $end
$var wire 32 $ im2 [31:0] $end
$var wire 32 % im1 [31:0] $end
$var reg 1 & arstn $end
$var reg 1 ' clk $end
$var reg 1 ( valid_i $end
$var reg 16 ) x1 [15:0] $end
$var reg 16 * x2 [15:0] $end
$scope module node $end
$var wire 1 & arstn $end
$var wire 1 ' clk $end
$var wire 1 ( valid_i $end
$var wire 16 + x1 [15:0] $end
$var wire 16 , x2 [15:0] $end
$var wire 1 ! valid_o $end
$var wire 32 - re2 [31:0] $end
$var wire 32 . re1 [31:0] $end
$var wire 32 / im2 [31:0] $end
$var wire 32 0 im1 [31:0] $end
$scope module node $end
$var wire 1 & arstn $end
$var wire 1 ' clk $end
$var wire 32 1 im1 [31:0] $end
$var wire 32 2 im2 [31:0] $end
$var wire 32 3 re1 [31:0] $end
$var wire 32 4 re2 [31:0] $end
$var wire 1 ( valid_i $end
$var wire 1 5 valid_psumm_i_im1 $end
$var wire 1 6 valid_psumm_i_im2 $end
$var wire 1 7 valid_psumm_i_re1 $end
$var wire 1 8 valid_psumm_i_re2 $end
$var wire 16 9 weight_im [15:0] $end
$var wire 16 : weight_re [15:0] $end
$var wire 16 ; x1 [15:0] $end
$var wire 16 < x2 [15:0] $end
$var wire 1 = valid_psumm_o_re2 $end
$var wire 1 > valid_psumm_o_re1 $end
$var wire 1 ? valid_psumm_o_im2 $end
$var wire 1 @ valid_psumm_o_im1 $end
$var wire 32 A psumm_o_re2 [31:0] $end
$var wire 32 B psumm_o_re1 [31:0] $end
$var wire 32 C psumm_o_im2 [31:0] $end
$var wire 32 D psumm_o_im1 [31:0] $end
$var wire 32 E psumm_i_re2 [31:0] $end
$var wire 32 F psumm_i_re1 [31:0] $end
$var wire 32 G psumm_i_im2 [31:0] $end
$var wire 32 H psumm_i_im1 [31:0] $end
$var reg 9 I counter [8:0] $end
$var reg 1 ! valid_o $end
$scope module im_node1 $end
$var wire 1 & arstn $end
$var wire 1 ' clk $end
$var wire 1 J en $end
$var wire 1 ( enable $end
$var wire 32 K psumm_i [31:0] $end
$var wire 1 L valid $end
$var wire 1 5 valid_psumm_i $end
$var wire 1 ( valid_x_i $end
$var wire 1 M valid_x_o $end
$var wire 16 N weight_i [15:0] $end
$var wire 16 O x_i [15:0] $end
$var wire 16 P x_o [15:0] $end
$var wire 32 Q weight_mult [31:0] $end
$var wire 32 R psumm_o [31:0] $end
$var reg 32 S psumm_reg [31:0] $end
$var reg 1 @ valid_o $end
$upscope $end
$scope module im_node2 $end
$var wire 1 & arstn $end
$var wire 1 ' clk $end
$var wire 1 T en $end
$var wire 1 ( enable $end
$var wire 32 U psumm_i [31:0] $end
$var wire 1 V valid $end
$var wire 1 6 valid_psumm_i $end
$var wire 1 ( valid_x_i $end
$var wire 1 W valid_x_o $end
$var wire 16 X weight_i [15:0] $end
$var wire 16 Y x_i [15:0] $end
$var wire 16 Z x_o [15:0] $end
$var wire 32 [ weight_mult [31:0] $end
$var wire 32 \ psumm_o [31:0] $end
$var reg 32 ] psumm_reg [31:0] $end
$var reg 1 ? valid_o $end
$upscope $end
$scope module re_node1 $end
$var wire 1 & arstn $end
$var wire 1 ' clk $end
$var wire 1 ^ en $end
$var wire 1 ( enable $end
$var wire 32 _ psumm_i [31:0] $end
$var wire 1 ` valid $end
$var wire 1 7 valid_psumm_i $end
$var wire 1 ( valid_x_i $end
$var wire 1 a valid_x_o $end
$var wire 16 b weight_i [15:0] $end
$var wire 16 c x_i [15:0] $end
$var wire 16 d x_o [15:0] $end
$var wire 32 e weight_mult [31:0] $end
$var wire 32 f psumm_o [31:0] $end
$var reg 32 g psumm_reg [31:0] $end
$var reg 1 > valid_o $end
$upscope $end
$scope module re_node2 $end
$var wire 1 & arstn $end
$var wire 1 ' clk $end
$var wire 1 h en $end
$var wire 1 ( enable $end
$var wire 32 i psumm_i [31:0] $end
$var wire 1 j valid $end
$var wire 1 8 valid_psumm_i $end
$var wire 1 ( valid_x_i $end
$var wire 1 k valid_x_o $end
$var wire 16 l weight_i [15:0] $end
$var wire 16 m x_i [15:0] $end
$var wire 16 n x_o [15:0] $end
$var wire 32 o weight_mult [31:0] $end
$var wire 32 p psumm_o [31:0] $end
$var reg 32 q psumm_reg [31:0] $end
$var reg 1 = valid_o $end
$upscope $end
$upscope $end
$upscope $end
$upscope $end
$enddefinitions $end
#0
$dumpvars
bx q
bx p
bx o
bx n
bx m
b10000000000 l
0k
0j
b0 i
0h
bx g
bx f
bx e
bx d
bx c
b10000000000 b
0a
0`
b0 _
0^
bx ]
bx \
bx [
bx Z
bx Y
b0 X
0W
0V
b0 U
0T
bx S
bx R
bx Q
bx P
bx O
b0 N
0M
0L
b0 K
0J
b0 I
b0 H
b0 G
b0 F
b0 E
bx D
bx C
bx B
bx A
0@
0?
0>
0=
bx <
bx ;
b10000000000 :
b0 9
18
17
16
15
bx 4
bx 3
bx 2
bx 1
bx 0
bx /
bx .
bx -
bx ,
bx +
bx *
bx )
0(
0'
0&
bx %
bx $
bx #
bx "
0!
$end
#10000
1'
#20000
0'
#30000
1'
#40000
0'
#50000
1&
1'
#60000
0'
#70000
1'
#80000
0'
#90000
1J
1T
1^
1h
1L
1V
1`
1j
b11111111111 P
b0 Q
b11111111111 d
b111111111110000000000 e
b11111111111 )
b11111111111 +
b11111111111 ;
b11111111111 O
b11111111111 c
1M
1W
1a
1k
1(
1'
#100000
0'
#110000
b111111111110000000000 F
b111111111110000000000 _
bx E
bx i
bx G
bx U
1>
1@
1=
1?
b1111111110 :
b1111111110 b
b1111111110 l
b100101111011010100 Q
b1000111 9
b1000111 N
b1000111 X
b1 I
b0 %
b0 0
b0 1
b0 D
b0 R
b0 S
b111111111110000000000 #
b111111111110000000000 .
b111111111110000000000 3
b111111111110000000000 B
b111111111110000000000 f
b111111111110000000000 g
b100010001100 P
b100010001100 d
b1000100001111011101000 e
b100010001100 )
b100010001100 +
b100010001100 ;
b100010001100 O
b100010001100 c
1'
#120000
0'
#130000
b10000100001101011101000 F
b10000100001101011101000 _
b100101111011010100 H
b100101111011010100 K
b1111110110 :
b1111110110 b
b1111110110 l
b10001111 9
b10001111 N
b10001111 X
b10 I
b100100011000 P
b1010001010001101000 Q
b100100011000 d
b1001000000010100010000 e
b100100011000 )
b100100011000 +
b100100011000 ;
b100100011000 O
b100100011000 c
b10000100001101011101000 #
b10000100001101011101000 .
b10000100001101011101000 3
b10000100001101011101000 B
b10000100001101011101000 f
b10000100001101011101000 g
b100101111011010100 %
b100101111011010100 0
b100101111011010100 1
b100101111011010100 D
b100101111011010100 R
b100101111011010100 S
1'
#140000
0'
#150000
b1110111001100111100 H
b1110111001100111100 K
b11001100001111111111000 F
b11001100001111111111000 _
b1111101010 :
b1111101010 b
b1111101010 l
b11010101 9
b11010101 N
b11010101 X
b11 I
b1110111001100111100 %
b1110111001100111100 0
b1110111001100111100 1
b1110111001100111100 D
b1110111001100111100 R
b1110111001100111100 S
b11001100001111111111000 #
b11001100001111111111000 .
b11001100001111111111000 3
b11001100001111111111000 B
b11001100001111111111000 f
b11001100001111111111000 g
b100110100010 P
b10000000001111001010 Q
b100110100010 d
b1001011011010000010100 e
b100110100010 )
b100110100010 +
b100110100010 ;
b100110100010 O
b100110100010 c
1'
#160000
0'
#170000
b100010111101010000001100 F
b100010111101010000001100 _
b11110111011100000110 H
b11110111011100000110 K
b1111011000 :
b1111011000 b
b1111011000 l
b100011010 9
b100011010 N
b100011010 X
b100 I
b101000101011 P
b10110011001101011110 Q
b101000101011 d
b1001110001010101001000 e
b101000101011 )
b101000101011 +
b101000101011 ;
b101000101011 O
b101000101011 c
b100010111101010000001100 #
b100010111101010000001100 .
b100010111101010000001100 3
b100010111101010000001100 B
b100010111101010000001100 f
b100010111101010000001100 g
b11110111011100000110 %
b11110111011100000110 0
b11110111011100000110 1
b11110111011100000110 D
b11110111011100000110 R
b11110111011100000110 S
1'
#180000
0'
#190000
b110101010101001100100 H
b110101010101001100100 K
b101100101110100101010100 F
b101100101110100101010100 _
b1111000010 :
b1111000010 b
b1111000010 l
b101011110 9
b101011110 N
b101011110 X
b101 I
b110101010101001100100 %
b110101010101001100100 0
b110101010101001100100 1
b110101010101001100100 D
b110101010101001100100 R
b110101010101001100100 S
b101100101110100101010100 #
b101100101110100101010100 .
b101100101110100101010100 3
b101100101110100101010100 B
b101100101110100101010100 f
b101100101110100101010100 g
b101010110001 P
b11101001110111111110 Q
b101010110001 d
b1010000010110100100010 e
b101010110001 )
b101010110001 +
b101010110001 ;
b101010110001 O
b101010110001 c
1'
#200000
0'
#210000
b110110110001011001110110 F
b110110110001011001110110 _
b1010010100100001100010 H
b1010010100100001100010 K
b1110100111 :
b1110100111 b
b1110100111 l
b110100000 9
b110100000 N
b110100000 X
b110 I
b101100110100 P
b100100011010010000000 Q
b101100110100 d
b1010001110101011101100 e
b101100110100 )
b101100110100 +
b101100110100 ;
b101100110100 O
b101100110100 c
b110110110001011001110110 #
b110110110001011001110110 .
b110110110001011001110110 3
b110110110001011001110110 B
b110110110001011001110110 f
b110110110001011001110110 g
b1010010100100001100010 %
b1010010100100001100010 0
b1010010100100001100010 1
b1010010100100001100010 D
b1010010100100001100010 R
b1010010100100001100010 S
1'
#220000
0'
#230000
b1110110111110011100010 H
b1110110111110011100010 K
b1000001000000000101100010 F
b1000001000000000101100010 _
b1110001000 :
b1110001000 b
b1110001000 l
b111100001 9
b111100001 N
b111100001 X
b111 I
b1110110111110011100010 %
b1110110111110011100010 0
b1110110111110011100010 1
b1110110111110011100010 D
b1110110111110011100010 R
b1110110111110011100010 S
b1000001000000000101100010 #
b1000001000000000101100010 .
b1000001000000000101100010 3
b1000001000000000101100010 B
b1000001000000000101100010 f
b1000001000000000101100010 g
b101110110010 P
b101011111100101110010 Q
b101110110010 d
b1010010100110010010000 e
b101110110010 )
b101110110010 +
b101110110010 ;
b101110110010 O
b101110110010 c
1'
#240000
0'
#250000
b1001011010100110111110010 F
b1001011010100110111110010 _
b10100010111011001010100 H
b10100010111011001010100 K
b1101100100 :
b1101100100 b
b1101100100 l
b1000011111 9
b1000011111 N
b1000011111 X
b1000 I
b110000101101 P
b110011101001101110011 Q
b110000101101 d
b1010010100100010010100 e
b110000101101 )
b110000101101 +
b110000101101 ;
b110000101101 O
b110000101101 c
b1001011010100110111110010 #
b1001011010100110111110010 .
b1001011010100110111110010 3
b1001011010100110111110010 B
b1001011010100110111110010 f
b1001011010100110111110010 g
b10100010111011001010100 %
b10100010111011001010100 0
b10100010111011001010100 1
b10100010111011001010100 D
b10100010111011001010100 R
b10100010111011001010100 S
1'
#260000
0'
#270000
b11010110100100111000111 H
b11010110100100111000111 K
b1010101101001011010000110 F
b1010101101001011010000110 _
b1100111100 :
b1100111100 b
b1100111100 l
b1001011010 9
b1001011010 N
b1001011010 X
b1001 I
b11010110100100111000111 %
b11010110100100111000111 0
b11010110100100111000111 1
b11010110100100111000111 D
b11010110100100111000111 R
b11010110100100111000111 S
b1010101101001011010000110 #
b1010101101001011010000110 .
b1010101101001011010000110 3
b1010101101001011010000110 B
b1010101101001011010000110 f
b1010101101001011010000110 g
b110010100010 P
b111011011010011110100 Q
b110010100010 d
b1010001101101111111000 e
b110010100010 )
b110010100010 +
b110010100010 ;
b110010100010 O
b110010100010 c
1'
#280000
0'
#290000
b1011111110111001001111110 F
b1011111110111001001111110 _
b100010001111111010111011 H
b100010001111111010111011 K
b1100010000 :
b1100010000 b
b1100010000 l
b1010010010 9
b1010010010 N
b1010010010 X
b1010 I
b110100010010 P
b1000011001100001000100 Q
b110100010010 d
b1010000000011100100000 e
b110100010010 )
b110100010010 +
b110100010010 ;
b110100010010 O
b110100010010 c
b1011111110111001001111110 #
b1011111110111001001111110 .
b1011111110111001001111110 3
b1011111110111001001111110 B
b1011111110111001001111110 f
b1011111110111001001111110 g
b100010001111111010111011 %
b100010001111111010111011 0
b100010001111111010111011 1
b100010001111111010111011 D
b100010001111111010111011 R
b100010001111111010111011 S
1'
#300000
0'
#310000
b101010101001011011111111 H
b101010101001011011111111 K
b1101001110111100110011110 F
b1101001110111100110011110 _
b1011100001 :
b1011100001 b
b1011100001 l
b1011000111 9
b1011000111 N
b1011000111 X
b1011 I
b101010101001011011111111 %
b101010101001011011111111 0
b101010101001011011111111 1
b101010101001011011111111 D
b101010101001011011111111 R
b101010101001011011111111 S
b1101001110111100110011110 #
b1101001110111100110011110 .
b1101001110111100110011110 3
b1101001110111100110011110 B
b1101001110111100110011110 f
b1101001110111100110011110 g
b110101111100 P
b1001010111001101100100 Q
b110101111100 d
b1001101101000111111100 e
b110101111100 )
b110101111100 +
b110101111100 ;
b110101111100 O
b110101111100 c
1'
#320000
0'
#330000
b1110011100100101110011010 F
b1110011100100101110011010 _
b110100000000101001100011 H
b110100000000101001100011 K
b1010101101 :
b1010101101 b
b1010101101 l
b1011111001 9
b1011111001 N
b1011111001 X
b1100 I
b110111011111 P
b1010010011101111100111 Q
b110111011111 d
b1001010001110110110011 e
b110111011111 )
b110111011111 +
b110111011111 ;
b110111011111 O
b110111011111 c
b1110011100100101110011010 #
b1110011100100101110011010 .
b1110011100100101110011010 3
b1110011100100101110011010 B
b1110011100100101110011010 f
b1110011100100101110011010 g
b110100000000101001100011 %
b110100000000101001100011 0
b110100000000101001100011 1
b110100000000101001100011 D
b110100000000101001100011 R
b110100000000101001100011 S
1'
#340000
0'
#350000
b111110010100011001001010 H
b111110010100011001001010 K
b1111100110110100101001101 F
b1111100110110100101001101 _
b1001110110 :
b1001110110 b
b1001110110 l
b1100100111 9
b1100100111 N
b1100100111 X
b1101 I
b111110010100011001001010 %
b111110010100011001001010 0
b111110010100011001001010 1
b111110010100011001001010 D
b111110010100011001001010 R
b111110010100011001001010 S
b1111100110110100101001101 #
b1111100110110100101001101 .
b1111100110110100101001101 3
b1111100110110100101001101 B
b1111100110110100101001101 f
b1111100110110100101001101 g
b111000111010 P
b1011001101100011010110 Q
b111000111010 d
b1000110000001010111100 e
b111000111010 )
b111000111010 +
b111000111010 ;
b111000111010 O
b111000111010 c
1'
#360000
0'
#370000
b10000101100110110000001001 F
b10000101100110110000001001 _
b1001001100001111100100000 H
b1001001100001111100100000 K
b1000111101 :
b1000111101 b
b1000111101 l
b1101010001 9
b1101010001 N
b1101010001 X
b1110 I
b111010001111 P
b1100000100100000111111 Q
b111010001111 d
b1000001001011000010011 e
b111010001111 )
b111010001111 +
b111010001111 ;
b111010001111 O
b111010001111 c
b10000101100110110000001001 #
b10000101100110110000001001 .
b10000101100110110000001001 3
b10000101100110110000001001 B
b10000101100110110000001001 f
b10000101100110110000001001 g
b1001001100001111100100000 %
b1001001100001111100100000 0
b1001001100001111100100000 1
b1001001100001111100100000 D
b1001001100001111100100000 R
b1001001100001111100100000 S
1'
#380000
0'
#390000
b1010101100110011101011111 H
b1010101100110011101011111 K
b10001101110000001000011100 F
b10001101110000001000011100 _
b1000000000 :
b1000000000 b
b1000000000 l
b1101110111 9
b1101110111 N
b1101110111 X
b1111 I
b1010101100110011101011111 %
b1010101100110011101011111 0
b1010101100110011101011111 1
b1010101100110011101011111 D
b1010101100110011101011111 R
b1010101100110011101011111 S
b10001101110000001000011100 #
b10001101110000001000011100 .
b10001101110000001000011100 3
b10001101110000001000011100 B
b10001101110000001000011100 f
b10001101110000001000011100 g
b111011011011 P
b1100110111100011001101 Q
b111011011011 d
b111011011011000000000 e
b111011011011 )
b111011011011 +
b111011011011 ;
b111011011011 O
b111011011011 c
1'
#400000
0'
#410000
b10010101001011100000011100 F
b10010101001011100000011100 _
b1100010011110000000101100 H
b1100010011110000000101100 K
b111000001 :
b111000001 b
b111000001 l
b1110011000 9
b1110011000 N
b1110011000 X
b10000 I
b111100011111 P
b1101100101011101101000 Q
b111100011111 d
b110101000010101011111 e
b111100011111 )
b111100011111 +
b111100011111 ;
b111100011111 O
b111100011111 c
b10010101001011100000011100 #
b10010101001011100000011100 .
b10010101001011100000011100 3
b10010101001011100000011100 B
b10010101001011100000011100 f
b10010101001011100000011100 g
b1100010011110000000101100 %
b1100010011110000000101100 0
b1100010011110000000101100 1
b1100010011110000000101100 D
b1100010011110000000101100 R
b1100010011110000000101100 S
1'
#420000
0'
#430000
b1110000000011011110010100 H
b1110000000011011110010100 K
b10011011110011110101111011 F
b10011011110011110101111011 _
b110000000 :
b110000000 b
b110000000 l
b1110110101 9
b1110110101 N
b1110110101 X
b10001 I
b1110000000011011110010100 %
b1110000000011011110010100 0
b1110000000011011110010100 1
b1110000000011011110010100 D
b1110000000011011110010100 R
b1110000000011011110010100 S
b10011011110011110101111011 #
b10011011110011110101111011 .
b10011011110011110101111011 3
b10011011110011110101111011 B
b10011011110011110101111011 f
b10011011110011110101111011 g
b111101011011 P
b1110001110110001010111 Q
b111101011011 d
b101110000100010000000 e
b111101011011 )
b111101011011 +
b111101011011 ;
b111101011011 O
b111101011011 c
1'
#440000
0'
#450000
b10100001100100010111111011 F
b10100001100100010111111011 _
b1111110010010001111101011 H
b1111110010010001111101011 K
b100111100 :
b100111100 b
b100111100 l
b1111001110 9
b1111001110 N
b1111001110 X
b10010 I
b111110001101 P
b1110110010101001110110 Q
b111110001101 d
b100110011001000001100 e
b111110001101 )
b111110001101 +
b111110001101 ;
b111110001101 O
b111110001101 c
b10100001100100010111111011 #
b10100001100100010111111011 .
b10100001100100010111111011 3
b10100001100100010111111011 B
b10100001100100010111111011 f
b10100001100100010111111011 g
b1111110010010001111101011 %
b1111110010010001111101011 0
b1111110010010001111101011 1
b1111110010010001111101011 D
b1111110010010001111101011 R
b1111110010010001111101011 S
1'
#460000
0'
#470000
b10001101000100111001100001 H
b10001101000100111001100001 K
b10100110010111100000000111 F
b10100110010111100000000111 _
b11111000 :
b11111000 b
b11111000 l
b1111100010 9
b1111100010 N
b1111100010 X
b10011 I
b10001101000100111001100001 %
b10001101000100111001100001 0
b10001101000100111001100001 1
b10001101000100111001100001 D
b10001101000100111001100001 R
b10001101000100111001100001 S
b10100110010111100000000111 #
b10100110010111100000000111 .
b10100110010111100000000111 3
b10100110010111100000000111 B
b10100110010111100000000111 f
b10100110010111100000000111 g
b111110110111 P
b1111010000010010001110 Q
b111110110111 d
b11110011100101001000 e
b111110110111 )
b111110110111 +
b111110110111 ;
b111110110111 O
b111110110111 c
1'
#480000
0'
#490000
b10101010001011000101001111 F
b10101010001011000101001111 _
b10011100010101001011101111 H
b10011100010101001011101111 K
b10110010 :
b10110010 b
b10110010 l
b1111110000 9
b1111110000 N
b1111110000 X
b10100 I
b111111010111 P
b1111100101111010010000 Q
b111111010111 d
b10110000001101111110 e
b111111010111 )
b111111010111 +
b111111010111 ;
b111111010111 O
b111111010111 c
b10101010001011000101001111 #
b10101010001011000101001111 .
b10101010001011000101001111 3
b10101010001011000101001111 B
b10101010001011000101001111 f
b10101010001011000101001111 g
b10011100010101001011101111 %
b10011100010101001011101111 0
b10011100010101001011101111 1
b10011100010101001011101111 D
b10011100010101001011101111 R
b10011100010101001011101111 S
1'
#500000
0'
