computing_cascade/mean/mean.sv
module mean 
#(
    parameter WIDTH = 32,
    parameter DEPTH_WIDTH = 33,
    parameter N = 1,             // Количество эллементов (степень двойки)
    parameter SIG = 0
) 
(
    input logic clk,
    input logic rstn,

    input logic i_vld,
    input logic [WIDTH-1:0] i_data,

    output logic o_vld,
    output logic [WIDTH-1:0] o_data
);

    localparam cnt_max = (1 << N) - 1;
    logic [N-1:0] cnt;
    logic enable;
    assign enable = cnt == cnt_max;
    always_ff @(posedge clk) begin
        if (!rstn) cnt <= 'b0;
        else if (i_vld) begin
            cnt <= cnt + 'b1;
        end
    end

    logic [DEPTH_WIDTH-1:0] sum;
    logic rstn_sum;
    assign rstn_sum = |cnt;
    generate
        if (SIG == 0) begin
            always_ff @(posedge clk) begin
                if(~rstn_sum)   sum <= i_data;
                else if (i_vld) sum <= sum + i_data;
            end
            assign o_data = sum >> N;
        end
        else begin
            always_ff @(posedge clk) begin
                if(~rstn_sum)   sum <= {{(DEPTH_WIDTH-WIDTH){i_data[WIDTH-1]}}, i_data};
                else if (i_vld) sum <= sum + {{(DEPTH_WIDTH-WIDTH){i_data[WIDTH-1]}}, i_data};
            end
            assign o_data = {{(N){sum[DEPTH_WIDTH-1]}}, sum[DEPTH_WIDTH-1:N]};
        end
    endgenerate

    always_ff @(posedge clk) begin
        if (!rstn)       o_vld <= 'b0;
        else if (enable) o_vld <= i_vld;
        else             o_vld <= 'b0;
    end
    
endmodule

computing_cascade/mean/testbench.sv
`timescale 1ns/1ps

module testbench;
    // Подключение
    localparam WIDTH  = 32;
    localparam DEPTH_WIDTH  = 33;
    localparam N = 1;

    logic                                        clk;
    logic                                        arstn;

    logic                                        i_vld;
    logic [WIDTH-1:0]                   i_data;

    logic                                        o_vld;
    logic [WIDTH-1:0]                   o_data;

    mean #(
        .WIDTH  (WIDTH),
        .DEPTH_WIDTH  (DEPTH_WIDTH),
        .N (N)
    ) m (
        .clk         (clk   ),
        .rstn       (arstn ),

        .i_vld       (i_vld),
        .i_data      (i_data),

        .o_vld       (o_vld),
        .o_data      (o_data)
    );

    initial begin
        $dumpfile("mean.vcd");
        $dumpvars;
    end
    // Запись значений в веса

    // Генерация clk
    parameter CLK_PERIOD = 20; // 50 МГц
    initial begin
        clk <= 0;
        forever begin
            #(CLK_PERIOD / 2); clk <= ~clk;
        end
    end

    //Генерация rst
    initial begin
        arstn <= 0;
        @(posedge clk);
        @(posedge clk);
        @(posedge clk);
        arstn <= 1;
    end

    // Генерация входных сигналов
    initial begin
        i_vld <= 'b0;

        wait(arstn);
        @(posedge clk);
    //---------------------------------------------------------------------------------------------
        //1
        @(posedge clk);
        i_vld <= 'b1;
        i_data <= 'd1;

        @(posedge clk);
        i_data <= 'd2;

        @(posedge clk);
        i_data <= 'd3;

        @(posedge clk);
        i_data <= 'd4;

        @(posedge clk);
        @(posedge clk);
        @(posedge clk);
        @(posedge clk);
        @(posedge clk);

        $finish;
    end
    
endmodule

computing_cascade/mean.vcd
$date
	Sat Mar 29 12:08:01 2025
$end
$version
	Icarus Verilog
$end
$timescale
	1ps
$end
$scope module testbench $end
$var wire 1 ! o_vld $end
$var wire 32 " o_data [31:0] $end
$var reg 1 # arstn $end
$var reg 1 $ clk $end
$var reg 32 % i_data [31:0] $end
$var reg 1 & i_vld $end
$scope module m $end
$var wire 1 $ clk $end
$var wire 32 ' i_data [31:0] $end
$var wire 1 & i_vld $end
$var wire 1 # rstn $end
$var wire 1 ( rstn_sum $end
$var wire 32 ) o_data [31:0] $end
$var wire 1 * enable $end
$var reg 1 + cnt $end
$var reg 1 ! o_vld $end
$var reg 33 , sum [32:0] $end
$upscope $end
$upscope $end
$enddefinitions $end
#0
$dumpvars
bx ,
x+
x*
bx )
x(
bx '
0&
bx %
0$
0#
bx "
x!
$end
#10000
0*
0(
0+
0!
1$
#20000
0$
#30000
b0xxxxxxxxxxxxxxxxxxxxxxxxxxxxxxx "
b0xxxxxxxxxxxxxxxxxxxxxxxxxxxxxxx )
b0xxxxxxxxxxxxxxxxxxxxxxxxxxxxxxxx ,
1$
#40000
0$
#50000
1#
1$
#60000
0$
#70000
1$
#80000
0$
#90000
b1 %
b1 '
1&
1$
#100000
0$
#110000
b0 "
b0 )
b1 ,
1*
1(
1+
b10 %
b10 '
1$
#120000
0$
#130000
b1 "
b1 )
b11 %
b11 '
0*
0(
0+
b11 ,
1!
1$
#140000
0$
#150000
0!
1*
1(
1+
b100 %
b100 '
1$
#160000
0$
#170000
b11 "
b11 )
0*
0(
0+
b111 ,
1!
1$
#180000
0$
#190000
b10 "
b10 )
0!
b100 ,
1*
1(
1+
1$
#200000
0$
#210000
b100 "
b100 )
0*
0(
0+
b1000 ,
1!
1$
#220000
0$
#230000
b10 "
b10 )
0!
b100 ,
1*
1(
1+
1$
#240000
0$
#250000
b100 "
b100 )
0*
0(
0+
b1000 ,
1!
1$
