postprocess/fix_point_div/fix_point_div.sv
module div 
#(
    parameter W_INTEGER_I    = 29,
    parameter W_FRACTIONAL_I = 3,

    parameter W_INTEGER_O    = 16,
    parameter W_FRACTIONAL_O = 16
)
(
    input  logic signed [W_INTEGER_I + W_FRACTIONAL_I - 1:0] a,
    input  logic signed [W_INTEGER_I + W_FRACTIONAL_I - 1:0] b,

    output logic signed [W_INTEGER_O + W_FRACTIONAL_O - 1:0] c
);
    wire signed [W_INTEGER_I + W_FRACTIONAL_I + W_FRACTIONAL_O - 1:0] a_extended;
    assign a_extended = a << W_FRACTIONAL_O;

    assign c = a_extended / b;
    
endmodule

postprocess/fix_point_div/testbench.sv
`timescale 1ns/1ps

module test;
    // Подключение

    logic                clk;
    logic                arstn;

    logic signed	[31:0] a, b;
    logic i_vld;

    logic signed	[31:0] c;
    logic o_vld;

    div tp (
        .a (a),
        .b (b),
        .c (c)
    );

    initial begin
        $dumpfile("div.vcd");
        $dumpvars;
    end

    // Генерация clk
    parameter CLK_PERIOD = 20; // 50 МГц
    initial begin
        clk <= 0;
        forever begin
            #(CLK_PERIOD / 2); clk <= ~clk;
        end
    end

    //Генерация rst
    initial begin
        arstn <= 0;
        @(posedge clk);
        @(posedge clk);
        @(posedge clk);
        arstn <= 1;
    end

    // Генерация входных сигналов
    initial begin

        wait(arstn);
        @(posedge clk);
    //---------------------------------------------------------------------------------------------
        @(posedge clk);

        a <= 32'd1 << 'd3;
        b <= 32'd1 << 'd3;

        @(posedge clk);
        a <= 32'd5 << 'd3;
        b <= 32'd1 << 'd3;

        @(posedge clk);
        a <= 32'd1 << 'd3;
        b <= 32'd5 << 'd3;

        @(posedge clk);
        a <= -32'd5 << 'd3;
        b <= 32'd1 << 'd3;

        @(posedge clk);
        a <= -32'd1 << 'd3;
        b <= 32'd5 << 'd3;

        @(posedge clk);
        a <= -32'd5 << 'd3;
        b <= -32'd1 << 'd3;

        @(posedge clk);
        a <= -32'd1 << 'd3;
        b <= -32'd5 << 'd3;

        @(posedge clk);
        $display("RESULTS");
        repeat(9) begin
            @(posedge clk);
            //$display("%d", o_phase);
        end

    //---------------------------------------------------------------------------------------------
        repeat(18) begin
            @(posedge clk);
        end
        @(posedge clk);
        @(posedge clk);
        @(posedge clk);
        $finish;
    end
endmodule

postprocess/div.vcd
$date
	Sun Mar 23 12:57:55 2025
$end
$version
	Icarus Verilog
$end
$timescale
	1ps
$end
$scope module test $end
$var wire 32 ! c [31:0] $end
$var reg 32 " a [31:0] $end
$var reg 1 # arstn $end
$var reg 32 $ b [31:0] $end
$var reg 1 % clk $end
$scope module tp $end
$var wire 32 & a [31:0] $end
$var wire 32 ' b [31:0] $end
$var wire 32 ( c [31:0] $end
$var wire 48 ) a_extended [47:0] $end
$upscope $end
$upscope $end
$enddefinitions $end
#0
$dumpvars
bx0000000000000000 )
bx (
bx '
bx &
0%
bx $
0#
bx "
bx !
$end
#10000
1%
#20000
0%
#30000
1%
#40000
0%
#50000
1#
1%
#60000
0%
#70000
1%
#80000
0%
#90000
b10000000000000000 !
b10000000000000000 (
b10000000000000000000 )
b1000 $
b1000 '
b1000 "
b1000 &
1%
#100000
0%
#110000
b1010000000000000000 !
b1010000000000000000 (
b1010000000000000000000 )
b101000 "
b101000 &
1%
#120000
0%
#130000
b11001100110011 !
b11001100110011 (
b10000000000000000000 )
b101000 $
b101000 '
b1000 "
b1000 &
1%
#140000
0%
#150000
b11111111111110110000000000000000 !
b11111111111110110000000000000000 (
b111111111111111111111111110110000000000000000000 )
b1000 $
b1000 '
b11111111111111111111111111011000 "
b11111111111111111111111111011000 &
1%
#160000
0%
#170000
b11111111111111111100110011001101 !
b11111111111111111100110011001101 (
b111111111111111111111111111110000000000000000000 )
b101000 $
b101000 '
b11111111111111111111111111111000 "
b11111111111111111111111111111000 &
1%
#180000
0%
#190000
b1010000000000000000 !
b1010000000000000000 (
b111111111111111111111111110110000000000000000000 )
b11111111111111111111111111111000 $
b11111111111111111111111111111000 '
b11111111111111111111111111011000 "
b11111111111111111111111111011000 &
1%
#200000
0%
#210000
b11001100110011 !
b11001100110011 (
b111111111111111111111111111110000000000000000000 )
b11111111111111111111111111011000 $
b11111111111111111111111111011000 '
b11111111111111111111111111111000 "
b11111111111111111111111111111000 &
1%
