postprocess/dec_to_polar/dec_to_polar.sv

module	topolar 
#(
    parameter WIDTH = 32
)
(
	input                              clk, 
	input                              rst, 
	
	input                              i_vld,
	input   logic signed [WIDTH - 1:0] i_x, 
	input   logic signed [WIDTH - 1:0] i_y,

	output  logic                      o_vld,
	output	logic signed [WIDTH - 1:0] o_mag,
	output	logic signed [31:0]	       o_phase
	);
	localparam NSTAGES = 16;
	//
	logic signed [31:0] cordic_angle [0:(NSTAGES-1)];
	assign	cordic_angle[ 0] = 32'h076b_19c1; //  26.565051 deg
	assign	cordic_angle[ 1] = 32'h03eb_6ebf; //  14.036243 deg
	assign	cordic_angle[ 2] = 32'h01fd_5ba9; //   7.125016 deg
	assign	cordic_angle[ 3] = 32'h00ff_aadd; //   3.576334 deg
	assign	cordic_angle[ 4] = 32'h007f_f556; //   1.789911 deg
	assign	cordic_angle[ 5] = 32'h003f_feaa; //   0.895174 deg
	assign	cordic_angle[ 6] = 32'h001f_ffd5; //   0.447614 deg
	assign	cordic_angle[ 7] = 32'h000f_fffa; //   0.223811 deg
	assign	cordic_angle[ 8] = 32'h0007_ffff; //   0.111906 deg
	assign	cordic_angle[ 9] = 32'h0003_ffff; //   0.055953 deg
	assign	cordic_angle[10] = 32'h0001_ffff; //   0.027976 deg
	assign	cordic_angle[11] = 32'h0000_ffff; //   0.013988 deg
	assign	cordic_angle[12] = 32'h0000_7fff; //   0.006994 deg
	assign	cordic_angle[13] = 32'h0000_3fff; //   0.003497 deg
	assign	cordic_angle[14] = 32'h0000_1fff; //   0.001749 deg
	assign	cordic_angle[15] = 32'h0000_0fff; //   0.000874 deg
	//assign	cordic_angle[16] = 32'h0000_1fff; //   0.000437 deg
	//assign	cordic_angle[17] = 32'h0000_0fff; //   0.000219 deg

	logic	signed [NSTAGES:0] [WIDTH-1:0]	xs;
	logic	signed [NSTAGES:0] [WIDTH-1:0]	ys;
	logic	signed [NSTAGES:0] [WIDTH-1:0]	phs;
	logic          [NSTAGES:0]              valids;
    
	// Предварительный поворот в сектор -45 45
	always_ff @(posedge clk) begin
		if (rst) valids[0] <= 'b0;
		else begin
			valids[0] <= i_vld;
			if (i_vld) begin
				case ({i_y[WIDTH-1], i_x[WIDTH-1]} )
					2'b00:begin
						xs[0]  <= i_x + i_y;
						ys[0]  <= i_y - i_x;
						// Угол в радианах
						// 1  - знак
						// 3  - целая часть
						// 28 - дробная часть
						phs[0] <= 32'h0c90_fdaa;    // 45 градусов
					end
					2'b01:begin
						xs[0]  <= i_y - i_x;
						ys[0]  <= -i_x - i_y;
						phs[0] <= 32'h25b2_f8fe;    //135
					end
					2'b11:begin
						xs[0]  <= -i_y - i_x;
						ys[0]  <= i_x - i_y;
						phs[0] <= 32'hda4d_0702;    //225 - 360
					end
					2'b10:begin
						xs[0]  <= i_x - i_y;
						ys[0]  <= i_x + i_y;
						phs[0] <= 32'hf36f_0256;    //315 - 360
					end
					default: begin
						xs[0]  <= i_x + i_y;
						ys[0]  <= i_y - i_x;
						phs[0] <= 32'h0c90_fdaa;
					end
				endcase
			end
		end
	end

	genvar	i;
	generate for(i = 0; i < NSTAGES; i++) begin : TOPOLARloop
		always @(posedge clk)
		if (rst)begin
			valids[i+1] <= 'b0;
		end 
		else begin
			valids[i+1] <= valids[i];
			if (valids[i]) begin
				if (~ys[i][WIDTH-1]) begin
					xs[i+1] <= xs[i] + {{(i+1){ys[i][WIDTH-1]}}, ys[i][WIDTH-1:(i+1)]};
					ys[i+1] <= ys[i] - {{(i+1){xs[i][WIDTH-1]}}, xs[i][WIDTH-1:(i+1)]};
					phs[i+1] <= phs[i] + cordic_angle[i];
				end 
				else begin
					xs[i+1] <= xs[i] - {{(i+1){ys[i][WIDTH-1]}}, ys[i][WIDTH-1:(i+1)]};
					ys[i+1] <= ys[i] + {{(i+1){xs[i][WIDTH-1]}}, xs[i][WIDTH-1:(i+1)]};
					phs[i+1] <= phs[i] - cordic_angle[i];
				end
			end
		end
	end 
	endgenerate

	assign o_mag = xs[NSTAGES];
    assign o_phase = phs[NSTAGES];
	assign o_vld = valids[NSTAGES];

endmodule

postprocess/dec_to_polar/testbench.sv
`timescale 1ns/1ps

module test;
    // Подключение

    logic                clk;
    logic                arstn;
    logic                enable;

    logic signed	[31:0] i_xval, i_yval;
    logic i_vld;

    logic signed	[31:0] o_mag;
    logic signed	[31:0] o_phase;
    logic o_vld;

    topolar tp (
        .clk           (clk),
        .rst         (~arstn),

        .i_vld (i_vld),
        .i_x (i_xval),
        .i_y (i_yval),

        .o_mag (o_mag),
        .o_phase (o_phase),
        .o_vld (o_vld)

    );

    initial begin
        $dumpfile("syst_node.vcd");
        $dumpvars;
    end

    // Генерация clk
    parameter CLK_PERIOD = 20; // 50 МГц
    initial begin
        clk <= 0;
        forever begin
            #(CLK_PERIOD / 2); clk <= ~clk;
        end
    end

    //Генерация rst
    initial begin
        arstn <= 0;
        @(posedge clk);
        @(posedge clk);
        @(posedge clk);
        arstn <= 1;
    end

    // Генерация входных сигналов
    initial begin
        i_vld <= 'b0;
        wait(arstn);
        @(posedge clk);
    //---------------------------------------------------------------------------------------------
        @(posedge clk);
        i_vld <= 'b1;
        i_xval <= 32'd1572864;
        i_yval <= 32'd1638400;
        @(posedge clk);
        i_vld <= 'b0;
    //---------------------------------------------------------------------------------------------
        repeat(18) begin
            @(posedge clk);
        end
        @(posedge clk);
        @(posedge clk);
        @(posedge clk);
        $finish;
    end
    
    // Проверка
    // initial begin
    //     wait(~arstn);
    //     @(posedge clk);
    //     @(posedge clk);
    // //---------------------------------------------------------------------------------------------
    //     repeat (32)
    //     begin
    //         @(posedge clk);
    //         if ($signed(psumm_o) != ($signed(psumm_i) + $signed(weight_i) * $signed(x_i) )) begin
    //             $display($signed(psumm_o));
    //             $display(($signed(psumm_i) + $signed(weight_i) * $signed(x_i)));
    //             $display($signed(psumm_i));
    //             $display($signed(weight_i));
    //             $display($signed(x_i));
    //             $error("BAD");
    //         end
    //         else begin
    //             $display("PASS");
    //             // $display($signed(psumm_o));
    //             // $display($signed(psumm_i));
    //             // $display($signed(weight_i));
    //             // $display($signed(x_i));
    //         end
    //     end
    // //---------------------------------------------------------------------------------------------
    //     @(posedge clk);
    //     @(posedge clk);
    //     @(posedge clk);
    //     $finish;
    // end
endmodule

postprocess/syst_node.vcd
$date
	Sun Mar 23 11:50:09 2025
$end
$version
	Icarus Verilog
$end
$timescale
	1ps
$end
$scope module test $end
$var wire 1 ! o_vld $end
$var wire 32 " o_phase [31:0] $end
$var wire 32 # o_mag [31:0] $end
$var reg 1 $ arstn $end
$var reg 1 % clk $end
$var reg 1 & i_vld $end
$var reg 32 ' i_xval [31:0] $end
$var reg 32 ( i_yval [31:0] $end
$scope module tp $end
$var wire 1 % clk $end
$var wire 1 & i_vld $end
$var wire 32 ) i_x [31:0] $end
$var wire 32 * i_y [31:0] $end
$var wire 1 + rst $end
$var wire 1 ! o_vld $end
$var wire 32 , o_phase [31:0] $end
$var wire 32 - o_mag [31:0] $end
$var reg 576 . phs [575:0] $end
$var reg 18 / valids [17:0] $end
$var reg 576 0 xs [575:0] $end
$var reg 576 1 ys [575:0] $end
$scope begin TOPOLARloop[0] $end
$upscope $end
$scope begin TOPOLARloop[1] $end
$upscope $end
$scope begin TOPOLARloop[2] $end
$upscope $end
$scope begin TOPOLARloop[3] $end
$upscope $end
$scope begin TOPOLARloop[4] $end
$upscope $end
$scope begin TOPOLARloop[5] $end
$upscope $end
$scope begin TOPOLARloop[6] $end
$upscope $end
$scope begin TOPOLARloop[7] $end
$upscope $end
$scope begin TOPOLARloop[8] $end
$upscope $end
$scope begin TOPOLARloop[9] $end
$upscope $end
$scope begin TOPOLARloop[10] $end
$upscope $end
$scope begin TOPOLARloop[11] $end
$upscope $end
$scope begin TOPOLARloop[12] $end
$upscope $end
$scope begin TOPOLARloop[13] $end
$upscope $end
$scope begin TOPOLARloop[14] $end
$upscope $end
$scope begin TOPOLARloop[15] $end
$upscope $end
$scope begin TOPOLARloop[16] $end
$upscope $end
$upscope $end
$upscope $end
$enddefinitions $end
#0
$dumpvars
bx 1
bx 0
bx /
bx .
bx -
bx ,
1+
bx *
bx )
bx (
bx '
0&
0%
0$
bx #
bx "
x!
$end
#10000
0!
b0 /
1%
#20000
0%
#30000
1%
#40000
0%
#50000
0+
1$
1%
#60000
0%
#70000
1%
#80000
0%
#90000
b10000000000 (
b10000000000 *
b10000000000 '
b10000000000 )
1&
1%
#100000
0%
#110000
bx00001011010000000000000000000000 .
bx00000000000000000000000000000000 1
bx00000000000000000000100000000000 0
b1 /
b1010000000000 '
b1010000000000 )
1%
#120000
0%
#130000
b1010000000000 (
b1010000000000 *
b10000000000 '
b10000000000 )
bx0001000111100100001010011100110000001011010000000000000000000000 .
b11 /
bx1111111111111111111111000000000011111111111111111111000000000000 1
bx0000000000000000000010000000000000000000000000000001100000000000 0
1%
#140000
0%
#150000
bx111111111111111111111110000000001111111111111111111111000000000000000000000000000001000000000000 1
b111 /
bx000011100110000111010111111111000000010010011011110101100011010000001011010000000000000000000000 .
bx000000000000000000001001000000000000000000000000001000000000000000000000000000000001100000000000 0
b10000000000 (
b10000000000 *
b11111111111111111110110000000000 '
b11111111111111111110110000000000 )
1%
#160000
0%
#170000
b1010000000000 (
b1010000000000 *
b11111111111111111111110000000000 '
b11111111111111111111110000000000 )
bx11111111111111111111111100100000000000000000000000000100000000000000000000000000000001000000000000000000000000000001000000000000 1
bx00000000000000000000100101000000000000000000000000100001000000000000000000000000001000000000000000000000000000000001100000000000 0
b1111 /
bx00001100100110011101011110111000000000010001100110000100011001000001000111100100001010011100110000100001110000000000000000000000 .
1%
#180000
0%
#190000
b11111 /
bx0000000000000000000010010100111000000000000000000010000110000000000000000000000000100001000000000000000000000000001000000000000000000000000000000001100000000000 0
bx1111111111111111111111111011010011111111111111111111111111100000111111111111111111111100000000000000000000000000000001000000000011111111111111111111000000000000 1
bx0000101110110100111101010000111100000010111000011000010010101000000101010110011001111011100111000010100001100100001010011100110000100001110000000000000000000000 .
b11111111111111111111110000000000 (
b11111111111111111111110000000000 *
b11111111111111111110110000000000 '
b11111111111111111110110000000000 )
1%
#200000
0%
#210000
b11111111111111111110110000000000 (
b11111111111111111110110000000000 *
b11111111111111111111110000000000 '
b11111111111111111111110000000000 )
bx111111111111111111111111111111100000000000000000000000011111100000000000000000000000000000100000111111111111111111111100000000001111111111111111111111000000000011111111111111111111000000000000 1
bx000000000000000000001001010100010000000000000000001000011000001000000000000000000010000110000000000000000000000000100001000000000000000000000000001000000000000000000000000000000001100000000000 0
b111111 /
bx000010110100001001100111001010100000000111111100101000011111111100010011100111100111101101011000001010111110011001111011100111000001101100011011110101100011010011011110010000000000000000000000 .
1%
#220000
0%
#230000
b1111111 /
bx00000000000000000000100101010010000000000000000000100001100100010000000000000000001000011000001000000000000000000010000110000000000000000000000000100001000000000000000000000000001000000000000000000000000000000001100000000000 0
bx00000000000000000000000000100011000000000000000000000000111011001111111111111111111111100000100000000000000000000000000000100000000000000000000000000100000000001111111111111111111111000000000000000000000000000001000000000000 1
bx00001011000010010001110010100100000000100110111100101111111001000001010010000011010111100000000100101010000111100111101101011000000101111001100110000100011001001101011110011011110101100011010011011110010000000000000000000000 .
b11111111111111111111110000000000 (
b11111111111111111111110000000000 *
b1010000000000 '
b1010000000000 )
1%
#240000
0%
#250000
b11111111111111111110110000000000 (
b11111111111111111110110000000000 *
b10000000000 '
b10000000000 )
bx0000000000000000000000000001000100000000000000000000000001100110111111111111111111111111000101001111111111111111111111100000100011111111111111111111111111100000000000000000000000000100000000000000000000000000000001000000000000000000000000000001000000000000 1
bx0000000000000000000010010101001000000000000000000010000110010100000000000000000000100001100100100000000000000000001000011000001000000000000000000010000110000000000000000000000000100001000000000000000000000000001000000000000000000000000000000001100000000000 0
b11111111 /
bx0000101100100101110000100101100100000010101010000111101001101010000101000001000011010000000111000010101100000011010111100000000100011001011000011000010010101000110101000001100110000100011001001110010011100100001010011100110011110100110000000000000000000000 .
1%
#260000
0%
#270000
b111111111 /
bx000000000000000000001001010100100000000000000000001000011001010000000000000000000010000110010110000000000000000000100001100100100000000000000000001000011000001000000000000000000010000110000000000000000000000000100001000000000000000000000000001000000000000000000000000000000001100000000000 0
bx000000000000000000000000000010000000000000000000000000000010001111111111111111111111111110011010111111111111111111111111000101000000000000000000000000011111100011111111111111111111111111100000111111111111111111111100000000000000000000000000000001000000000011111111111111111111000000000000 1
bx000010110011010000010101010000100000001011000101001000000001111100010011110101111000010110010110001010101001000011010000000111000001100001111100101000011111111111010101111000011000010010101000111010000110011001111011100111001111101101100100001010011100110011110100110000000000000000000000 .
1%
#280000
0%
#290000
bx00001011001110110011111010111000000000101101001101110011000010000001001110111010110111111110000100101010010101111000010110010110000110001110111100101111111001001101010011111100101000011111111111100110100111100111101101011000111111101110011001111011100111001110111000011011110101100011010011110100110000000000000000000000 .
bx00000000000000000000000000000100000000000000000000000000000000101111111111111111111111111101110111111111111111111111111110011010000000000000000000000000111011000000000000000000000000011111100000000000000000000000000000100000111111111111111111111100000000001111111111111111111111000000000011111111111111111111000000000000 1
bx00000000000000000000100101010010000000000000000000100001100101000000000000000000001000011001011100000000000000000010000110010110000000000000000000100001100100010000000000000000001000011000001000000000000000000010000110000000000000000000000000100001000000000000000000000000001000000000000000000000000000000001100000000000 0
b1111111111 /
1%
#300000
0%
#310000
b11111111111 /
bx0000000000000000000010010101001000000000000000000010000110010100000000000000000000100001100110000000000000000000001000011001011100000000000000000010000110010100000000000000000000100001100100010000000000000000001000011000001000000000000000000010000110000000000000000000000000100001000000000000000000000000001000000000000000000000000000000001100000000000 0
bx0000101100111110110100110111001100000010110110101001110001111110000100111010110010001100111110000010101000111010110111111110000100011001001010000111101001101010110101010110111100101111111001001110011110000011010111100000000111111101000111100111101101011000111010101001100110000100011001001110111000011011110101100011010011110100110000000000000000000000 .
bx0000000000000000000000000000001011111111111111111111111111110010111111111111111111111111111111101111111111111111111111111101110100000000000000000000000001100110000000000000000000000000111011001111111111111111111111100000100000000000000000000000000000100000000000000000000000000100000000001111111111111111111111000000000011111111111111111111000000000000 1
1%
#320000
0%
#330000
bx000010110100000010011101110100000000001011010111000001111100001100010011101001010110001110000010001010100010110010001100111110000001100101000101001000000001111111010101101010000111101001101010111001110001000011010000000111001111111000000011010111100000000111101100011000011000010010101000111010101001100110000100011001001110111000011011110101100011010011110100110000000000000000000000 .
bx000000000000000000000000000000011111111111111111111111111111101000000000000000000000000000001110111111111111111111111111111111100000000000000000000000000010001100000000000000000000000001100110111111111111111111111111000101001111111111111111111111100000100011111111111111111111111111100000000000000000000000000100000000001111111111111111111111000000000011111111111111111111000000000000 1
bx000000000000000000001001010100100000000000000000001000011001010100000000000000000010000110011001000000000000000000100001100110000000000000000000001000011001010000000000000000000010000110010100000000000000000000100001100100100000000000000000001000011000001000000000000000000010000110000000000000000000000000100001000000000000000000000000001000000000000000000000000000000001100000000000 0
b111111111111 /
1%
#340000
0%
#350000
b1111111111111 /
bx00000000000000000000100101010010000000000000000000100001100101100000000000000000001000011001100100000000000000000010000110011001000000000000000000100001100101000000000000000000001000011001010000000000000000000010000110010110000000000000000000100001100100100000000000000000001000011000001000000000000000000010000110000000000000000000000000100001000000000000000000000000001000000000000000000000000000000001100000000000 0
bx00001011010000011000001011111110000000101101010100111101011001100001001110101000111110000011110100101010001001010110001110000010000110010101001101110011000010001101010111000101001000000001111111100110110101111000010110010110111111011001000011010000000111001110101101111100101000011111111111101100011000011000010010101000111010101001100110000100011001001110111000011011110101100011010011110100110000000000000000000000 .
bx00000000000000000000000000000001111111111111111111111111111111100000000000000000000000000000011000000000000000000000000000001110000000000000000000000000000000100000000000000000000000000010001111111111111111111111111110011010111111111111111111111111000101000000000000000000000000011111100011111111111111111111111111100000000000000000000000000100000000001111111111111111111111000000000011111111111111111111000000000000 1
1%
#360000
0%
#370000
bx0000101101000001111101011001010100000010110101000101100000111000000100111010101011000010100110100010101000101000111110000011110100011001010110101001110001111110110101011101001101110011000010001110011010111010110111111110000111111101010101111000010110010110111010111110111100101111111001001110101101111100101000011111111111101100011000011000010010101000111010101001100110000100011001001110111000011011110101100011010011110100110000000000000000000000 .
bx0000000000000000000000000000000100000000000000000000000000000000000000000000000000000000000000100000000000000000000000000000011011111111111111111111111111110010000000000000000000000000000000101111111111111111111111111101110111111111111111111111111110011010000000000000000000000000111011000000000000000000000000011111100011111111111111111111111111100000000000000000000000000100000000001111111111111111111111000000000011111111111111111111000000000000 1
bx0000000000000000000010010101001000000000000000000010000110010111000000000000000000100001100110010000000000000000001000011001100100000000000000000010000110010100000000000000000000100001100101000000000000000000001000011001011100000000000000000010000110010110000000000000000000100001100100010000000000000000001000011000001000000000000000000010000110000000000000000000000000100001000000000000000000000000001000000000000000000000000000000001100000000000 0
b11111111111111 /
1%
#380000
0%
#390000
b111111111111111 /
bx000010110100001000101110111000000000001011010100110010101100111100010011101010111010011111001000001010100010101011000010100110100001100101010111000001111100001111010101110110101001110001111110111001101010110010001100111110001111110100111010110111111110000111101100001010000111101001101010111010111110111100101111111001001110101101111100101000011111111111101100011000011000010010101000111010101001100110000100011001001110111000011011110101100011010011110100110000000000000000000000 .
bx000000000000000000000000000000011111111111111111111111111111111100000000000000000000000000000000000000000000000000000000000000101111111111111111111111111111101011111111111111111111111111110010111111111111111111111111111111101111111111111111111111111101110100000000000000000000000001100110000000000000000000000000111011000000000000000000000000011111100011111111111111111111111111100000000000000000000000000100000000001111111111111111111111000000000011111111111111111111000000000000 1
bx000000000000000000001001010100100000000000000000001000011001011100000000000000000010000110011001000000000000000000100001100110010000000000000000001000011001010100000000000000000010000110010100000000000000000000100001100110000000000000000000001000011001011100000000000000000010000110010100000000000000000000100001100100010000000000000000001000011000001000000000000000000010000110000000000000000000000000100001000000000000000000000000001000000000000000000000000000000001100000000000 0
1%
#400000
0%
#410000
bx00001011010000100100101110000101000000101101010010010001100001000001001110101100000110100101111100101010001010111010011111001000000110010101010100111101011001101101010111010111000001111100001111100110101001010110001110000010111111010010110010001100111110001110110001000101001000000001111111101100001010000111101001101010111010111110111100101111111001001110101101111100101000011111111111101100011000011000010010101000111010101001100110000100011001001110111000011011110101100011010011110100110000000000000000000000 .
bx00000000000000000000000000000001111111111111111111111111111111111111111111111111111111111111111100000000000000000000000000000000111111111111111111111111111111101111111111111111111111111111101000000000000000000000000000001110111111111111111111111111111111100000000000000000000000000010001100000000000000000000000001100110000000000000000000000000111011000000000000000000000000011111100011111111111111111111111111100000000000000000000000000100000000001111111111111111111111000000000011111111111111111111000000000000 1
bx00000000000000000000100101010010000000000000000000100001100110000000000000000000001000011001100100000000000000000010000110011001000000000000000000100001100101100000000000000000001000011001010100000000000000000010000110011001000000000000000000100001100110000000000000000000001000011001010000000000000000000010000110010100000000000000000000100001100100010000000000000000001000011000001000000000000000000010000110000000000000000000000000100001000000000000000000000000001000000000000000000000000000000001100000000000 0
b1111111111111111 /
1%
#420000
0%
#430000
b11111111111111111 /
bx0000101101000010010110011101011100000010110101000111010011011111000100111010101111100001000101000010101000101100000110100101111100011001010101000101100000111000110101011101010100111101011001101110011010101000111110000011110111111101001001010110001110000010111011000101001101110011000010001110110001000101001000000001111111101100001010000111101001101010111010111110111100101111111001001110101101111100101000011111111111101100011000011000010010101000111010101001100110000100011001001110111000011011110101100011010011110100110000000000000000000000 .
bx0000000000000000000000000000000111111111111111111111111111111111111111111111111111111111111111111111111111111111111111111111111100000000000000000000000000000000111111111111111111111111111111100000000000000000000000000000011000000000000000000000000000001110000000000000000000000000000000100000000000000000000000000010001100000000000000000000000001100110000000000000000000000000111011000000000000000000000000011111100011111111111111111111111111100000000000000000000000000100000000001111111111111111111111000000000011111111111111111111000000000000 1
bx0000000000000000000010010101001000000000000000000010000110011001000000000000000000100001100110100000000000000000001000011001100100000000000000000010000110010111000000000000000000100001100101100000000000000000001000011001100100000000000000000010000110011001000000000000000000100001100101000000000000000000001000011001010000000000000000000010000110010100000000000000000000100001100100010000000000000000001000011000001000000000000000000010000110000000000000000000000000100001000000000000000000000000001000000000000000000000000000000001100000000000 0
1%
#440000
0%
#450000
b1011010000100110000100000000 "
b1011010000100110000100000000 ,
b100101010010 #
b100101010010 -
1!
b10110100001001100001000000000000001011010100011001101000110100010011101010111100010001101111001010100010101111100001000101000001100101010100110010101100111111010101110101000101100000111000111001101010101011000010100110101111110100101000111110000011110111101100010110101001110001111110111011000101001101110011000010001110110001000101001000000001111111101100001010000111101001101010111010111110111100101111111001001110101101111100101000011111111111101100011000011000010010101000111010101001100110000100011001001110111000011011110101100011010011110100110000000000000000000000 .
b11111111111111111111111111111111111111111111111111111111111111111111111111111111111111111111111111111111111111111111111111111111100000000000000000000000000000000000000000000000000000000000000100000000000000000000000000000011011111111111111111111111111110010000000000000000000000000000000100000000000000000000000000010001100000000000000000000000001100110000000000000000000000000111011000000000000000000000000011111100011111111111111111111111111100000000000000000000000000100000000001111111111111111111111000000000011111111111111111111000000000000 1
b1001010100100000000000000000001000011001101000000000000000000010000110011011000000000000000000100001100110100000000000000000001000011001011100000000000000000010000110010111000000000000000000100001100110010000000000000000001000011001100100000000000000000010000110010100000000000000000000100001100101000000000000000000001000011001010000000000000000000010000110010100000000000000000000100001100100010000000000000000001000011000001000000000000000000010000110000000000000000000000000100001000000000000000000000000001000000000000000000000000000000001100000000000 0
b111111111111111111 /
1%
#460000
0%
#470000
b10110101000101111101100100 "
b10110101000101111101100100 ,
b10000110011011 #
b10000110011011 -
b101101010001011111011001000001001110101011101101100001110100101010001010111100010001101111000110010101010010010001100001001101010111010100110010101100111111100110101010111010011111001000111111010010101011000010100110101110110001010111000001111100001111101100010110101001110001111110111011000101001101110011000010001110110001000101001000000001111111101100001010000111101001101010111010111110111100101111111001001110101101111100101000011111111111101100011000011000010010101000111010101001100110000100011001001110111000011011110101100011010011110100110000000000000000000000 .
b111111111111111111111111111111111111111111111111111111111111111111111111111111111111111111111111111111111111111111111111111111111111111111111111111111111111111100000000000000000000000000000000000000000000000000000000000000101111111111111111111111111111101011111111111111111111111111110010000000000000000000000000000000100000000000000000000000000010001100000000000000000000000001100110000000000000000000000000111011000000000000000000000000011111100011111111111111111111111111100000000000000000000000000100000000001111111111111111111111000000000011111111111111111111000000000000 1
b100001100110110000000000000000001000011001110000000000000000000010000110011011000000000000000000100001100110000000000000000000001000011001011100000000000000000010000110011001000000000000000000100001100110010000000000000000001000011001010100000000000000000010000110010100000000000000000000100001100101000000000000000000001000011001010000000000000000000010000110010100000000000000000000100001100100010000000000000000001000011000001000000000000000000010000110000000000000000000000000100001000000000000000000000000001000000000000000000000000000000001100000000000 0
1%
#480000
0%
#490000
b10011101010111010111011110100 "
b10011101010111010111011110100 ,
b10000110011101 #
b10000110011101 -
b111111111111111111111111111111111111111111111111111111111111111111111111111111111111111111111111111111111111111111111111111111111111111111111111111111111111111100000000000000000000000000000000111111111111111111111111111111101111111111111111111111111111101011111111111111111111111111110010000000000000000000000000000000100000000000000000000000000010001100000000000000000000000001100110000000000000000000000000111011000000000000000000000000011111100011111111111111111111111111100000000000000000000000000100000000001111111111111111111111000000000011111111111111111111000000000000 1
b100111010101110101110111101000010101000101011101101100001110100011001010101000111010011011111110101011101010010010001100001001110011010101100000110100101111111111101001010111010011111001000111011000101010100111101011001101110110001010111000001111100001111101100010110101001110001111110111011000101001101110011000010001110110001000101001000000001111111101100001010000111101001101010111010111110111100101111111001001110101101111100101000011111111111101100011000011000010010101000111010101001100110000100011001001110111000011011110101100011010011110100110000000000000000000000 .
b100001100111010000000000000000001000011001110000000000000000000010000110011001000000000000000000100001100110000000000000000000001000011001100100000000000000000010000110011001000000000000000000100001100101100000000000000000001000011001010100000000000000000010000110010100000000000000000000100001100101000000000000000000001000011001010000000000000000000010000110010100000000000000000000100001100100010000000000000000001000011000001000000000000000000010000110000000000000000000000000100001000000000000000000000000001000000000000000000000000000000001100000000000 0
1%
#500000
0%
#510000
b101010001010111010111011110100 "
b101010001010111010111011110100 ,
b1010100010101110101110111101000001100101010100011001101000110111010101110101000111010011011111111001101010101111100001000101001111110100101100000110100101111111101100010101000101100000111000111011000101010100111101011001101110110001010111000001111100001111101100010110101001110001111110111011000101001101110011000010001110110001000101001000000001111111101100001010000111101001101010111010111110111100101111111001001110101101111100101000011111111111101100011000011000010010101000111010101001100110000100011001001110111000011011110101100011010011110100110000000000000000000000 .
b100001100111010000000000000000001000011001101000000000000000000010000110011001000000000000000000100001100110100000000000000000001000011001100100000000000000000010000110010111000000000000000000100001100101100000000000000000001000011001010100000000000000000010000110010100000000000000000000100001100101000000000000000000001000011001010000000000000000000010000110010100000000000000000000100001100100010000000000000000001000011000001000000000000000000010000110000000000000000000000000100001000000000000000000000000001000000000000000000000000000000001100000000000 0
1%
#520000
0%
#530000
b11001010101000101111101100100 "
b11001010101000101111101100100 ,
b10000110011011 #
b10000110011011 -
b110010101010001011111011001001101010111010100011001101000110111100110101010111100010001101111111111010010101111100001000101001110110001010100110010101100111111101100010101000101100000111000111011000101010100111101011001101110110001010111000001111100001111101100010110101001110001111110111011000101001101110011000010001110110001000101001000000001111111101100001010000111101001101010111010111110111100101111111001001110101101111100101000011111111111101100011000011000010010101000111010101001100110000100011001001110111000011011110101100011010011110100110000000000000000000000 .
b100001100110110000000000000000001000011001101000000000000000000010000110011011000000000000000000100001100110100000000000000000001000011001011100000000000000000010000110010111000000000000000000100001100101100000000000000000001000011001010100000000000000000010000110010100000000000000000000100001100101000000000000000000001000011001010000000000000000000010000110010100000000000000000000100001100100010000000000000000001000011000001000000000000000000010000110000000000000000000000000100001000000000000000000000000001000000000000000000000000000000001100000000000 0
1%
#540000
0%
#550000
b11010101110101000101111101100100 "
b11010101110101000101111101100100 ,
b110101011101010001011111011001001110011010101011101101100001110111111101001010111100010001101111111011000101010010010001100001001110110001010100110010101100111111101100010101000101100000111000111011000101010100111101011001101110110001010111000001111100001111101100010110101001110001111110111011000101001101110011000010001110110001000101001000000001111111101100001010000111101001101010111010111110111100101111111001001110101101111100101000011111111111101100011000011000010010101000111010101001100110000100011001001110111000011011110101100011010011110100110000000000000000000000 .
b100001100110110000000000000000001000011001110000000000000000000010000110011011000000000000000000100001100110000000000000000000001000011001011100000000000000000010000110010111000000000000000000100001100101100000000000000000001000011001010100000000000000000010000110010100000000000000000000100001100101000000000000000000001000011001010000000000000000000010000110010100000000000000000000100001100100010000000000000000001000011000001000000000000000000010000110000000000000000000000000100001000000000000000000000000001000000000000000000000000000000001100000000000 0
1%
#560000
0%
#570000
b11100110101010111010111011110100 "
b11100110101010111010111011110100 ,
b10000110011101 #
b10000110011101 -
b111001101010101110101110111101001111110100101011101101100001110111101100010101000111010011011111111011000101010010010001100001001110110001010100110010101100111111101100010101000101100000111000111011000101010100111101011001101110110001010111000001111100001111101100010110101001110001111110111011000101001101110011000010001110110001000101001000000001111111101100001010000111101001101010111010111110111100101111111001001110101101111100101000011111111111101100011000011000010010101000111010101001100110000100011001001110111000011011110101100011010011110100110000000000000000000000 .
b100001100111010000000000000000001000011001110000000000000000000010000110011001000000000000000000100001100110000000000000000000001000011001011100000000000000000010000110010111000000000000000000100001100101100000000000000000001000011001010100000000000000000010000110010100000000000000000000100001100101000000000000000000001000011001010000000000000000000010000110010100000000000000000000100001100100010000000000000000001000011000001000000000000000000010000110000000000000000000000000100001000000000000000000000000001000000000000000000000000000000001100000000000 0
1%
#580000
0%
#590000
b11111101001010111010111011110100 "
b11111101001010111010111011110100 ,
b111111010010101110101110111101001110110001010100011001101000110111101100010101000111010011011111111011000101010010010001100001001110110001010100110010101100111111101100010101000101100000111000111011000101010100111101011001101110110001010111000001111100001111101100010110101001110001111110111011000101001101110011000010001110110001000101001000000001111111101100001010000111101001101010111010111110111100101111111001001110101101111100101000011111111111101100011000011000010010101000111010101001100110000100011001001110111000011011110101100011010011110100110000000000000000000000 .
b100001100111010000000000000000001000011001101000000000000000000010000110011001000000000000000000100001100110000000000000000000001000011001011100000000000000000010000110010111000000000000000000100001100101100000000000000000001000011001010100000000000000000010000110010100000000000000000000100001100101000000000000000000001000011001010000000000000000000010000110010100000000000000000000100001100100010000000000000000001000011000001000000000000000000010000110000000000000000000000000100001000000000000000000000000001000000000000000000000000000000001100000000000 0
1%
#600000
0%
#610000
b11101100010101000101111101100100 "
b11101100010101000101111101100100 ,
b10000110011011 #
b10000110011011 -
b111011000101010001011111011001001110110001010100011001101000110111101100010101000111010011011111111011000101010010010001100001001110110001010100110010101100111111101100010101000101100000111000111011000101010100111101011001101110110001010111000001111100001111101100010110101001110001111110111011000101001101110011000010001110110001000101001000000001111111101100001010000111101001101010111010111110111100101111111001001110101101111100101000011111111111101100011000011000010010101000111010101001100110000100011001001110111000011011110101100011010011110100110000000000000000000000 .
b100001100110110000000000000000001000011001101000000000000000000010000110011001000000000000000000100001100110000000000000000000001000011001011100000000000000000010000110010111000000000000000000100001100101100000000000000000001000011001010100000000000000000010000110010100000000000000000000100001100101000000000000000000001000011001010000000000000000000010000110010100000000000000000000100001100100010000000000000000001000011000001000000000000000000010000110000000000000000000000000100001000000000000000000000000001000000000000000000000000000000001100000000000 0
1%
