postprocess/dec_to_polar_fsm/dec_to_polar_fsm.sv

module	topolar_fsm
#(
    parameter WIDTH = 32
)
(
	input                              clk, 
	input                              rst, 
	
	input                              i_vld,
	input   logic signed [WIDTH - 1:0] i_x, 
	input   logic signed [WIDTH - 1:0] i_y,

	output  logic                      o_vld,
	output	logic signed [WIDTH - 1:0] o_mag,
	output	logic signed [31:0]	       o_phase,
	output  logic                      ready
	);
	localparam NSTAGES = 16;
	//
	logic signed [31:0] cordic_angle [0:(NSTAGES-1)];
	assign	cordic_angle[ 0] = 32'h06a4_29cc; //  26.565051 deg
	assign	cordic_angle[ 1] = 32'h0382_51d0; //  14.036243 deg
	assign	cordic_angle[ 2] = 32'h01c8_0044; //   7.125016 deg
	assign	cordic_angle[ 3] = 32'h00e4_e2a9; //   3.576334 deg
	assign	cordic_angle[ 4] = 32'h0072_8de5; //   1.789911 deg
	assign	cordic_angle[ 5] = 32'h0039_4a86; //   0.895174 deg
	assign	cordic_angle[ 6] = 32'h001c_a5b5; //   0.447614 deg
	assign	cordic_angle[ 7] = 32'h000e_52e9; //   0.223811 deg
	assign	cordic_angle[ 8] = 32'h0007_2976; //   0.111906 deg
	assign	cordic_angle[ 9] = 32'h0003_94bb; //   0.055953 deg
	assign	cordic_angle[10] = 32'h0001_ca5d; //   0.027976 deg
	assign	cordic_angle[11] = 32'h0000_e52e; //   0.013988 deg
	assign	cordic_angle[12] = 32'h0000_7297; //   0.006994 deg
	assign	cordic_angle[13] = 32'h0000_394b; //   0.003497 deg
	assign	cordic_angle[14] = 32'h0000_1ca5; //   0.001749 deg
	assign	cordic_angle[15] = 32'h0000_0e52; //   0.000874 deg
	//assign	cordic_angle[16] = 32'h0000_0729; //   0.000437 deg
	//assign	cordic_angle[17] = 32'h0000_0394; //   0.000219 deg

	enum logic[1:0]
  	{
    	IDLE   = 2'b00,
    	BUSY   = 2'b01,
    	OUTPUT = 2'b10
	}
	state, new_state;
	always_ff @ (posedge clk)
    if (rst)
    	state <= IDLE;
    else
    	state <= new_state;

	// Логика переходов
	localparam counter_width = $clog2 (NSTAGES + 1);
	logic [counter_width-1:0] cnt;
	logic en;
	assign en = cnt == (NSTAGES - 1);
	always_ff @(posedge clk) begin
		if (rst) cnt <= 'b0;
		else if (state == BUSY) begin
			if (en) cnt <= 'b0;
			else    cnt <= cnt + 'b1;
		end
		else cnt <= 'b0;
	end

	always_comb
	begin
		new_state = state;
		case (state)
		IDLE:   if (i_vld) new_state = BUSY;
		BUSY:   if (en   ) new_state = OUTPUT;
		OUTPUT: if (i_vld) new_state = BUSY;
				else       new_state = IDLE;
		default: new_state = state;
		endcase
	end

	logic signed [WIDTH-1:0] xs;
	logic signed [WIDTH-1:0] ys;
	logic signed [WIDTH-1:0] phs;
    
	logic signed [WIDTH-1:0] ys_abs;
	assign ys_abs = (ys[WIDTH-1]) ? -ys : ys;

	always_ff @(posedge clk) begin
		// Предварительный поворот в сектор -45 45
		if (i_vld & ready) begin
			case ({i_y[WIDTH-1], i_x[WIDTH-1]} )
				2'b00:begin
					xs  <= i_x + i_y;
					ys  <= i_y - i_x;
					// Угол в градусах
					// 1  - знак
					// 9  - целая часть
					// 22 - дробная часть
					phs <= 32'h0b40_0000;    // 45 градусов
				end
				2'b01:begin
					xs  <= i_y - i_x;
					ys  <= -i_x - i_y;
					phs <= 32'h21c0_0000;    //135
				end
				2'b11:begin
					xs  <= -i_y - i_x;
					ys  <= i_x - i_y;
					phs <= 32'hde40_0000;    //225 - 360
				end
				2'b10:begin
					xs  <= i_x - i_y;
					ys  <= i_x + i_y;
					phs <= 32'hf4c0_0000;    //315 - 360
				end
				default: begin
					xs  <= i_x + i_y;
					ys  <= i_y - i_x;
					phs <= 32'h0c90_fdaa;
				end
			endcase
		end
		else if (state == BUSY) begin
			if (ys[WIDTH-1]) begin
				xs <= xs + (ys_abs >> (cnt + 'b1));
				ys <= ys + (xs >> (cnt + 'b1));
				phs <= phs - cordic_angle[cnt];
			end 
			else begin
				xs <= xs + (ys >> (cnt + 'b1));
				ys <= ys - (xs >> (cnt + 'b1));
				phs <= phs + cordic_angle[cnt];
			end
		end
		else begin
			xs <= 'b0;
			ys <= 'b0;
			phs <= 'b0;
		end
	end 

	assign o_mag = xs;
    assign o_phase = phs;
	assign o_vld = state == OUTPUT;
	assign ready = state != BUSY;

endmodule

postprocess/dec_to_polar_fsm/testbench.sv
`timescale 1ns/1ps

module test;
    // Подключение

    logic                clk;
    logic                arstn;
    logic                enable;

    logic signed	[31:0] i_xval, i_yval;
    logic i_vld;

    logic signed	[31:0] o_mag;
    logic signed	[31:0] o_phase;
    logic o_vld;
    logic ready;

    topolar_fsm tp (
        .clk           (clk),
        .rst         (~arstn),

        .i_vld (i_vld),
        .i_x (i_xval),
        .i_y (i_yval),

        .o_mag (o_mag),
        .o_phase (o_phase),
        .o_vld (o_vld),
        .ready (ready)
    );

    initial begin
        $dumpfile("syst_node.vcd");
        $dumpvars;
    end

    // Генерация clk
    parameter CLK_PERIOD = 20; // 50 МГц
    initial begin
        clk <= 0;
        forever begin
            #(CLK_PERIOD / 2); clk <= ~clk;
        end
    end

    //Генерация rst
    initial begin
        arstn <= 0;
        @(posedge clk);
        @(posedge clk);
        @(posedge clk);
        arstn <= 1;
    end

    // Генерация входных сигналов
    initial begin
        i_vld <= 'b0;
        wait(arstn);
        @(posedge clk);
    //---------------------------------------------------------------------------------------------
        @(posedge clk);
        i_vld <= 'b1;
        i_xval <= 32'd1 << 'd10;
        i_yval <= 32'd1 << 'd10;
        $display("%d", 32'd1);
        $display("%d", 32'd1);

        @(posedge o_vld);
        i_vld <= 'b1;
        i_xval <= 32'd5 << 'd10;
        i_yval <= 32'd1 << 'd10;
        $display("%d", 32'd5);
        $display("%d", 32'd1);
        @(posedge o_vld);
        i_vld <= 'b1;
        i_xval <= 32'd1 << 'd10;
        i_yval <= 32'd5 << 'd10;
        $display("%d", 32'd1);
        $display("%d", 32'd5);

        @(posedge o_vld);
        i_vld <= 'b1;
        i_xval <= -32'd5 << 'd10;
        i_yval <= 32'd1 << 'd10;
        $display("-%d", 32'd5);
        $display("%d", 32'd1);
        @(posedge o_vld);
        i_vld <= 'b1;
        i_xval <= -32'd1 << 'd10;
        i_yval <= 32'd5 << 'd10;
        $display("-%d", 32'd1);
        $display("%d", 32'd5);

        @(posedge o_vld);
        i_vld <= 'b1;
        i_xval <= -32'd5 << 'd10;
        i_yval <= -32'd1 << 'd10;
        $display("-%d", 32'd5);
        $display("-%d", 32'd1);
        @(posedge o_vld);
        i_vld <= 'b1;
        i_xval <= -32'd1 << 'd10;
        i_yval <= -32'd5 << 'd10;
        $display("-%d", 32'd1);
        $display("-%d", 32'd5);

        @(posedge o_vld);
        i_vld <= 'b1;
        i_xval <= 32'd5 << 'd10;
        i_yval <= -32'd1 << 'd10;
        $display("%d", 32'd5);
        $display("-%d", 32'd1);
        @(posedge o_vld);
        i_vld <= 'b1;
        i_xval <= 32'd1 << 'd10;
        i_yval <= -32'd5 << 'd10;
        $display("%d", 32'd1);
        $display("-%d", 32'd5);
    //---------------------------------------------------------------------------------------------
        repeat(18) begin
            @(posedge clk);
        end
        @(posedge clk);
        @(posedge clk);
        @(posedge clk);
        $finish;
    end
endmodule

postprocess/syst_node.vcd
$date
	Sun Mar 23 14:28:15 2025
$end
$version
	Icarus Verilog
$end
$timescale
	1ps
$end
$scope module test $end
$var wire 1 ! ready $end
$var wire 1 " o_vld $end
$var wire 32 # o_phase [31:0] $end
$var wire 32 $ o_mag [31:0] $end
$var reg 1 % arstn $end
$var reg 1 & clk $end
$var reg 1 ' i_vld $end
$var reg 32 ( i_xval [31:0] $end
$var reg 32 ) i_yval [31:0] $end
$scope module tp $end
$var wire 1 & clk $end
$var wire 1 ' i_vld $end
$var wire 32 * i_x [31:0] $end
$var wire 32 + i_y [31:0] $end
$var wire 32 , o_mag [31:0] $end
$var wire 32 - o_phase [31:0] $end
$var wire 1 . rst $end
$var wire 32 / ys_abs [31:0] $end
$var wire 1 ! ready $end
$var wire 1 " o_vld $end
$var wire 1 0 en $end
$var reg 5 1 cnt [4:0] $end
$var reg 2 2 new_state [1:0] $end
$var reg 32 3 phs [31:0] $end
$var reg 2 4 state [1:0] $end
$var reg 32 5 xs [31:0] $end
$var reg 32 6 ys [31:0] $end
$upscope $end
$upscope $end
$enddefinitions $end
#0
$dumpvars
bx 6
bx 5
bx 4
bx 3
bx 2
bx 1
x0
bx /
1.
bx -
bx ,
bx +
bx *
bx )
bx (
0'
0&
0%
bx $
bx #
x"
x!
$end
#10000
b0 2
b0 /
0"
1!
b0 4
00
b0 1
b0 #
b0 -
b0 3
b0 6
b0 $
b0 ,
b0 5
1&
#20000
0&
#30000
1&
#40000
0&
#50000
0.
1%
1&
#60000
0&
#70000
1&
#80000
0&
#90000
b1 2
b10000000000 )
b10000000000 +
b10000000000 (
b10000000000 *
1'
1&
#100000
0&
#110000
b1011010000000000000000000000 #
b1011010000000000000000000000 -
b1011010000000000000000000000 3
b100000000000 $
b100000000000 ,
b100000000000 5
0!
b1 4
1&
#120000
0&
#130000
b10000000000 /
b1 1
b10001111001000010100111001100 #
b10001111001000010100111001100 -
b10001111001000010100111001100 3
b11111111111111111111110000000000 6
1&
#140000
0&
#150000
b1000000000 /
b1110011000011101011111111100 #
b1110011000011101011111111100 -
b1110011000011101011111111100 3
b11111111111111111111111000000000 6
b100100000000 $
b100100000000 ,
b100100000000 5
b10 1
1&
#160000
0&
#170000
b11100000 /
b11 1
b1100100110011101011110111000 #
b1100100110011101011110111000 -
b1100100110011101011110111000 3
b11111111111111111111111100100000 6
b100101000000 $
b100101000000 ,
b100101000000 5
1&
#180000
0&
#190000
b1001100 /
b1011101101001111010100001111 #
b1011101101001111010100001111 -
b1011101101001111010100001111 3
b11111111111111111111111110110100 6
b100101001110 $
b100101001110 ,
b100101001110 5
b100 1
1&
#200000
0&
#210000
b10 /
b101 1
b1011010000100110011100101010 #
b1011010000100110011100101010 -
b1011010000100110011100101010 3
b11111111111111111111111111111110 6
b100101010000 $
b100101010000 ,
b100101010000 5
1&
#220000
0&
#230000
b100011 /
b1011000010010001110010100100 #
b1011000010010001110010100100 -
b1011000010010001110010100100 3
b100011 6
b110 1
1&
#240000
0&
#250000
b10001 /
b111 1
b1011001001011100001001011001 #
b1011001001011100001001011001 -
b1011001001011100001001011001 3
b10001 6
1&
#260000
0&
#270000
b1000 /
b1011001101000001010101000010 #
b1011001101000001010101000010 -
b1011001101000001010101000010 3
b1000 6
b1000 1
1&
#280000
0&
#290000
b100 /
b1001 1
b1011001110110011111010111000 #
b1011001110110011111010111000 -
b1011001110110011111010111000 3
b100 6
1&
#300000
0&
#310000
b10 /
b1011001111101101001101110011 #
b1011001111101101001101110011 -
b1011001111101101001101110011 3
b10 6
b1010 1
1&
#320000
0&
#330000
b1 /
b1011 1
b1011010000001001110111010000 #
b1011010000001001110111010000 -
b1011010000001001110111010000 3
b1 6
1&
#340000
0&
#350000
b1011010000011000001011111110 #
b1011010000011000001011111110 -
b1011010000011000001011111110 3
b1100 1
1&
#360000
0&
#370000
b1101 1
b1011010000011111010110010101 #
b1011010000011111010110010101 -
b1011010000011111010110010101 3
1&
#380000
0&
#390000
b1011010000100010111011100000 #
b1011010000100010111011100000 -
b1011010000100010111011100000 3
b1110 1
1&
#400000
0&
#410000
b10 2
10
b1111 1
b1011010000100100101110000101 #
b1011010000100100101110000101 -
b1011010000100100101110000101 3
1&
#420000
0&
#430000
b1010000000000 (
b1010000000000 *
b1 2
b1011010000100101100111010111 #
b1011010000100101100111010111 -
b1011010000100101100111010111 3
00
b0 1
1"
1!
b10 4
1&
#440000
0&
#450000
b1000000000000 /
0"
0!
b1 4
b1011010000000000000000000000 #
b1011010000000000000000000000 -
b1011010000000000000000000000 3
b11111111111111111111000000000000 6
b1100000000000 $
b1100000000000 ,
b1100000000000 5
1&
#460000
0&
#470000
b10000000000 /
b100100110111101011000110100 #
b100100110111101011000110100 -
b100100110111101011000110100 3
b11111111111111111111110000000000 6
b10000000000000 $
b10000000000000 ,
b10000000000000 5
b1 1
1&
#480000
0&
#490000
b10000000000 /
b10 1
b1000110011000010001100100 #
b1000110011000010001100100 -
b1000110011000010001100100 3
b10000000000 6
b10000100000000 $
b10000100000000 ,
b10000100000000 5
1&
#500000
0&
#510000
b100000 /
b10111000011000010010101000 #
b10111000011000010010101000 -
b10111000011000010010101000 3
b11111111111111111111111111100000 6
b10000110000000 $
b10000110000000 ,
b10000110000000 5
b11 1
1&
#520000
0&
#530000
b111111000 /
b100 1
b1111111001010000111111111 #
b1111111001010000111111111 -
b1111111001010000111111111 3
b111111000 6
b10000110000010 $
b10000110000010 ,
b10000110000010 5
1&
#540000
0&
#550000
b11101100 /
b10011011110010111111100100 #
b10011011110010111111100100 -
b10011011110010111111100100 3
b11101100 6
b10000110010001 $
b10000110010001 ,
b10000110010001 5
b101 1
1&
#560000
0&
#570000
b1100110 /
b110 1
b10101010000111101001101010 #
b10101010000111101001101010 -
b10101010000111101001101010 3
b1100110 6
b10000110010100 $
b10000110010100 ,
b10000110010100 5
1&
#580000
0&
#590000
b100011 /
b10110001010010000000011111 #
b10110001010010000000011111 -
b10110001010010000000011111 3
b100011 6
b111 1
1&
#600000
0&
#610000
b10 /
b1000 1
b10110100110111001100001000 #
b10110100110111001100001000 -
b10110100110111001100001000 3
b10 6
1&
#620000
0&
#630000
b1110 /
b10110110101001110001111110 #
b10110110101001110001111110 -
b10110110101001110001111110 3
b11111111111111111111111111110010 6
b1001 1
1&
#640000
0&
#650000
b110 /
b1010 1
b10110101110000011111000011 #
b10110101110000011111000011 -
b10110101110000011111000011 3
b11111111111111111111111111111010 6
1&
#660000
0&
#670000
b10 /
b10110101010011110101100110 #
b10110101010011110101100110 -
b10110101010011110101100110 3
b11111111111111111111111111111110 6
b1011 1
1&
#680000
0&
#690000
b0 /
b1100 1
b10110101000101100000111000 #
b10110101000101100000111000 -
b10110101000101100000111000 3
b0 6
1&
#700000
0&
#710000
b1 /
b10110101001100101011001111 #
b10110101001100101011001111 -
b10110101001100101011001111 3
b11111111111111111111111111111111 6
b1101 1
1&
#720000
0&
#730000
b1110 1
b10110101001001000110000100 #
b10110101001001000110000100 -
b10110101001001000110000100 3
1&
#740000
0&
#750000
b10 2
b10110101000111010011011111 #
b10110101000111010011011111 -
b10110101000111010011011111 3
10
b1111 1
1&
#760000
0&
#770000
b1010000000000 )
b1010000000000 +
b10000000000 (
b10000000000 *
b1 2
1"
1!
b10 4
00
b0 1
b10110101000110011010001101 #
b10110101000110011010001101 -
b10110101000110011010001101 3
1&
#780000
0&
#790000
b1000000000000 /
b1011010000000000000000000000 #
b1011010000000000000000000000 -
b1011010000000000000000000000 3
b1000000000000 6
b1100000000000 $
b1100000000000 ,
b1100000000000 5
0"
0!
b1 4
1&
#800000
0&
#810000
b10000000000 /
b1 1
b10001111001000010100111001100 #
b10001111001000010100111001100 -
b10001111001000010100111001100 3
b10000000000 6
b10000000000000 $
b10000000000000 ,
b10000000000000 5
1&
#820000
0&
#830000
b10000000000 /
b10101011001100111101110011100 #
b10101011001100111101110011100 -
b10101011001100111101110011100 3
b11111111111111111111110000000000 6
b10000100000000 $
b10000100000000 ,
b10000100000000 5
b10 1
1&
#840000
0&
#850000
b100000 /
b11 1
b10011100111100111101101011000 #
b10011100111100111101101011000 -
b10011100111100111101101011000 3
b100000 6
b10000110000000 $
b10000110000000 ,
b10000110000000 5
1&
#860000
0&
#870000
b111111000 /
b10100100000110101111000000001 #
b10100100000110101111000000001 -
b10100100000110101111000000001 3
b11111111111111111111111000001000 6
b10000110000010 $
b10000110000010 ,
b10000110000010 5
b100 1
1&
#880000
0&
#890000
b11101100 /
b101 1
b10100000100001101000000011100 #
b10100000100001101000000011100 -
b10100000100001101000000011100 3
b11111111111111111111111100010100 6
b10000110010001 $
b10000110010001 ,
b10000110010001 5
1&
#900000
0&
#910000
b1100110 /
b10011110101111000010110010110 #
b10011110101111000010110010110 -
b10011110101111000010110010110 3
b11111111111111111111111110011010 6
b10000110010100 $
b10000110010100 ,
b10000110010100 5
b110 1
1&
#920000
0&
#930000
b100011 /
b111 1
b10011101110101101111111100001 #
b10011101110101101111111100001 -
b10011101110101101111111100001 3
b11111111111111111111111111011101 6
1&
#940000
0&
#950000
b10 /
b10011101011001000110011111000 #
b10011101011001000110011111000 -
b10011101011001000110011111000 3
b11111111111111111111111111111110 6
b1000 1
1&
#960000
0&
#970000
b1110 /
b1001 1
b10011101001010110001110000010 #
b10011101001010110001110000010 -
b10011101001010110001110000010 3
b1110 6
1&
#980000
0&
#990000
b110 /
b10011101010001111100000111101 #
b10011101010001111100000111101 -
b10011101010001111100000111101 3
b110 6
b1010 1
1&
#1000000
0&
#1010000
b10 /
b1011 1
b10011101010101100001010011010 #
b10011101010101100001010011010 -
b10011101010101100001010011010 3
b10 6
1&
#1020000
0&
#1030000
b0 /
b10011101010111010011111001000 #
b10011101010111010011111001000 -
b10011101010111010011111001000 3
b0 6
b1100 1
1&
#1040000
0&
#1050000
b1 /
b1101 1
b10011101011000001101001011111 #
b10011101011000001101001011111 -
b10011101011000001101001011111 3
b11111111111111111111111111111111 6
1&
#1060000
0&
#1070000
b10011101010111110000100010100 #
b10011101010111110000100010100 -
b10011101010111110000100010100 3
b1110 1
1&
#1080000
0&
#1090000
b10 2
10
b1111 1
b10011101010111100010001101111 #
b10011101010111100010001101111 -
b10011101010111100010001101111 3
1&
#1100000
0&
#1110000
b10000000000 )
b10000000000 +
b11111111111111111110110000000000 (
b11111111111111111110110000000000 *
b1 2
b10011101010111011011000011101 #
b10011101010111011011000011101 -
b10011101010111011011000011101 3
00
b0 1
1"
1!
b10 4
1&
#1120000
0&
#1130000
b1000000000000 /
0"
0!
b1 4
b100001110000000000000000000000 #
b100001110000000000000000000000 -
b100001110000000000000000000000 3
b1000000000000 6
b1100000000000 $
b1100000000000 ,
b1100000000000 5
1&
#1140000
0&
#1150000
b10000000000 /
b101000011001000010100111001100 #
b101000011001000010100111001100 -
b101000011001000010100111001100 3
b10000000000 6
b10000000000000 $
b10000000000000 ,
b10000000000000 5
b1 1
1&
#1160000
0&
#1170000
b10000000000 /
b10 1
b101011111001100111101110011100 #
b101011111001100111101110011100 -
b101011111001100111101110011100 3
b11111111111111111111110000000000 6
b10000100000000 $
b10000100000000 ,
b10000100000000 5
1&
#1180000
0&
#1190000
b100000 /
b101010000111100111101101011000 #
b101010000111100111101101011000 -
b101010000111100111101101011000 3
b100000 6
b10000110000000 $
b10000110000000 ,
b10000110000000 5
b11 1
1&
#1200000
0&
#1210000
b111111000 /
b100 1
b101011000000110101111000000001 #
b101011000000110101111000000001 -
b101011000000110101111000000001 3
b11111111111111111111111000001000 6
b10000110000010 $
b10000110000010 ,
b10000110000010 5
1&
#1220000
0&
#1230000
b11101100 /
b101010100100001101000000011100 #
b101010100100001101000000011100 -
b101010100100001101000000011100 3
b11111111111111111111111100010100 6
b10000110010001 $
b10000110010001 ,
b10000110010001 5
b101 1
1&
#1240000
0&
#1250000
b1100110 /
b110 1
b101010010101111000010110010110 #
b101010010101111000010110010110 -
b101010010101111000010110010110 3
b11111111111111111111111110011010 6
b10000110010100 $
b10000110010100 ,
b10000110010100 5
1&
#1260000
0&
#1270000
b100011 /
b101010001110101101111111100001 #
b101010001110101101111111100001 -
b101010001110101101111111100001 3
b11111111111111111111111111011101 6
b111 1
1&
#1280000
0&
#1290000
b10 /
b1000 1
b101010001011001000110011111000 #
b101010001011001000110011111000 -
b101010001011001000110011111000 3
b11111111111111111111111111111110 6
1&
#1300000
0&
#1310000
b1110 /
b101010001001010110001110000010 #
b101010001001010110001110000010 -
b101010001001010110001110000010 3
b1110 6
b1001 1
1&
#1320000
0&
#1330000
b110 /
b1010 1
b101010001010001111100000111101 #
b101010001010001111100000111101 -
b101010001010001111100000111101 3
b110 6
1&
#1340000
0&
#1350000
b10 /
b101010001010101100001010011010 #
b101010001010101100001010011010 -
b101010001010101100001010011010 3
b10 6
b1011 1
1&
#1360000
0&
#1370000
b0 /
b1100 1
b101010001010111010011111001000 #
b101010001010111010011111001000 -
b101010001010111010011111001000 3
b0 6
1&
#1380000
0&
#1390000
b1 /
b101010001011000001101001011111 #
b101010001011000001101001011111 -
b101010001011000001101001011111 3
b11111111111111111111111111111111 6
b1101 1
1&
#1400000
0&
#1410000
b1110 1
b101010001010111110000100010100 #
b101010001010111110000100010100 -
b101010001010111110000100010100 3
1&
#1420000
0&
#1430000
b10 2
b101010001010111100010001101111 #
b101010001010111100010001101111 -
b101010001010111100010001101111 3
10
b1111 1
1&
#1440000
0&
#1450000
b1010000000000 )
b1010000000000 +
b11111111111111111111110000000000 (
b11111111111111111111110000000000 *
b1 2
1"
1!
b10 4
00
b0 1
b101010001010111011011000011101 #
b101010001010111011011000011101 -
b101010001010111011011000011101 3
1&
#1460000
0&
#1470000
b1000000000000 /
b100001110000000000000000000000 #
b100001110000000000000000000000 -
b100001110000000000000000000000 3
b11111111111111111111000000000000 6
b1100000000000 $
b1100000000000 ,
b1100000000000 5
0"
0!
b1 4
1&
#1480000
0&
#1490000
b10000000000 /
b1 1
b11011000110111101011000110100 #
b11011000110111101011000110100 -
b11011000110111101011000110100 3
b11111111111111111111110000000000 6
b10000000000000 $
b10000000000000 ,
b10000000000000 5
1&
#1500000
0&
#1510000
b10000000000 /
b10111100110011000010001100100 #
b10111100110011000010001100100 -
b10111100110011000010001100100 3
b10000000000 6
b10000100000000 $
b10000100000000 ,
b10000100000000 5
b10 1
1&
#1520000
0&
#1530000
b100000 /
b11 1
b11001011000011000010010101000 #
b11001011000011000010010101000 -
b11001011000011000010010101000 3
b11111111111111111111111111100000 6
b10000110000000 $
b10000110000000 ,
b10000110000000 5
1&
#1540000
0&
#1550000
b111111000 /
b11000011111001010000111111111 #
b11000011111001010000111111111 -
b11000011111001010000111111111 3
b111111000 6
b10000110000010 $
b10000110000010 ,
b10000110000010 5
b100 1
1&
#1560000
0&
#1570000
b11101100 /
b101 1
b11000111011110010111111100100 #
b11000111011110010111111100100 -
b11000111011110010111111100100 3
b11101100 6
b10000110010001 $
b10000110010001 ,
b10000110010001 5
1&
#1580000
0&
#1590000
b1100110 /
b11001001010000111101001101010 #
b11001001010000111101001101010 -
b11001001010000111101001101010 3
b1100110 6
b10000110010100 $
b10000110010100 ,
b10000110010100 5
b110 1
1&
#1600000
0&
#1610000
b100011 /
b111 1
b11001010001010010000000011111 #
b11001010001010010000000011111 -
b11001010001010010000000011111 3
b100011 6
1&
#1620000
0&
#1630000
b10 /
b11001010100110111001100001000 #
b11001010100110111001100001000 -
b11001010100110111001100001000 3
b10 6
b1000 1
1&
#1640000
0&
#1650000
b1110 /
b1001 1
b11001010110101001110001111110 #
b11001010110101001110001111110 -
b11001010110101001110001111110 3
b11111111111111111111111111110010 6
1&
#1660000
0&
#1670000
b110 /
b11001010101110000011111000011 #
b11001010101110000011111000011 -
b11001010101110000011111000011 3
b11111111111111111111111111111010 6
b1010 1
1&
#1680000
0&
#1690000
b10 /
b1011 1
b11001010101010011110101100110 #
b11001010101010011110101100110 -
b11001010101010011110101100110 3
b11111111111111111111111111111110 6
1&
#1700000
0&
#1710000
b0 /
b11001010101000101100000111000 #
b11001010101000101100000111000 -
b11001010101000101100000111000 3
b0 6
b1100 1
1&
#1720000
0&
#1730000
b1 /
b1101 1
b11001010101001100101011001111 #
b11001010101001100101011001111 -
b11001010101001100101011001111 3
b11111111111111111111111111111111 6
1&
#1740000
0&
#1750000
b11001010101001001000110000100 #
b11001010101001001000110000100 -
b11001010101001001000110000100 3
b1110 1
1&
#1760000
0&
#1770000
b10 2
10
b1111 1
b11001010101000111010011011111 #
b11001010101000111010011011111 -
b11001010101000111010011011111 3
1&
#1780000
0&
#1790000
b11111111111111111111110000000000 )
b11111111111111111111110000000000 +
b11111111111111111110110000000000 (
b11111111111111111110110000000000 *
b1 2
b11001010101000110011010001101 #
b11001010101000110011010001101 -
b11001010101000110011010001101 3
00
b0 1
1"
1!
b10 4
1&
#1800000
0&
#1810000
b1000000000000 /
0"
0!
b1 4
b11011110010000000000000000000000 #
b11011110010000000000000000000000 -
b11011110010000000000000000000000 3
b11111111111111111111000000000000 6
b1100000000000 $
b1100000000000 ,
b1100000000000 5
1&
#1820000
0&
#1830000
b10000000000 /
b11010111100110111101011000110100 #
b11010111100110111101011000110100 -
b11010111100110111101011000110100 3
b11111111111111111111110000000000 6
b10000000000000 $
b10000000000000 ,
b10000000000000 5
b1 1
1&
#1840000
0&
#1850000
b10000000000 /
b10 1
b11010100000110011000010001100100 #
b11010100000110011000010001100100 -
b11010100000110011000010001100100 3
b10000000000 6
b10000100000000 $
b10000100000000 ,
b10000100000000 5
1&
#1860000
0&
#1870000
b100000 /
b11010101111000011000010010101000 #
b11010101111000011000010010101000 -
b11010101111000011000010010101000 3
b11111111111111111111111111100000 6
b10000110000000 $
b10000110000000 ,
b10000110000000 5
b11 1
1&
#1880000
0&
#1890000
b111111000 /
b100 1
b11010100111111001010000111111111 #
b11010100111111001010000111111111 -
b11010100111111001010000111111111 3
b111111000 6
b10000110000010 $
b10000110000010 ,
b10000110000010 5
1&
#1900000
0&
#1910000
b11101100 /
b11010101011011110010111111100100 #
b11010101011011110010111111100100 -
b11010101011011110010111111100100 3
b11101100 6
b10000110010001 $
b10000110010001 ,
b10000110010001 5
b101 1
1&
#1920000
0&
#1930000
b1100110 /
b110 1
b11010101101010000111101001101010 #
b11010101101010000111101001101010 -
b11010101101010000111101001101010 3
b1100110 6
b10000110010100 $
b10000110010100 ,
b10000110010100 5
1&
#1940000
0&
#1950000
b100011 /
b11010101110001010010000000011111 #
b11010101110001010010000000011111 -
b11010101110001010010000000011111 3
b100011 6
b111 1
1&
#1960000
0&
#1970000
b10 /
b1000 1
b11010101110100110111001100001000 #
b11010101110100110111001100001000 -
b11010101110100110111001100001000 3
b10 6
1&
#1980000
0&
#1990000
b1110 /
b11010101110110101001110001111110 #
b11010101110110101001110001111110 -
b11010101110110101001110001111110 3
b11111111111111111111111111110010 6
b1001 1
1&
#2000000
0&
#2010000
b110 /
b1010 1
b11010101110101110000011111000011 #
b11010101110101110000011111000011 -
b11010101110101110000011111000011 3
b11111111111111111111111111111010 6
1&
#2020000
0&
#2030000
b10 /
b11010101110101010011110101100110 #
b11010101110101010011110101100110 -
b11010101110101010011110101100110 3
b11111111111111111111111111111110 6
b1011 1
1&
#2040000
0&
#2050000
b0 /
b1100 1
b11010101110101000101100000111000 #
b11010101110101000101100000111000 -
b11010101110101000101100000111000 3
b0 6
1&
#2060000
0&
#2070000
b1 /
b11010101110101001100101011001111 #
b11010101110101001100101011001111 -
b11010101110101001100101011001111 3
b11111111111111111111111111111111 6
b1101 1
1&
#2080000
0&
#2090000
b1110 1
b11010101110101001001000110000100 #
b11010101110101001001000110000100 -
b11010101110101001001000110000100 3
1&
#2100000
0&
#2110000
b10 2
b11010101110101000111010011011111 #
b11010101110101000111010011011111 -
b11010101110101000111010011011111 3
10
b1111 1
1&
#2120000
0&
#2130000
b11111111111111111110110000000000 )
b11111111111111111110110000000000 +
b11111111111111111111110000000000 (
b11111111111111111111110000000000 *
b1 2
1"
1!
b10 4
00
b0 1
b11010101110101000110011010001101 #
b11010101110101000110011010001101 -
b11010101110101000110011010001101 3
1&
#2140000
0&
#2150000
b1000000000000 /
b11011110010000000000000000000000 #
b11011110010000000000000000000000 -
b11011110010000000000000000000000 3
b1000000000000 6
b1100000000000 $
b1100000000000 ,
b1100000000000 5
0"
0!
b1 4
1&
#2160000
0&
#2170000
b10000000000 /
b1 1
b11100100111001000010100111001100 #
b11100100111001000010100111001100 -
b11100100111001000010100111001100 3
b10000000000 6
b10000000000000 $
b10000000000000 ,
b10000000000000 5
1&
#2180000
0&
#2190000
b10000000000 /
b11101000011001100111101110011100 #
b11101000011001100111101110011100 -
b11101000011001100111101110011100 3
b11111111111111111111110000000000 6
b10000100000000 $
b10000100000000 ,
b10000100000000 5
b10 1
1&
#2200000
0&
#2210000
b100000 /
b11 1
b11100110100111100111101101011000 #
b11100110100111100111101101011000 -
b11100110100111100111101101011000 3
b100000 6
b10000110000000 $
b10000110000000 ,
b10000110000000 5
1&
#2220000
0&
#2230000
b111111000 /
b11100111100000110101111000000001 #
b11100111100000110101111000000001 -
b11100111100000110101111000000001 3
b11111111111111111111111000001000 6
b10000110000010 $
b10000110000010 ,
b10000110000010 5
b100 1
1&
#2240000
0&
#2250000
b11101100 /
b101 1
b11100111000100001101000000011100 #
b11100111000100001101000000011100 -
b11100111000100001101000000011100 3
b11111111111111111111111100010100 6
b10000110010001 $
b10000110010001 ,
b10000110010001 5
1&
#2260000
0&
#2270000
b1100110 /
b11100110110101111000010110010110 #
b11100110110101111000010110010110 -
b11100110110101111000010110010110 3
b11111111111111111111111110011010 6
b10000110010100 $
b10000110010100 ,
b10000110010100 5
b110 1
1&
#2280000
0&
#2290000
b100011 /
b111 1
b11100110101110101101111111100001 #
b11100110101110101101111111100001 -
b11100110101110101101111111100001 3
b11111111111111111111111111011101 6
1&
#2300000
0&
#2310000
b10 /
b11100110101011001000110011111000 #
b11100110101011001000110011111000 -
b11100110101011001000110011111000 3
b11111111111111111111111111111110 6
b1000 1
1&
#2320000
0&
#2330000
b1110 /
b1001 1
b11100110101001010110001110000010 #
b11100110101001010110001110000010 -
b11100110101001010110001110000010 3
b1110 6
1&
#2340000
0&
#2350000
b110 /
b11100110101010001111100000111101 #
b11100110101010001111100000111101 -
b11100110101010001111100000111101 3
b110 6
b1010 1
1&
#2360000
0&
