postprocess/dec_to_polar/dec_to_polar.sv

module	topolar 
#(
    parameter WIDTH = 32
)
(
	input                              clk, 
	input                              rst, 
	
	input                              i_vld,
	input   logic signed [WIDTH - 1:0] i_x, 
	input   logic signed [WIDTH - 1:0] i_y,

	output  logic                      o_vld,
	output	logic signed [WIDTH - 1:0] o_mag,
	output	logic signed [31:0]	       o_phase
	);
	localparam NSTAGES = 16;
	//
	logic signed [31:0] cordic_angle [0:(NSTAGES-1)];
	assign	cordic_angle[ 0] = 32'h1dac_6705; //  26.565051 deg
	assign	cordic_angle[ 1] = 32'h0fad_bafc; //  14.036243 deg
	assign	cordic_angle[ 2] = 32'h07f5_6ea6; //   7.125016 deg
	assign	cordic_angle[ 3] = 32'h03fe_ab76; //   3.576334 deg
	assign	cordic_angle[ 4] = 32'h01ff_d55b; //   1.789911 deg
	assign	cordic_angle[ 5] = 32'h00ff_faaa; //   0.895174 deg
	assign	cordic_angle[ 6] = 32'h007f_ff55; //   0.447614 deg
	assign	cordic_angle[ 7] = 32'h003f_ffea; //   0.223811 deg
	assign	cordic_angle[ 8] = 32'h001f_fffd; //   0.111906 deg
	assign	cordic_angle[ 9] = 32'h000f_ffff; //   0.055953 deg
	assign	cordic_angle[10] = 32'h0007_ffff; //   0.027976 deg
	assign	cordic_angle[11] = 32'h0003_ffff; //   0.013988 deg
	assign	cordic_angle[12] = 32'h0001_ffff; //   0.006994 deg
	assign	cordic_angle[13] = 32'h0000_ffff; //   0.003497 deg
	assign	cordic_angle[14] = 32'h0000_7fff; //   0.001749 deg
	assign	cordic_angle[15] = 32'h0000_3fff; //   0.000874 deg
	//assign	cordic_angle[16] = 32'h0000_1fff; //   0.000437 deg
	//assign	cordic_angle[17] = 32'h0000_0fff; //   0.000219 deg

	logic	signed [NSTAGES:0] [WIDTH-1:0]	xs;
	logic	signed [NSTAGES:0] [WIDTH-1:0]	ys;
	logic	signed [NSTAGES:0] [WIDTH-1:0]	phs;
	logic          [NSTAGES:0]              valids;
    
	// Предварительный поворот в сектор -45 45
	always_ff @(posedge clk) begin
		if (rst) valids[0] <= 'b0;
		else begin
			valids[0] <= i_vld;
			if (i_vld) begin
				case ({i_y[WIDTH-1], i_x[WIDTH-1]} )
					2'b00:begin
						xs[0]  <= i_x + i_y;
						ys[0]  <= i_y - i_x;
						// Угол в радианах
						// 1  - знак
						// 1  - целая часть
						// 30 - дробная часть
						phs[0] <= 32'h3243f6a8;    // 45 градусов
					end
					2'b01:begin
						xs[0]  <= i_y - i_x;
						ys[0]  <= -i_x - i_y;
						phs[0] <= 32'hcdbc0958;    //135 - 180
					end
					2'b11:begin
						xs[0]  <= -i_y - i_x;
						ys[0]  <= i_x - i_y;
						phs[0] <= 32'h3243f6a8;    //225 - 180
					end
					2'b01:begin
						xs[0]  <= i_x - i_y;
						ys[0]  <= i_x + i_y;
						phs[0] <= 32'hcdbc0958;    //315 - 360
					end
					default: begin
						xs[0]  <= i_x + i_y;
						ys[0]  <= i_y - i_x;
						phs[0] <= 32'h3243f6a8;
					end
				endcase
			end
		end
	end

	genvar	i;
	generate for(i = 0; i < NSTAGES; i++) begin : TOPOLARloop
		always @(posedge clk)
		if (rst)begin
			valids[i+1] <= 'b0;
		end 
		else begin
			valids[i+1] <= valids[i];
			if (valids[i]) begin
				if (~ys[i][WIDTH-1]) begin
					xs[i+1] <= xs[i] + {{(i+1){ys[i][WIDTH-1]}}, ys[i][WIDTH-1:(i+1)]};
					ys[i+1] <= ys[i] - {{(i+1){xs[i][WIDTH-1]}}, xs[i][WIDTH-1:(i+1)]};
					phs[i+1] <= phs[i] + cordic_angle[i];
				end 
				else begin
					xs[i+1] <= xs[i] - {{(i+1){ys[i][WIDTH-1]}}, ys[i][WIDTH-1:(i+1)]};
					ys[i+1] <= ys[i] + {{(i+1){xs[i][WIDTH-1]}}, xs[i][WIDTH-1:(i+1)]};
					phs[i+1] <= phs[i] - cordic_angle[i];
				end
			end
		end
	end 
	endgenerate

	assign o_mag = xs[NSTAGES];
    assign o_phase = phs[NSTAGES];
	assign o_vld = valids[NSTAGES];

endmodule

postprocess/dec_to_polar/testbench.sv
`timescale 1ns/1ps

module test;
    // Подключение

    logic                clk;
    logic                arstn;
    logic                enable;

    logic signed	[31:0] i_xval, i_yval;
    logic i_vld;

    logic signed	[31:0] o_mag;
    logic signed	[31:0] o_phase;
    logic o_vld;

    topolar tp (
        .clk           (clk),
        .rst         (~arstn),

        .i_vld (i_vld),
        .i_x (i_xval),
        .i_y (i_yval),

        .o_mag (o_mag),
        .o_phase (o_phase),
        .o_vld (o_vld)

    );

    initial begin
        $dumpfile("syst_node.vcd");
        $dumpvars;
    end

    // Генерация clk
    parameter CLK_PERIOD = 20; // 50 МГц
    initial begin
        clk <= 0;
        forever begin
            #(CLK_PERIOD / 2); clk <= ~clk;
        end
    end

    //Генерация rst
    initial begin
        arstn <= 0;
        @(posedge clk);
        @(posedge clk);
        @(posedge clk);
        arstn <= 1;
    end

    // Генерация входных сигналов
    initial begin
        i_vld <= 'b0;
        wait(arstn);
        @(posedge clk);
    //---------------------------------------------------------------------------------------------
        @(posedge clk);
        i_vld <= 'b1;
        i_xval <= 32'd1572864;
        i_yval <= 32'd1638400;
        @(posedge clk);
        i_vld <= 'b0;
    //---------------------------------------------------------------------------------------------
        repeat(18) begin
            @(posedge clk);
        end
        @(posedge clk);
        @(posedge clk);
        @(posedge clk);
        $finish;
    end
    
    // Проверка
    // initial begin
    //     wait(~arstn);
    //     @(posedge clk);
    //     @(posedge clk);
    // //---------------------------------------------------------------------------------------------
    //     repeat (32)
    //     begin
    //         @(posedge clk);
    //         if ($signed(psumm_o) != ($signed(psumm_i) + $signed(weight_i) * $signed(x_i) )) begin
    //             $display($signed(psumm_o));
    //             $display(($signed(psumm_i) + $signed(weight_i) * $signed(x_i)));
    //             $display($signed(psumm_i));
    //             $display($signed(weight_i));
    //             $display($signed(x_i));
    //             $error("BAD");
    //         end
    //         else begin
    //             $display("PASS");
    //             // $display($signed(psumm_o));
    //             // $display($signed(psumm_i));
    //             // $display($signed(weight_i));
    //             // $display($signed(x_i));
    //         end
    //     end
    // //---------------------------------------------------------------------------------------------
    //     @(posedge clk);
    //     @(posedge clk);
    //     @(posedge clk);
    //     $finish;
    // end
endmodule

postprocess/syst_node.vcd
$date
	Fri Mar 21 12:06:23 2025
$end
$version
	Icarus Verilog
$end
$timescale
	1ps
$end
$scope module test $end
$var wire 1 ! o_vld $end
$var wire 32 " o_phase [31:0] $end
$var wire 32 # o_mag [31:0] $end
$var reg 1 $ arstn $end
$var reg 1 % clk $end
$var reg 1 & i_vld $end
$var reg 32 ' i_xval [31:0] $end
$var reg 32 ( i_yval [31:0] $end
$scope module tp $end
$var wire 1 % clk $end
$var wire 1 & i_vld $end
$var wire 32 ) i_x [31:0] $end
$var wire 32 * i_y [31:0] $end
$var wire 1 + rst $end
$var wire 1 ! o_vld $end
$var wire 32 , o_phase [31:0] $end
$var wire 32 - o_mag [31:0] $end
$var reg 544 . phs [543:0] $end
$var reg 17 / valids [16:0] $end
$var reg 544 0 xs [543:0] $end
$var reg 544 1 ys [543:0] $end
$scope begin TOPOLARloop[0] $end
$upscope $end
$scope begin TOPOLARloop[1] $end
$upscope $end
$scope begin TOPOLARloop[2] $end
$upscope $end
$scope begin TOPOLARloop[3] $end
$upscope $end
$scope begin TOPOLARloop[4] $end
$upscope $end
$scope begin TOPOLARloop[5] $end
$upscope $end
$scope begin TOPOLARloop[6] $end
$upscope $end
$scope begin TOPOLARloop[7] $end
$upscope $end
$scope begin TOPOLARloop[8] $end
$upscope $end
$scope begin TOPOLARloop[9] $end
$upscope $end
$scope begin TOPOLARloop[10] $end
$upscope $end
$scope begin TOPOLARloop[11] $end
$upscope $end
$scope begin TOPOLARloop[12] $end
$upscope $end
$scope begin TOPOLARloop[13] $end
$upscope $end
$scope begin TOPOLARloop[14] $end
$upscope $end
$scope begin TOPOLARloop[15] $end
$upscope $end
$upscope $end
$upscope $end
$enddefinitions $end
#0
$dumpvars
bx 1
bx 0
bx /
bx .
bx -
bx ,
1+
bx *
bx )
bx (
bx '
0&
0%
0$
bx #
bx "
x!
$end
#10000
0!
b0 /
1%
#20000
0%
#30000
1%
#40000
0%
#50000
0+
1$
1%
#60000
0%
#70000
1%
#80000
0%
#90000
b110010000000000000000 (
b110010000000000000000 *
b110000000000000000000 '
b110000000000000000000 )
1&
1%
#100000
0%
#110000
bx00110010010000111111011010101000 .
bx00000000000000010000000000000000 1
bx00000000001100010000000000000000 0
b1 /
0&
1%
#120000
0%
#130000
bx0100111111110000010111011010110100110010010000111111011010101000 .
bx1111111111101000100000000000000000000000000000010000000000000000 1
bx0000000000110001100000000000000000000000001100010000000000000000 0
b10 /
1%
#140000
0%
#150000
bx010000000100001010100010101100010100111111110000010111011010110100110010010000111111011010101000 .
bx111111111111010011100000000000001111111111101000100000000000000000000000000000010000000000000000 1
bx000000000011011101100000000000000000000000110001100000000000000000000000001100010000000000000000 0
b100 /
1%
#160000
0%
#170000
bx00111000010011010011010000001011010000000100001010100010101100010100111111110000010111011010110100110010010000111111011010101000 .
bx11111111111110111100110000000000111111111111010011100000000000001111111111101000100000000000000000000000000000010000000000000000 1
bx00000000001110001100010000000000000000000011011101100000000000000000000000110001100000000000000000000000001100010000000000000000 0
b1000 /
1%
#180000
0%
#190000
bx0011010001001110100010001001010100111000010011010011010000001011010000000100001010100010101100010100111111110000010111011010110100110010010000111111011010101000 .
bx1111111111111111010110000100000011111111111110111100110000000000111111111111010011100000000000001111111111101000100000000000000000000000000000010000000000000000 1
bx0000000000111001000001110100000000000000001110001100010000000000000000000011011101100000000000000000000000110001100000000000000000000000001100010000000000000000 0
b10000 /
1%
#200000
0%
#210000
bx001100100100111010110011001110100011010001001110100010001001010100111000010011010011010000001011010000000100001010100010101100010100111111110000010111011010110100110010010000111111011010101000 .
bx000000000000000100100000011110101111111111111111010110000100000011111111111110111100110000000000111111111111010011100000000000001111111111101000100000000000000000000000000000010000000000000000 1
bx000000000011100100001100011111100000000000111001000001110100000000000000001110001100010000000000000000000011011101100000000000000000000000110001100000000000000000000000001100010000000000000000 0
b100000 /
1%
#220000
0%
#230000
bx00110011010011101010110111100100001100100100111010110011001110100011010001001110100010001001010100111000010011010011010000001011010000000100001010100010101100010100111111110000010111011010110100110010010000111111011010101000 .
bx00000000000000000011110001001001000000000000000100100000011110101111111111111111010110000100000011111111111110111100110000000000111111111111010011100000000000001111111111101000100000000000000000000000000000010000000000000000 1
bx00000000001110010001000011111111000000000011100100001100011111100000000000111001000001110100000000000000001110001100010000000000000000000011011101100000000000000000000000110001100000000000000000000000001100010000000000000000 0
b1000000 /
1%
#240000
0%
#250000
bx0011001111001110101011010011100100110011010011101010110111100100001100100100111010110011001110100011010001001110100010001001010100111000010011010011010000001011010000000100001010100010101100010100111111110000010111011010110100110010010000111111011010101000 .
bx1111111111111111110010100010100000000000000000000011110001001001000000000000000100100000011110101111111111111111010110000100000011111111111110111100110000000000111111111111010011100000000000001111111111101000100000000000000000000000000000010000000000000000 1
bx0000000000111001000100010111011100000000001110010001000011111111000000000011100100001100011111100000000000111001000001110100000000000000001110001100010000000000000000000011011101100000000000000000000000110001100000000000000000000000001100010000000000000000 0
b10000000 /
1%
#260000
0%
#270000
bx001100111000111010101101010011110011001111001110101011010011100100110011010011101010110111100100001100100100111010110011001110100011010001001110100010001001010100111000010011010011010000001011010000000100001010100010101100010100111111110000010111011010110100110010010000111111011010101000 .
bx000000000000000000000011001110011111111111111111110010100010100000000000000000000011110001001001000000000000000100100000011110101111111111111111010110000100000011111111111110111100110000000000111111111111010011100000000000001111111111101000100000000000000000000000000000010000000000000000 1
bx000000000011100100010001101011010000000000111001000100010111011100000000001110010001000011111111000000000011100100001100011111100000000000111001000001110100000000000000001110001100010000000000000000000011011101100000000000000000000000110001100000000000000000000000001100010000000000000000 0
b100000000 /
1%
#280000
0%
#290000
bx00110011101011101010110101001100001100111000111010101101010011110011001111001110101011010011100100110011010011101010110111100100001100100100111010110011001110100011010001001110100010001001010100111000010011010011010000001011010000000100001010100010101100010100111111110000010111011010110100110010010000111111011010101000 .
bx11111111111111111110011010110001000000000000000000000011001110011111111111111111110010100010100000000000000000000011110001001001000000000000000100100000011110101111111111111111010110000100000011111111111110111100110000000000111111111111010011100000000000001111111111101000100000000000000000000000000000010000000000000000 1
bx00000000001110010001000110101110000000000011100100010001101011010000000000111001000100010111011100000000001110010001000011111111000000000011100100001100011111100000000000111001000001110100000000000000001110001100010000000000000000000011011101100000000000000000000000110001100000000000000000000000001100010000000000000000 0
b1000000000 /
1%
#300000
0%
#310000
bx0011001110011110101011010100110100110011101011101010110101001100001100111000111010101101010011110011001111001110101011010011100100110011010011101010110111100100001100100100111010110011001110100011010001001110100010001001010100111000010011010011010000001011010000000100001010100010101100010100111111110000010111011010110100110010010000111111011010101000 .
bx1111111111111111111101001111010111111111111111111110011010110001000000000000000000000011001110011111111111111111110010100010100000000000000000000011110001001001000000000000000100100000011110101111111111111111010110000100000011111111111110111100110000000000111111111111010011100000000000001111111111101000100000000000000000000000000000010000000000000000 1
bx0000000000111001000100011011010100000000001110010001000110101110000000000011100100010001101011010000000000111001000100010111011100000000001110010001000011111111000000000011100100001100011111100000000000111001000001110100000000000000001110001100010000000000000000000011011101100000000000000000000000110001100000000000000000000000001100010000000000000000 0
b10000000000 /
1%
#320000
0%
#330000
bx001100111001011010101101010011100011001110011110101011010100110100110011101011101010110101001100001100111000111010101101010011110011001111001110101011010011100100110011010011101010110111100100001100100100111010110011001110100011010001001110100010001001010100111000010011010011010000001011010000000100001010100010101100010100111111110000010111011010110100110010010000111111011010101000 .
bx111111111111111111111100000101111111111111111111111101001111010111111111111111111110011010110001000000000000000000000011001110011111111111111111110010100010100000000000000000000011110001001001000000000000000100100000011110101111111111111111010110000100000011111111111110111100110000000000111111111111010011100000000000001111111111101000100000000000000000000000000000010000000000000000 1
bx000000000011100100010001101101110000000000111001000100011011010100000000001110010001000110101110000000000011100100010001101011010000000000111001000100010111011100000000001110010001000011111111000000000011100100001100011111100000000000111001000001110100000000000000001110001100010000000000000000000011011101100000000000000000000000110001100000000000000000000000001100010000000000000000 0
b100000000000 /
1%
#340000
0%
#350000
bx00110011100100101010110101001111001100111001011010101101010011100011001110011110101011010100110100110011101011101010110101001100001100111000111010101101010011110011001111001110101011010011100100110011010011101010110111100100001100100100111010110011001110100011010001001110100010001001010100111000010011010011010000001011010000000100001010100010101100010100111111110000010111011010110100110010010000111111011010101000 .
bx11111111111111111111111110101000111111111111111111111100000101111111111111111111111101001111010111111111111111111110011010110001000000000000000000000011001110011111111111111111110010100010100000000000000000000011110001001001000000000000000100100000011110101111111111111111010110000100000011111111111110111100110000000000111111111111010011100000000000001111111111101000100000000000000000000000000000010000000000000000 1
bx00000000001110010001000110111000000000000011100100010001101101110000000000111001000100011011010100000000001110010001000110101110000000000011100100010001101011010000000000111001000100010111011100000000001110010001000011111111000000000011100100001100011111100000000000111001000001110100000000000000001110001100010000000000000000000011011101100000000000000000000000110001100000000000000000000000001100010000000000000000 0
b1000000000000 /
1%
#360000
0%
#370000
bx0011001110010000101011010101000000110011100100101010110101001111001100111001011010101101010011100011001110011110101011010100110100110011101011101010110101001100001100111000111010101101010011110011001111001110101011010011100100110011010011101010110111100100001100100100111010110011001110100011010001001110100010001001010100111000010011010011010000001011010000000100001010100010101100010100111111110000010111011010110100110010010000111111011010101000 .
bx0000000000000000000000010111000011111111111111111111111110101000111111111111111111111100000101111111111111111111111101001111010111111111111111111110011010110001000000000000000000000011001110011111111111111111110010100010100000000000000000000011110001001001000000000000000100100000011110101111111111111111010110000100000011111111111110111100110000000000111111111111010011100000000000001111111111101000100000000000000000000000000000010000000000000000 1
bx0000000000111001000100011011100100000000001110010001000110111000000000000011100100010001101101110000000000111001000100011011010100000000001110010001000110101110000000000011100100010001101011010000000000111001000100010111011100000000001110010001000011111111000000000011100100001100011111100000000000111001000001110100000000000000001110001100010000000000000000000011011101100000000000000000000000110001100000000000000000000000001100010000000000000000 0
b10000000000000 /
1%
#380000
0%
#390000
bx001100111001000110101101010011110011001110010000101011010101000000110011100100101010110101001111001100111001011010101101010011100011001110011110101011010100110100110011101011101010110101001100001100111000111010101101010011110011001111001110101011010011100100110011010011101010110111100100001100100100111010110011001110100011010001001110100010001001010100111000010011010011010000001011010000000100001010100010101100010100111111110000010111011010110100110010010000111111011010101000 .
bx000000000000000000000000100011000000000000000000000000010111000011111111111111111111111110101000111111111111111111111100000101111111111111111111111101001111010111111111111111111110011010110001000000000000000000000011001110011111111111111111110010100010100000000000000000000011110001001001000000000000000100100000011110101111111111111111010110000100000011111111111110111100110000000000111111111111010011100000000000001111111111101000100000000000000000000000000000010000000000000000 1
bx000000000011100100010001101110010000000000111001000100011011100100000000001110010001000110111000000000000011100100010001101101110000000000111001000100011011010100000000001110010001000110101110000000000011100100010001101011010000000000111001000100010111011100000000001110010001000011111111000000000011100100001100011111100000000000111001000001110100000000000000001110001100010000000000000000000011011101100000000000000000000000110001100000000000000000000000001100010000000000000000 0
b100000000000000 /
1%
#400000
0%
#410000
bx00110011100100100010110101001110001100111001000110101101010011110011001110010000101011010101000000110011100100101010110101001111001100111001011010101101010011100011001110011110101011010100110100110011101011101010110101001100001100111000111010101101010011110011001111001110101011010011100100110011010011101010110111100100001100100100111010110011001110100011010001001110100010001001010100111000010011010011010000001011010000000100001010100010101100010100111111110000010111011010110100110010010000111111011010101000 .
bx00000000000000000000000000011010000000000000000000000000100011000000000000000000000000010111000011111111111111111111111110101000111111111111111111111100000101111111111111111111111101001111010111111111111111111110011010110001000000000000000000000011001110011111111111111111110010100010100000000000000000000011110001001001000000000000000100100000011110101111111111111111010110000100000011111111111110111100110000000000111111111111010011100000000000001111111111101000100000000000000000000000000000010000000000000000 1
bx00000000001110010001000110111001000000000011100100010001101110010000000000111001000100011011100100000000001110010001000110111000000000000011100100010001101101110000000000111001000100011011010100000000001110010001000110101110000000000011100100010001101011010000000000111001000100010111011100000000001110010001000011111111000000000011100100001100011111100000000000111001000001110100000000000000001110001100010000000000000000000011011101100000000000000000000000110001100000000000000000000000001100010000000000000000 0
b1000000000000000 /
1%
#420000
0%
#430000
b110011100100100110110101001101 "
b110011100100100110110101001101 ,
b1110010001000110111001 #
b1110010001000110111001 -
1!
b11001110010010011011010100110100110011100100100010110101001110001100111001000110101101010011110011001110010000101011010101000000110011100100101010110101001111001100111001011010101101010011100011001110011110101011010100110100110011101011101010110101001100001100111000111010101101010011110011001111001110101011010011100100110011010011101010110111100100001100100100111010110011001110100011010001001110100010001001010100111000010011010011010000001011010000000100001010100010101100010100111111110000010111011010110100110010010000111111011010101000 .
b1111111111111111111111111110000100000000000000000000000000011010000000000000000000000000100011000000000000000000000000010111000011111111111111111111111110101000111111111111111111111100000101111111111111111111111101001111010111111111111111111110011010110001000000000000000000000011001110011111111111111111110010100010100000000000000000000011110001001001000000000000000100100000011110101111111111111111010110000100000011111111111110111100110000000000111111111111010011100000000000001111111111101000100000000000000000000000000000010000000000000000 1
b111001000100011011100100000000001110010001000110111001000000000011100100010001101110010000000000111001000100011011100100000000001110010001000110111000000000000011100100010001101101110000000000111001000100011011010100000000001110010001000110101110000000000011100100010001101011010000000000111001000100010111011100000000001110010001000011111111000000000011100100001100011111100000000000111001000001110100000000000000001110001100010000000000000000000011011101100000000000000000000000110001100000000000000000000000001100010000000000000000 0
b10000000000000000 /
1%
#440000
0%
#450000
0!
b0 /
1%
