postprocess/dec_to_polar/dec_to_polar.sv

module	topolar 
#(
    parameter WIDTH = 32
)
(
	input                              clk, 
	input                              rst, 
	
	input                              i_vld,
	input   logic signed [WIDTH - 1:0] i_x, 
	input   logic signed [WIDTH - 1:0] i_y,

	output  logic                      o_vld,
	output	logic signed [WIDTH - 1:0] o_mag,
	output	logic signed [31:0]	       o_phase
	);
	localparam NSTAGES = 16;
	//
	logic signed [31:0] cordic_angle [0:(NSTAGES-1)];
	assign	cordic_angle[ 0] = 32'h076b_19c1; //  26.565051 deg
	assign	cordic_angle[ 1] = 32'h03eb_6ebf; //  14.036243 deg
	assign	cordic_angle[ 2] = 32'h01fd_5ba9; //   7.125016 deg
	assign	cordic_angle[ 3] = 32'h00ff_aadd; //   3.576334 deg
	assign	cordic_angle[ 4] = 32'h007f_f556; //   1.789911 deg
	assign	cordic_angle[ 5] = 32'h003f_feaa; //   0.895174 deg
	assign	cordic_angle[ 6] = 32'h001f_ffd5; //   0.447614 deg
	assign	cordic_angle[ 7] = 32'h000f_fffa; //   0.223811 deg
	assign	cordic_angle[ 8] = 32'h0007_ffff; //   0.111906 deg
	assign	cordic_angle[ 9] = 32'h0003_ffff; //   0.055953 deg
	assign	cordic_angle[10] = 32'h0001_ffff; //   0.027976 deg
	assign	cordic_angle[11] = 32'h0000_ffff; //   0.013988 deg
	assign	cordic_angle[12] = 32'h0000_7fff; //   0.006994 deg
	assign	cordic_angle[13] = 32'h0000_3fff; //   0.003497 deg
	assign	cordic_angle[14] = 32'h0000_1fff; //   0.001749 deg
	assign	cordic_angle[15] = 32'h0000_0fff; //   0.000874 deg
	//assign	cordic_angle[16] = 32'h0000_1fff; //   0.000437 deg
	//assign	cordic_angle[17] = 32'h0000_0fff; //   0.000219 deg

	logic	signed [NSTAGES:0] [WIDTH-1:0]	xs;
	logic	signed [NSTAGES:0] [WIDTH-1:0]	ys;
	logic	signed [NSTAGES:0] [WIDTH-1:0]	phs;
	logic          [NSTAGES:0]              valids;
    
	// Предварительный поворот в сектор -45 45
	always_ff @(posedge clk) begin
		if (rst) valids[0] <= 'b0;
		else begin
			valids[0] <= i_vld;
			if (i_vld) begin
				case ({i_y[WIDTH-1], i_x[WIDTH-1]} )
					2'b00:begin
						xs[0]  <= i_x + i_y;
						ys[0]  <= i_y - i_x;
						// Угол в радианах
						// 1  - знак
						// 3  - целая часть
						// 28 - дробная часть
						phs[0] <= 32'h0c90_fdaa;    // 45 градусов
					end
					2'b01:begin
						xs[0]  <= i_y - i_x;
						ys[0]  <= -i_x - i_y;
						phs[0] <= 32'h25b2_f8fe;    //135
					end
					2'b11:begin
						xs[0]  <= -i_y - i_x;
						ys[0]  <= i_x - i_y;
						phs[0] <= 32'hda4d_0702;    //225 - 360
					end
					2'b01:begin
						xs[0]  <= i_x - i_y;
						ys[0]  <= i_x + i_y;
						phs[0] <= 32'hf36f_0256;    //315 - 360
					end
					default: begin
						xs[0]  <= i_x + i_y;
						ys[0]  <= i_y - i_x;
						phs[0] <= 32'h0c90_fdaa;
					end
				endcase
			end
		end
	end

	genvar	i;
	generate for(i = 0; i < NSTAGES; i++) begin : TOPOLARloop
		always @(posedge clk)
		if (rst)begin
			valids[i+1] <= 'b0;
		end 
		else begin
			valids[i+1] <= valids[i];
			if (valids[i]) begin
				if (~ys[i][WIDTH-1]) begin
					xs[i+1] <= xs[i] + {{(i+1){ys[i][WIDTH-1]}}, ys[i][WIDTH-1:(i+1)]};
					ys[i+1] <= ys[i] - {{(i+1){xs[i][WIDTH-1]}}, xs[i][WIDTH-1:(i+1)]};
					phs[i+1] <= phs[i] + cordic_angle[i];
				end 
				else begin
					xs[i+1] <= xs[i] - {{(i+1){ys[i][WIDTH-1]}}, ys[i][WIDTH-1:(i+1)]};
					ys[i+1] <= ys[i] + {{(i+1){xs[i][WIDTH-1]}}, xs[i][WIDTH-1:(i+1)]};
					phs[i+1] <= phs[i] - cordic_angle[i];
				end
			end
		end
	end 
	endgenerate

	assign o_mag = xs[NSTAGES];
    assign o_phase = phs[NSTAGES];
	assign o_vld = valids[NSTAGES];

endmodule

postprocess/dec_to_polar/testbench.sv
`timescale 1ns/1ps

module test;
    // Подключение

    logic                clk;
    logic                arstn;
    logic                enable;

    logic signed	[31:0] i_xval, i_yval;
    logic i_vld;

    logic signed	[31:0] o_mag;
    logic signed	[31:0] o_phase;
    logic o_vld;

    topolar tp (
        .clk           (clk),
        .rst         (~arstn),

        .i_vld (i_vld),
        .i_x (i_xval),
        .i_y (i_yval),

        .o_mag (o_mag),
        .o_phase (o_phase),
        .o_vld (o_vld)

    );

    initial begin
        $dumpfile("syst_node.vcd");
        $dumpvars;
    end

    // Генерация clk
    parameter CLK_PERIOD = 20; // 50 МГц
    initial begin
        clk <= 0;
        forever begin
            #(CLK_PERIOD / 2); clk <= ~clk;
        end
    end

    //Генерация rst
    initial begin
        arstn <= 0;
        @(posedge clk);
        @(posedge clk);
        @(posedge clk);
        arstn <= 1;
    end

    // Генерация входных сигналов
    initial begin
        i_vld <= 'b0;
        wait(arstn);
        @(posedge clk);
    //---------------------------------------------------------------------------------------------
        @(posedge clk);
        i_vld <= 'b1;
        i_xval <= 32'd1 << 'd10;
        i_yval <= 32'd1 << 'd10;
        $display("%d", 32'd1);
        $display("%d", 32'd1);

        @(posedge clk);
        i_vld <= 'b1;
        i_xval <= 32'd5 << 'd10;
        i_yval <= 32'd1 << 'd10;
        $display("%d", 32'd5);
        $display("%d", 32'd1);
        @(posedge clk);
        i_vld <= 'b1;
        i_xval <= 32'd1 << 'd10;
        i_yval <= 32'd5 << 'd10;
        $display("%d", 32'd1);
        $display("%d", 32'd5);

        @(posedge clk);
        i_vld <= 'b1;
        i_xval <= -32'd5 << 'd10;
        i_yval <= 32'd1 << 'd10;
        $display("-%d", 32'd5);
        $display("%d", 32'd1);
        @(posedge clk);
        i_vld <= 'b1;
        i_xval <= -32'd1 << 'd10;
        i_yval <= 32'd5 << 'd10;
        $display("-%d", 32'd1);
        $display("%d", 32'd5);

        @(posedge clk);
        i_vld <= 'b1;
        i_xval <= -32'd5 << 'd10;
        i_yval <= -32'd1 << 'd10;
        $display("-%d", 32'd5);
        $display("-%d", 32'd1);
        @(posedge clk);
        i_vld <= 'b1;
        i_xval <= -32'd1 << 'd10;
        i_yval <= -32'd5 << 'd10;
        $display("-%d", 32'd1);
        $display("-%d", 32'd5);

        @(posedge clk);
        i_vld <= 'b1;
        i_xval <= 32'd5 << 'd10;
        i_yval <= -32'd1 << 'd10;
        $display("%d", 32'd5);
        $display("-%d", 32'd1);
        @(posedge clk);
        i_vld <= 'b1;
        i_xval <= 32'd1 << 'd10;
        i_yval <= -32'd5 << 'd10;
        $display("%d", 32'd1);
        $display("-%d", 32'd5);

        @(posedge o_vld);
        $display("RESULTS");
        repeat(9) begin
            @(posedge clk);
            $display("%d", o_phase);
        end

    //---------------------------------------------------------------------------------------------
        repeat(18) begin
            @(posedge clk);
        end
        @(posedge clk);
        @(posedge clk);
        @(posedge clk);
        $finish;
    end
endmodule

postprocess/syst_node.vcd
$date
	Fri Mar 21 15:58:13 2025
$end
$version
	Icarus Verilog
$end
$timescale
	1ps
$end
$scope module test $end
$var wire 1 ! o_vld $end
$var wire 32 " o_phase [31:0] $end
$var wire 32 # o_mag [31:0] $end
$var reg 1 $ arstn $end
$var reg 1 % clk $end
$var reg 1 & i_vld $end
$var reg 32 ' i_xval [31:0] $end
$var reg 32 ( i_yval [31:0] $end
$scope module tp $end
$var wire 1 % clk $end
$var wire 1 & i_vld $end
$var wire 32 ) i_x [31:0] $end
$var wire 32 * i_y [31:0] $end
$var wire 1 + rst $end
$var wire 1 ! o_vld $end
$var wire 32 , o_phase [31:0] $end
$var wire 32 - o_mag [31:0] $end
$var reg 544 . phs [543:0] $end
$var reg 17 / valids [16:0] $end
$var reg 544 0 xs [543:0] $end
$var reg 544 1 ys [543:0] $end
$scope begin TOPOLARloop[0] $end
$upscope $end
$scope begin TOPOLARloop[1] $end
$upscope $end
$scope begin TOPOLARloop[2] $end
$upscope $end
$scope begin TOPOLARloop[3] $end
$upscope $end
$scope begin TOPOLARloop[4] $end
$upscope $end
$scope begin TOPOLARloop[5] $end
$upscope $end
$scope begin TOPOLARloop[6] $end
$upscope $end
$scope begin TOPOLARloop[7] $end
$upscope $end
$scope begin TOPOLARloop[8] $end
$upscope $end
$scope begin TOPOLARloop[9] $end
$upscope $end
$scope begin TOPOLARloop[10] $end
$upscope $end
$scope begin TOPOLARloop[11] $end
$upscope $end
$scope begin TOPOLARloop[12] $end
$upscope $end
$scope begin TOPOLARloop[13] $end
$upscope $end
$scope begin TOPOLARloop[14] $end
$upscope $end
$scope begin TOPOLARloop[15] $end
$upscope $end
$upscope $end
$upscope $end
$enddefinitions $end
#0
$dumpvars
bx 1
bx 0
bx /
bx .
bx -
bx ,
1+
bx *
bx )
bx (
bx '
0&
0%
0$
bx #
bx "
x!
$end
#10000
0!
b0 /
1%
#20000
0%
#30000
1%
#40000
0%
#50000
0+
1$
1%
#60000
0%
#70000
1%
#80000
0%
#90000
b10000000000 (
b10000000000 *
b10000000000 '
b10000000000 )
1&
1%
#100000
0%
#110000
bx00001100100100001111110110101010 .
bx00000000000000000000000000000000 1
bx00000000000000000000100000000000 0
b1 /
b1010000000000 '
b1010000000000 )
1%
#120000
0%
#130000
b1010000000000 (
b1010000000000 *
b10000000000 '
b10000000000 )
bx0001001111111100000101110110101100001100100100001111110110101010 .
b11 /
bx1111111111111111111111000000000011111111111111111111000000000000 1
bx0000000000000000000010000000000000000000000000000001100000000000 0
1%
#140000
0%
#150000
bx111111111111111111111110000000001111111111111111111111000000000000000000000000000001000000000000 1
b111 /
bx000100000001000010101000101011000000010100100101111000111110100100001100100100001111110110101010 .
bx000000000000000000001001000000000000000000000000001000000000000000000000000000000001100000000000 0
b10000000000 (
b10000000000 *
b11111111111111111110110000000000 '
b11111111111111111110110000000000 )
1%
#160000
0%
#170000
b1010000000000 (
b1010000000000 *
b11111111111111111111110000000000 '
b11111111111111111111110000000000 )
bx11111111111111111111111100100000000000000000000000000100000000000000000000000000000001000000000000000000000000000001000000000000 1
bx00000000000000000000100101000000000000000000000000100001000000000000000000000000001000000000000000000000000000000001100000000000 0
b1111 /
bx00001110000100110100110100000011000000010011101001110101001010100001001111111100000101110110101100100101101100101111100011111110 .
1%
#180000
0%
#190000
b11111 /
bx0000000000000000000010010100111000000000000000000010000110000000000000000000000000100001000000000000000000000000001000000000000000000000000000000001100000000000 0
bx1111111111111111111111111011010011111111111111111111111111100000111111111111111111111100000000000000000000000000000001000000000011111111111111111111000000000000 1
bx0000110100010011101000100010011000000011001101111101000011010011000101111110011110000110001010100010110100011110000100101011111100100101101100101111100011111110 .
b11111111111111111111110000000000 (
b11111111111111111111110000000000 *
b11111111111111111110110000000000 '
b11111111111111111110110000000000 )
1%
#200000
0%
#210000
b11111111111111111110110000000000 (
b11111111111111111110110000000000 *
b11111111111111111111110000000000 '
b11111111111111111111110000000000 )
bx111111111111111111111111111111100000000000000000000000011111100000000000000000000000000000100000111111111111111111111100000000001111111111111111111111000000000011111111111111111111000000000000 1
bx000000000000000000001001010100010000000000000000001000011000001000000000000000000010000110000000000000000000000000100001000000000000000000000000001000000000000000000000000000000001100000000000 0
b111111 /
bx000011001001001110101100110100000000001000111000001001011111011000010101111010100010101010000001001100010000100110000001011111100001111001000111110111110011110111011010010011010000011100000010 .
1%
#220000
0%
#230000
b1111111 /
bx00000000000000000000100101010010000000000000000000100001100100010000000000000000001000011000001000000000000000000010000110000000000000000000000000100001000000000000000000000000001000000000000000000000000000000001100000000000 0
bx00000000000000000000000000100011000000000000000000000000111011001111111111111111111111100000100000000000000000000000000000100000000000000000000000000100000000001111111111111111111111000000000000000000000000000001000000000000 1
bx00001100010100111010111000100110000000101011100000011011010011000001011011101001110101010101111000101111000011000010010111010101000110100101110001110000011111101101001011100001111011010100000111011010010011010000011100000010 .
b11111111111111111111110000000000 (
b11111111111111111111110000000000 *
b1010000000000 '
b1010000000000 )
1%
#240000
0%
#250000
b11111111111111111110110000000000 (
b11111111111111111110110000000000 *
b10000000000 '
b10000000000 )
b11111111 /
bx0000110001110011101011011111101100000010111110000001100111110110000101100110100111100000000010000011000000001011110100001011001000011100010110011100110000100111110011101111011001111110100000101110000110111000001000001100001100001100100100001111110110101010 .
bx0000000000000000000000000001000100000000000000000000000001100110111111111111111111111111000101001111111111111111111111100000100011111111111111111111111111100000000000000000000000000100000000000000000000000000000001000000000011111111111111111110100000000000 1
bx0000000000000000000010010101001000000000000000000010000110010100000000000000000000100001100100100000000000000000001000011000001000000000000000000010000110000000000000000000000000100001000000000000000000000000001000000000000000000000000000000001000000000000 0
1%
#260000
0%
#270000
b111111111 /
bx000011001000001110101101111101010000001100011000000110011100101100010110001010011110000101011110001011111000101111011011010111000001101101011010001000010100101011010000111100111101101000101011111001011010001110001111100000100000010100100101111000111110100100001100100100001111110110101010 .
bx000000000000000000000000000010000000000000000000000000000010001111111111111111111111111110011010111111111111111111111111000101000000000000000000000000011111100011111111111111111111111111100000111111111111111111111100000000001111111111111111111100000000000011111111111111111110100000000000 1
bx000000000000000000001001010100100000000000000000001000011001010000000000000000000010000110010110000000000000000000100001100100100000000000000000001000011000001000000000000000000010000110000000000000000000000000100001000000000000000000000000000111000000000011111111111111111111000000000000 0
1%
#280000
0%
#290000
bx00001100100010111010110111110100000000110010100000011001110001010001011000001001111000011000100100101111010010111101110010110010000110111101101000010110101000001100111111110100001011110100111011100011101001100011001111011001000000010011101001110101001010100000010100100101111000111110100100001100100100001111110110101010 .
bx00000000000000000000000000000100000000000000000000000000000000101111111111111111111111111101110111111111111111111111111110011010000000000000000000000000111011000000000000000000000000011111100000000000000000000000000000100000111111111111111111110111000000001111111111111111111000000000000011111111111111111110100000000000 1
bx00000000000000000000100101010010000000000000000000100001100101000000000000000000001000011001011100000000000000000010000110010110000000000000000000100001100100010000000000000000001000011000001000000000000000000010000110000000000000000000000000100000000000001111111111111111111111000000000011111111111111111111000000000000 0
b1111111111 /
1%
#300000
0%
#310000
b11111111111 /
bx0000110010001111101011011111001100000011001100000001100111000100000101011111100111100001100011110010111100101011110111001101110100011100000110100001010101001010110100000111010000100100101001001110010010100101110111101011011011111111001111010001100110000001000000010011101001110101001010100000010100100101111000111110100100001100100100001111110110101010 .
bx0000000000000000000000000000001011111111111111111111111111110010111111111111111111111111111111101111111111111111111111111101110100000000000000000000000001100110000000000000000000000000111011001111111111111111111111100000100011111111111111111111101100000000111111111111111111011111000000001111111111111111111000000000000011111111111111111110100000000000 1
bx0000000000000000000010010101001000000000000000000010000110010100000000000000000000100001100110000000000000000000001000011001011100000000000000000010000110010100000000000000000000100001100100010000000000000000001000011000001000000000000000000010000100100000000000000000000000000100000000001111111111111111111111000000000011111111111111111111000000000000 0
1%
#320000
0%
#330000
bx000011001001000110101101111100100000001100101100000110011100010100010101111100011110000110010000001011110001101111011100111000110001110000111010000101010001111111010000101101000010001101001110111001000010010111101001011000001111111000111101011011101010010011111111001111010001100110000001000000010011101001110101001010100000010100100101111000111110100100001100100100001111110110101010 .
bx000000000000000000000000000000011111111111111111111111111111101000000000000000000000000000001110111111111111111111111111111111100000000000000000000000000010001100000000000000000000000001100110111111111111111111111111000101001111111111111111111111010001001011111111111111111101111110000000111111111111111111011111000000001111111111111111111000000000000011111111111111111110100000000000 1
bx000000000000000000001001010100100000000000000000001000011001010100000000000000000010000110011001000000000000000000100001100110000000000000000000001000011001010000000000000000000010000110010100000000000000000000100001100100100000000000000000001000010111000000000000000000000000100000100000000000000000000000000100000000001111111111111111111111000000000011111111111111111111000000000000 0
b111111111111 /
1%
#340000
0%
#350000
b1111111111111 /
bx00001100100100101010110111110001000000110010101000011001110001100001010111110101111000011000111100101111000100111101110011100100000111000100101000010101000110011101000011010100001000110010001111100011111001011110101010110110111111011011110101111001010011101111111000111101011011101010010011111111001111010001100110000001000000010011101001110101001010100000010100100101111000111110100100001100100100001111110110101010 .
bx00000000000000000000000000000001111111111111111111111111111111100000000000000000000000000000011000000000000000000000000000001110000000000000000000000000000000100000000000000000000000000010001111111111111111111111111110011010111111111111111111111110000111011111111111111111111000000000001011111111111111111101111110000000111111111111111111011111000000001111111111111111111000000000000011111111111111111110100000000000 1
bx00000000000000000000100101010010000000000000000000100001100101100000000000000000001000011001100100000000000000000010000110011001000000000000000000100001100101000000000000000000001000011001010000000000000000000010000110010110000000000000000000100001100010000000000000000000000010100010100000000000000000000000100000100000000000000000000000000100000000001111111111111111111111000000000011111111111111111111000000000000 0
1%
#360000
0%
#370000
bx0000110010010011001011011111000000000011001010010001100111000111000101011111011111100001100011100010111100010111110111001110001100011100010100100001010100011000110100001110010000100011000111011110001111000101111010101110000111111101011111010111101010100100111111011011110101111001010011101111111000111101011011101010010011111111001111010001100110000001000000010011101001110101001010100000010100100101111000111110100100001100100100001111110110101010 .
bx0000000000000000000000000000000100000000000000000000000000000000000000000000000000000000000000100000000000000000000000000000011011111111111111111111111111110010000000000000000000000000000000101111111111111111111111111101110111111111111111111111111010100011111111111111111111100000010100111111111111111111111000000000001011111111111111111101111110000000111111111111111111011111000000001111111111111111111000000000000011111111111111111110100000000000 1
bx0000000000000000000010010101001000000000000000000010000110010111000000000000000000100001100110010000000000000000001000011001100100000000000000000010000110010100000000000000000000100001100101000000000000000000001000011001011100000000000000000010000110010000000000000000000000001011001010000000000000000000000010100010100000000000000000000000100000100000000000000000000000000100000000001111111111111111111111000000000011111111111111111111000000000000 0
b11111111111111 /
1%
#380000
0%
#390000
b111111111111111 /
bx000011001001001101101101111011110000001100101001100110011100011000010101111110001110000110001101001011110001100111011100111000100001110001001110000101010001100111010000111011000010001100011100111000111011010111101010111001111111110101011101011110101100111111111101011111010111101010100100111111011011110101111001010011101111111000111101011011101010010011111111001111010001100110000001000000010011101001110101001010100000010100100101111000111110100100001100100100001111110110101010 .
bx000000000000000000000000000000011111111111111111111111111111111100000000000000000000000000000000000000000000000000000000000000101111111111111111111111111111101011111111111111111111111111110010111111111111111111111111111111101111111111111111111111101110011011111111111111111110000001111111111111111111111111100000010100111111111111111111111000000000001011111111111111111101111110000000111111111111111111011111000000001111111111111111111000000000000011111111111111111110100000000000 1
bx000000000000000000001001010100100000000000000000001000011001011100000000000000000010000110011001000000000000000000100001100110010000000000000000001000011001010100000000000000000010000110010100000000000000000000100001100110000000000000000000001000011001001100000000000000000000101110100111000000000000000000001011001010000000000000000000000010100010100000000000000000000000100000100000000000000000000000000100000000001111111111111111111111000000000011111111111111111111000000000000 0
1%
#400000
0%
#410000
bx00001100100100111000110111101110000000110010100101011001110001110001010111111001011000011000110000101111000110101101110011100001000111000100110000010101000110101101000011101000001000110001110111100011101011011110101011101000111111010100110101111010110101011111110101011101011110101100111111111101011111010111101010100100111111011011110101111001010011101111111000111101011011101010010011111111001111010001100110000001000000010011101001110101001010100000010100100101111000111110100100001100100100001111110110101010 .
bx00000000000000000000000000000001111111111111111111111111111111111111111111111111111111111111111100000000000000000000000000000000111111111111111111111111111111101111111111111111111111111111101000000000000000000000000000001110111111111111111111111111000001111111111111111111111000001001011011111111111111111110000001111111111111111111111111100000010100111111111111111111111000000000001011111111111111111101111110000000111111111111111111011111000000001111111111111111111000000000000011111111111111111110100000000000 1
bx00000000000000000000100101010010000000000000000000100001100110000000000000000000001000011001100100000000000000000010000110011001000000000000000000100001100101100000000000000000001000011001010100000000000000000010000110011001000000000000000000100001100101010000000000000000000010111110011100000000000000000000101110100111000000000000000000001011001010000000000000000000000010100010100000000000000000000000100000100000000000000000000000000100000000001111111111111111111111000000000011111111111111111111000000000000 0
b1111111111111111 /
1%
#420000
0%
#430000
b1100100100111001110111101101 "
b1100100100111001110111101101 ,
b100101010010 #
b100101010010 -
1!
b11111111111111111 /
b110010010011100111011110110100000011001010010011100111001000000101011111100100100001100011010010111100011011010111001110000000011100010010110001010100011011110100001110011000100011000111101110001110110001111010101110011111111101010001010111101011010110111111010100110101111010110101011111110101011101011110101100111111111101011111010111101010100100111111011011110101111001010011101111111000111101011011101010010011111111001111010001100110000001000000010011101001110101001010100000010100100101111000111110100100001100100100001111110110101010 .
b111111111111111111111111111111111111111111111111111111111111111111111111111111111111111111111111100000000000000000000000000000000111111111111111111111111111111100000000000000000000000000000011011111111111111111111111100010111111111111111111111100000101000011111111111111111111000001001011011111111111111111110000001111111111111111111111111100000010100111111111111111111111000000000001011111111111111111101111110000000111111111111111111011111000000001111111111111111111000000000000011111111111111111110100000000000 1
b10010101001000000000000000000010000110011001000000000000000000100001100110100000000000000000001000011001100100000000000000000010000110010111000000000000000000100001100101100000000000000000001000011001100100000000000000000010000110010110000000000000000000001100000001110000000000000000000010111110011100000000000000000000101110100111000000000000000000001011001010000000000000000000000010100010100000000000000000000000100000100000000000000000000000000100000000001111111111111111111111000000000011111111111111111111000000000000 0
1%
#440000
0%
#450000
b11001010010010100111001001 "
b11001010010010100111001001 ,
b10000110011010 #
b10000110011010 -
b1100101001001010011100100100010101111110010000000110001110001011110001101100011100111000010001110001001011100101010001101011010000111001010010001100011111111000111011001111101010111001101111110101000001011110101101011111111101010001010111101011010110111111010100110101111010110101011111110101011101011110101100111111111101011111010111101010100100111111011011110101111001010011101111111000111101011011101010010011111111001111010001100110000001000000010011101001110101001010100000010100100101111000111110100100001100100100001111110110101010 .
b1111111111111111111111111111111111111111111111111111111111111111111111111111111111111111111111111111111111111111111111111111111100000000000000000000000000000000000000000000000000000000000000101111111111111111111111110001111111111111111111111110000010100111111111111111111111100000101000011111111111111111111000001001011011111111111111111110000001111111111111111111111111100000010100111111111111111111111000000000001011111111111111111101111110000000111111111111111111011111000000001111111111111111111000000000000011111111111111111110100000000000 1
b1000011001101000000000000000000010000110011011000000000000000000100001100110100000000000000000001000011001011100000000000000000010000110010111000000000000000000100001100110010000000000000000001000011001011100000000000000000000110000010111000000000000000000001100000001110000000000000000000010111110011100000000000000000000101110100111000000000000000000001011001010000000000000000000000010100010100000000000000000000000100000100000000000000000000000000100000000001111111111111111111111000000000011111111111111111111000000000000 0
1%
#460000
0%
#470000
b10101111110001111000110001111 "
b10101111110001111000110001111 ,
b10000110011100 #
b10000110011100 -
b1010111111000111100011000111100101111000110101111110011100010000111000100101101010101000110111101000011100101101000110001111011100011101101001110101011100101111111010011111101111010110110001111110101000001011110101101011111111101010001010111101011010110111111010100110101111010110101011111110101011101011110101100111111111101011111010111101010100100111111011011110101111001010011101111111000111101011011101010010011111111001111010001100110000001000000010011101001110101001010100000010100100101111000111110100100001100100100001111110110101010 .
b1111111111111111111111111111111111111111111111111111111111111111111111111111111111111111111111111111111111111111111111111111111100000000000000000000000000000000111111111111111111111111001000111111111111111111111000001010101011111111111111111110000010100111111111111111111111100000101000011111111111111111111000001001011011111111111111111110000001111111111111111111111111100000010100111111111111111111111000000000001011111111111111111101111110000000111111111111111111011111000000001111111111111111111000000000000011111111111111111110100000000000 1
b1000011001110000000000000000000010000110011011000000000000000000100001100110000000000000000000001000011001011100000000000000000010000110011001000000000000000000100001100110000000000000000000000011000001111100000000000000000000110000010111000000000000000000001100000001110000000000000000000010111110011100000000000000000000101110100111000000000000000000001011001010000000000000000000000010100010100000000000000000000000100000100000000000000000000000000100000000001111111111111111111111000000000011111111111111111111000000000000 0
1%
#480000
0%
#490000
b101111000110101110110011100011 "
b101111000110101110110011100011 ,
b1111111111111111111111111111111111111111111111111111111111111111111111111111111111111111111111111111111111111111111111111111111111111111111111111111111100100101111111111111111111100000101010111111111111111111111000001010101011111111111111111110000010100111111111111111111111100000101000011111111111111111111000001001011011111111111111111110000001111111111111111111111111100000010100111111111111111111111000000000001011111111111111111101111110000000111111111111111111011111000000001111111111111111111000000000000011111111111111111110100000000000 1
b1000011001110000000000000000000010000110011001000000000000000000100001100110000000000000000000001000011001100100000000000000000010000110011001000000000000000000001100001000110000000000000000000011000001111100000000000000000000110000010111000000000000000000001100000001110000000000000000000010111110011100000000000000000000101110100111000000000000000000001011001010000000000000000000000010100010100000000000000000000000100000100000000000000000000000000100000000001111111111111111111111000000000011111111111111111111000000000000 0
b10111100011010111011001110001100011100010010110011010100011100110100001110010101100011000111111110001110110101011010101110010011111101001111100111101011011001111111010011111101111010110110001111110101000001011110101101011111111101010001010111101011010110111111010100110101111010110101011111110101011101011110101100111111111101011111010111101010100100111111011011110101111001010011101111111000111101011011101010010011111111001111010001100110000001000000010011101001110101001010100000010100100101111000111110100100001100100100001111110110101010 .
1%
#500000
0%
#510000
b11100010010110010010100011101 "
b11100010010110010010100011101 ,
b10000110011010 #
b10000110011010 -
b1110001001011001001010001110111010000111001010100001100100000111000111011010100101010111001011111110100111101111110101101101011111101001111100111101011011001111111010011111101111010110110001111110101000001011110101101011111111101010001010111101011010110111111010100110101111010110101011111110101011101011110101100111111111101011111010111101010100100111111011011110101111001010011101111111000111101011011101010010011111111001111010001100110000001000000010011101001110101001010100000010100100101111000111110100100001100100100001111110110101010 .
b1111111111111111111111111111111111111111111111111111111111111111111111111111111111111111111111111111111111111111111111110010011011111111111111111110000010101011111111111111111111100000101010111111111111111111111000001010101011111111111111111110000010100111111111111111111111100000101000011111111111111111111000001001011011111111111111111110000001111111111111111111111111100000010100111111111111111111111000000000001011111111111111111101111110000000111111111111111111011111000000001111111111111111111000000000000011111111111111111110100000000000 1
b1000011001101000000000000000000010000110011001000000000000000000100001100110100000000000000000001000011001101000000000000000000000110000100101000000000000000000001100001000110000000000000000000011000001111100000000000000000000110000010111000000000000000000001100000001110000000000000000000010111110011100000000000000000000101110100111000000000000000000001011001010000000000000000000000010100010100000000000000000000000100000100000000000000000000000000100000000001111111111111111111111000000000011111111111111111111000000000000 0
1%
#520000
0%
#530000
b11010000111001010011001100100001 "
b11010000111001010011001100100001 ,
b1111111111111111111111111111111111111111111111111111111111111111111111111111111111111111001001101111111111111111111000001010101111111111111111111110000010101011111111111111111111100000101010111111111111111111111000001010101011111111111111111110000010100111111111111111111111100000101000011111111111111111111000001001011011111111111111111110000001111111111111111111111111100000010100111111111111111111111000000000001011111111111111111101111110000000111111111111111111011111000000001111111111111111111000000000000011111111111111111110100000000000 1
b1000011001101000000000000000000010000110011011000000000000000000100001100110110000000000000000000011000010011000000000000000000000110000100101000000000000000000001100001000110000000000000000000011000001111100000000000000000000110000010111000000000000000000001100000001110000000000000000000010111110011100000000000000000000101110100111000000000000000000001011001010000000000000000000000010100010100000000000000000000000100000100000000000000000000000000100000000001111111111111111111111000000000011111111111111111111000000000000 0
b1101000011100101001100110010000111100011101101010000101011100110111111010011110110111010110110111111110100111101111110101101101011111101001111100111101011011001111111010011111101111010110110001111110101000001011110101101011111111101010001010111101011010110111111010100110101111010110101011111110101011101011110101100111111111101011111010111101010100100111111011011110101111001010011101111111000111101011011101010010011111111001111010001100110000001000000010011101001110101001010100000010100100101111000111110100100001100100100001111110110101010 .
1%
#540000
0%
#550000
b11100011101101001111101011100111 "
b11100011101101001111101011100111 ,
b10000110011100 #
b10000110011100 -
b1110001110110100111110101110011111111101001111011001101011011100111111010011110110111010110110111111110100111101111110101101101011111101001111100111101011011001111111010011111101111010110110001111110101000001011110101101011111111101010001010111101011010110111111010100110101111010110101011111110101011101011110101100111111111101011111010111101010100100111111011011110101111001010011101111111000111101011011101010010011111111001111010001100110000001000000010011101001110101001010100000010100100101111000111110100100001100100100001111110110101010 .
b1111111111111111111111111111111111111111111111111111111100100110111111111111111111100000101010111111111111111111111000001010101111111111111111111110000010101011111111111111111111100000101010111111111111111111111000001010101011111111111111111110000010100111111111111111111111100000101000011111111111111111111000001001011011111111111111111110000001111111111111111111111111100000010100111111111111111111111000000000001011111111111111111101111110000000111111111111111111011111000000001111111111111111111000000000000011111111111111111110100000000000 1
b1000011001110000000000000000000010000110011100000000000000000000001100001001110000000000000000000011000010011000000000000000000000110000100101000000000000000000001100001000110000000000000000000011000001111100000000000000000000110000010111000000000000000000001100000001110000000000000000000010111110011100000000000000000000101110100111000000000000000000001011001010000000000000000000000010100010100000000000000000000000100000100000000000000000000000000100000000001111111111111111111111000000000011111111111111111111000000000000 0
1%
#560000
0%
#570000
b11111101001111011000101011011101 "
b11111101001111011000101011011101 ,
b10000110011101 #
b10000110011101 -
b1111110100111101100010101101110111111101001111011001101011011100111111010011110110111010110110111111110100111101111110101101101011111101001111100111101011011001111111010011111101111010110110001111110101000001011110101101011111111101010001010111101011010110111111010100110101111010110101011111110101011101011110101100111111111101011111010111101010100100111111011011110101111001010011101111111000111101011011101010010011111111001111010001100110000001000000010011101001110101001010100000010100100101111000111110100100001100100100001111110110101010 .
b1111111111111111111111110010011011111111111111111110000010101011111111111111111111100000101010111111111111111111111000001010101111111111111111111110000010101011111111111111111111100000101010111111111111111111111000001010101011111111111111111110000010100111111111111111111111100000101000011111111111111111111000001001011011111111111111111110000001111111111111111111111111100000010100111111111111111111111000000000001011111111111111111101111110000000111111111111111111011111000000001111111111111111111000000000000011111111111111111110100000000000 1
b1000011001110100000000000000000000110000101000000000000000000000001100001001110000000000000000000011000010011000000000000000000000110000100101000000000000000000001100001000110000000000000000000011000001111100000000000000000000110000010111000000000000000000001100000001110000000000000000000010111110011100000000000000000000101110100111000000000000000000001011001010000000000000000000000010100010100000000000000000000000100000100000000000000000000000000100000000001111111111111111111111000000000011111111111111111111000000000000 0
1%
#580000
0%
