computing_cascade/AC_PH/postprocess/dec_to_polar_fsm/dec_to_polar_fsm.sv

module dec_to_polar_fsm
#(
    parameter WIDTH_XY   = 32,
	parameter WIDTH_PH   = 32,
	parameter NSTAGES    = 16
)
(
	input                                     clk, 
	input                                     rstn, 

	input  logic signed [WIDTH_PH-1:0]        cordic_angle,
	output logic        [$clog2(NSTAGES)-1:0] cnt,
	
	input                                     i_vld,
	input  logic signed [WIDTH_XY - 1:0]      i_x, 
	input  logic signed [WIDTH_XY - 1:0]      i_y,

	output logic                              o_vld,
	output logic signed [WIDTH_XY - 1:0]      o_mag,
	output logic signed [WIDTH_PH - 1:0]      o_phase,
	output logic                              ready
	);

	enum logic[1:0]
  	{
    	IDLE   = 2'b00,
    	BUSY   = 2'b01,
    	OUTPUT = 2'b10
	}
	state, new_state;
	always_ff @ (posedge clk)
    if (!rstn)
    	state <= IDLE;
    else
    	state <= new_state;

	// Логика переходов
	logic en;
	assign en = cnt == (NSTAGES - 1);
	always_ff @(posedge clk) begin
		if (!rstn)    cnt <= 'b0;
		else if (state == BUSY) begin
			if (en) cnt <= 'b0;
			else    cnt <= cnt + 'b1;
		end
		else        cnt <= 'b0;
	end

	always_comb
	begin
		new_state = state;
		case (state)
		IDLE:   if (i_vld) new_state = BUSY;
		BUSY:   if (en   ) new_state = OUTPUT;
		OUTPUT: if (i_vld) new_state = BUSY;
				else       new_state = IDLE;
		default:           new_state = state;
		endcase
	end

	logic signed [WIDTH_XY-1:0] xs;
	logic signed [WIDTH_XY-1:0] ys;
	logic signed [WIDTH_PH-1:0] phs;
    
	logic signed [WIDTH_XY-1:0] ys_abs;
	logic sig;
	assign sig = ys[WIDTH_XY-1];
	assign ys_abs = sig ? -ys : ys;

	always_ff @(posedge clk) begin
		// Предварительный поворот в сектор -45 45
		if (i_vld & ready) begin
			case ({i_y[WIDTH_XY-1], i_x[WIDTH_XY-1]} )
				2'b00:begin
					xs  <= i_x + i_y;
					ys  <= i_y - i_x;
					// Угол в градусах
					// 1  - знак
					// 9  - целая часть
					// 22 - дробная часть
					phs <= 32'h0b40_0000;    // 45 градусов
				end
				2'b01:begin
					xs  <= i_y - i_x;
					ys  <= -i_x - i_y;
					phs <= 32'h21c0_0000;    //135
				end
				2'b11:begin
					xs  <= -i_y - i_x;
					ys  <= i_x - i_y;
					phs <= 32'h3840_0000;    //225 - 360
				end
				2'b10:begin
					xs  <= i_x - i_y;
					ys  <= i_x + i_y;
					phs <= 32'h4ec0_0000;    //315 - 360
				end
				default: begin
					xs  <= i_x + i_y;
					ys  <= i_y - i_x;
					phs <= 32'h0b40_0000;
				end
			endcase
		end
		else if (state == BUSY) begin
			if (sig) begin
				xs <= xs + (ys_abs >> (cnt + 'b1));
				ys <= ys + (xs >> (cnt + 'b1));
				phs <= phs - cordic_angle;
			end 
			else begin
				xs <= xs + (ys >> (cnt + 'b1));
				ys <= ys - (xs >> (cnt + 'b1));
				phs <= phs + cordic_angle;
			end
		end
	end 

	assign o_mag   = xs;
    assign o_phase = phs;
	assign o_vld   = state == OUTPUT;
	assign ready   = state != BUSY;

endmodule

postprocess/RAM_angle/RAM_angle.sv
module RAM_angle
#(
    parameter WIDTH = 32,
    parameter DEPTH = 18
)
(
    input                         clk,
    input                         write_enable,
    input  [$clog2 (DEPTH) - 1:0] address,
    input  [WIDTH-1:0]            data_in,
    output [WIDTH-1:0]            data_out
);

  logic [WIDTH-1:0] w_re [0:DEPTH-1];
  initial $readmemh(".\\weigths\\angle.txt", w_re);

  always @(posedge clk)
    if (write_enable)
      w_re[address] <= data_in;

  assign data_out = w_re[address];

endmodule

computing_cascade/AC_PH/postprocess/dec_to_polar_fsm/testbench.sv
`timescale 1ns/1ps
`include ".\RAM_angle\RAM_angle.sv"

module test;
    // Подключение

    logic                clk;
    logic                arstn;
    logic                enable;

    logic signed	[31:0] i_xval, i_yval;
    logic i_vld;

    logic signed	[31:0] o_mag;
    logic signed	[31:0] o_phase;
    logic o_vld;
    logic ready;

    localparam NSTAGES = 4;
    logic [$clog2(NSTAGES)-1:0] cnt;
	logic signed [31:0] cordic_angle;
    RAM_angle
    #(
        .WIDTH(32),
        .DEPTH(NSTAGES)
    ) ram1 (
        .clk(clk),
        .address (cnt),
        .data_out (cordic_angle)
    );

    dec_to_polar_fsm
    #(
        .NSTAGES(NSTAGES)
    ) tp (
        .clk           (clk),
        .rstn         (arstn),

        .cordic_angle (cordic_angle),
        .cnt (cnt),

        .i_vld (i_vld),
        .i_x (i_xval),
        .i_y (i_yval),

        .o_mag (o_mag),
        .o_phase (o_phase),
        .o_vld (o_vld),
        .ready (ready)
    );

    initial begin
        $dumpfile("dec_to_polar_fsm.vcd");
        $dumpvars;
    end

    // Генерация clk
    parameter CLK_PERIOD = 20; // 50 МГц
    initial begin
        clk <= 0;
        forever begin
            #(CLK_PERIOD / 2); clk <= ~clk;
        end
    end

    //Генерация rst
    initial begin
        arstn <= 0;
        @(posedge clk);
        @(posedge clk);
        @(posedge clk);
        arstn <= 1;
    end

    // Генерация входных сигналов
    initial begin
        i_vld <= 'b0;
        wait(arstn);
        @(posedge clk);
    //---------------------------------------------------------------------------------------------
        @(posedge clk);
        i_vld <= 'b1;
        i_xval <= 32'd1 << 'd10;
        i_yval <= 32'd1 << 'd10;
        $display("%d", 32'd1);
        $display("%d", 32'd1);

        @(posedge o_vld);
        i_vld <= 'b1;
        i_xval <= 32'd5 << 'd10;
        i_yval <= 32'd1 << 'd10;
        $display("%d", 32'd5);
        $display("%d", 32'd1);
        @(posedge o_vld);
        i_vld <= 'b1;
        i_xval <= 32'd1 << 'd10;
        i_yval <= 32'd5 << 'd10;
        $display("%d", 32'd1);
        $display("%d", 32'd5);

        @(posedge o_vld);
        i_vld <= 'b1;
        i_xval <= -32'd5 << 'd10;
        i_yval <= 32'd1 << 'd10;
        $display("-%d", 32'd5);
        $display("%d", 32'd1);
        @(posedge o_vld);
        i_vld <= 'b1;
        i_xval <= -32'd1 << 'd10;
        i_yval <= 32'd5 << 'd10;
        $display("-%d", 32'd1);
        $display("%d", 32'd5);

        @(posedge o_vld);
        i_vld <= 'b1;
        i_xval <= -32'd5 << 'd10;
        i_yval <= -32'd1 << 'd10;
        $display("-%d", 32'd5);
        $display("-%d", 32'd1);
        @(posedge o_vld);
        i_vld <= 'b1;
        i_xval <= -32'd1 << 'd10;
        i_yval <= -32'd5 << 'd10;
        $display("-%d", 32'd1);
        $display("-%d", 32'd5);

        @(posedge o_vld);
        i_vld <= 'b1;
        i_xval <= 32'd5 << 'd10;
        i_yval <= -32'd1 << 'd10;
        $display("%d", 32'd5);
        $display("-%d", 32'd1);
        @(posedge o_vld);
        i_vld <= 'b1;
        i_xval <= 32'd1 << 'd10;
        i_yval <= -32'd5 << 'd10;
        $display("%d", 32'd1);
        $display("-%d", 32'd5);
    //---------------------------------------------------------------------------------------------
        repeat(18) begin
            @(posedge clk);
        end
        @(posedge clk);
        @(posedge clk);
        @(posedge clk);
        $finish;
    end
endmodule

computing_cascade/AC_PH/postprocess/dec_to_polar_fsm.vcd
$date
	Fri May 16 13:09:37 2025
$end
$version
	Icarus Verilog
$end
$timescale
	1ps
$end
$scope module test $end
$var wire 1 ! ready $end
$var wire 1 " o_vld $end
$var wire 32 # o_phase [31:0] $end
$var wire 32 $ o_mag [31:0] $end
$var wire 32 % cordic_angle [31:0] $end
$var wire 2 & cnt [1:0] $end
$var reg 1 ' arstn $end
$var reg 1 ( clk $end
$var reg 1 ) i_vld $end
$var reg 32 * i_xval [31:0] $end
$var reg 32 + i_yval [31:0] $end
$scope module ram1 $end
$var wire 1 ( clk $end
$var wire 32 , data_in [31:0] $end
$var wire 32 - data_out [31:0] $end
$var wire 1 . write_enable $end
$var wire 2 / address [1:0] $end
$upscope $end
$scope module tp $end
$var wire 1 ( clk $end
$var wire 32 0 cordic_angle [31:0] $end
$var wire 1 ) i_vld $end
$var wire 32 1 i_x [31:0] $end
$var wire 32 2 i_y [31:0] $end
$var wire 32 3 o_mag [31:0] $end
$var wire 32 4 o_phase [31:0] $end
$var wire 1 ' rstn $end
$var wire 32 5 ys_abs [31:0] $end
$var wire 1 6 sig $end
$var wire 1 ! ready $end
$var wire 1 " o_vld $end
$var wire 1 7 en $end
$var reg 2 8 cnt [1:0] $end
$var reg 2 9 new_state [1:0] $end
$var reg 32 : phs [31:0] $end
$var reg 2 ; state [1:0] $end
$var reg 32 < xs [31:0] $end
$var reg 32 = ys [31:0] $end
$upscope $end
$upscope $end
$enddefinitions $end
#0
$dumpvars
bx =
bx <
bx ;
bx :
bx 9
bx 8
x7
x6
bx 5
bx 4
bx 3
bx 2
bx 1
bx 0
bx /
z.
bx -
bz ,
bx +
bx *
0)
0(
0'
bx &
bx %
bx $
bx #
x"
x!
$end
#10000
b0 9
0"
1!
b0 ;
07
b110101001000010100111001100 %
b110101001000010100111001100 -
b110101001000010100111001100 0
b0 &
b0 /
b0 8
1(
#20000
0(
#30000
1(
#40000
0(
#50000
1'
1(
#60000
0(
#70000
1(
#80000
0(
#90000
b1 9
b10000000000 +
b10000000000 2
b10000000000 *
b10000000000 1
1)
1(
#100000
0(
#110000
06
b0 5
b1011010000000000000000000000 #
b1011010000000000000000000000 4
b1011010000000000000000000000 :
b0 =
b100000000000 $
b100000000000 3
b100000000000 <
0!
b1 ;
1(
#120000
0(
#130000
16
b10000000000 5
b11100000100101000111010000 %
b11100000100101000111010000 -
b11100000100101000111010000 0
b1 &
b1 /
b1 8
b10001111001000010100111001100 #
b10001111001000010100111001100 4
b10001111001000010100111001100 :
b11111111111111111111110000000000 =
1(
#140000
0(
#150000
b1000000000 5
b1110011000011101011111111100 #
b1110011000011101011111111100 4
b1110011000011101011111111100 :
b11111111111111111111111000000000 =
b100100000000 $
b100100000000 3
b100100000000 <
b1110010000000000001000100 %
b1110010000000000001000100 -
b1110010000000000001000100 0
b10 &
b10 /
b10 8
1(
#160000
0(
#170000
b10 9
b11100000 5
17
b111001001110001010101001 %
b111001001110001010101001 -
b111001001110001010101001 0
b11 &
b11 /
b11 8
b1100100110011101011110111000 #
b1100100110011101011110111000 4
b1100100110011101011110111000 :
b11111111111111111111111100100000 =
b100101000000 $
b100101000000 3
b100101000000 <
1(
#180000
0(
#190000
b1010000000000 *
b1010000000000 1
b1001100 5
b1 9
b1011101101001111010100001111 #
b1011101101001111010100001111 4
b1011101101001111010100001111 :
b11111111111111111111111110110100 =
b100101001110 $
b100101001110 3
b100101001110 <
07
b110101001000010100111001100 %
b110101001000010100111001100 -
b110101001000010100111001100 0
b0 &
b0 /
b0 8
1"
1!
b10 ;
1(
#200000
0(
#210000
b1000000000000 5
0"
0!
b1 ;
b1011010000000000000000000000 #
b1011010000000000000000000000 4
b1011010000000000000000000000 :
b11111111111111111111000000000000 =
b1100000000000 $
b1100000000000 3
b1100000000000 <
1(
#220000
0(
#230000
b10000000000 5
b100100110111101011000110100 #
b100100110111101011000110100 4
b100100110111101011000110100 :
b11111111111111111111110000000000 =
b10000000000000 $
b10000000000000 3
b10000000000000 <
b11100000100101000111010000 %
b11100000100101000111010000 -
b11100000100101000111010000 0
b1 &
b1 /
b1 8
1(
#240000
0(
#250000
06
b10000000000 5
b1110010000000000001000100 %
b1110010000000000001000100 -
b1110010000000000001000100 0
b10 &
b10 /
b10 8
b1000110011000010001100100 #
b1000110011000010001100100 4
b1000110011000010001100100 :
b10000000000 =
b10000100000000 $
b10000100000000 3
b10000100000000 <
1(
#260000
0(
#270000
16
b100000 5
b10 9
b10111000011000010010101000 #
b10111000011000010010101000 4
b10111000011000010010101000 :
b11111111111111111111111111100000 =
b10000110000000 $
b10000110000000 3
b10000110000000 <
17
b111001001110001010101001 %
b111001001110001010101001 -
b111001001110001010101001 0
b11 &
b11 /
b11 8
1(
#280000
0(
#290000
b1010000000000 +
b1010000000000 2
b10000000000 *
b10000000000 1
b1 9
06
b111111000 5
1"
1!
b10 ;
07
b110101001000010100111001100 %
b110101001000010100111001100 -
b110101001000010100111001100 0
b0 &
b0 /
b0 8
b1111111001010000111111111 #
b1111111001010000111111111 4
b1111111001010000111111111 :
b111111000 =
b10000110000010 $
b10000110000010 3
b10000110000010 <
1(
#300000
0(
#310000
b1000000000000 5
b1011010000000000000000000000 #
b1011010000000000000000000000 4
b1011010000000000000000000000 :
b1000000000000 =
b1100000000000 $
b1100000000000 3
b1100000000000 <
0"
0!
b1 ;
1(
#320000
0(
#330000
b10000000000 5
b11100000100101000111010000 %
b11100000100101000111010000 -
b11100000100101000111010000 0
b1 &
b1 /
b1 8
b10001111001000010100111001100 #
b10001111001000010100111001100 4
b10001111001000010100111001100 :
b10000000000 =
b10000000000000 $
b10000000000000 3
b10000000000000 <
1(
#340000
0(
#350000
16
b10000000000 5
b10101011001100111101110011100 #
b10101011001100111101110011100 4
b10101011001100111101110011100 :
b11111111111111111111110000000000 =
b10000100000000 $
b10000100000000 3
b10000100000000 <
b1110010000000000001000100 %
b1110010000000000001000100 -
b1110010000000000001000100 0
b10 &
b10 /
b10 8
1(
#360000
0(
#370000
b10 9
06
b100000 5
17
b111001001110001010101001 %
b111001001110001010101001 -
b111001001110001010101001 0
b11 &
b11 /
b11 8
b10011100111100111101101011000 #
b10011100111100111101101011000 4
b10011100111100111101101011000 :
b100000 =
b10000110000000 $
b10000110000000 3
b10000110000000 <
1(
#380000
0(
#390000
b10000000000 +
b10000000000 2
b11111111111111111110110000000000 *
b11111111111111111110110000000000 1
16
b111111000 5
b1 9
b10100100000110101111000000001 #
b10100100000110101111000000001 4
b10100100000110101111000000001 :
b11111111111111111111111000001000 =
b10000110000010 $
b10000110000010 3
b10000110000010 <
07
b110101001000010100111001100 %
b110101001000010100111001100 -
b110101001000010100111001100 0
b0 &
b0 /
b0 8
1"
1!
b10 ;
1(
#400000
0(
#410000
06
b1000000000000 5
0"
0!
b1 ;
b100001110000000000000000000000 #
b100001110000000000000000000000 4
b100001110000000000000000000000 :
b1000000000000 =
b1100000000000 $
b1100000000000 3
b1100000000000 <
1(
#420000
0(
#430000
b10000000000 5
b101000011001000010100111001100 #
b101000011001000010100111001100 4
b101000011001000010100111001100 :
b10000000000 =
b10000000000000 $
b10000000000000 3
b10000000000000 <
b11100000100101000111010000 %
b11100000100101000111010000 -
b11100000100101000111010000 0
b1 &
b1 /
b1 8
1(
#440000
0(
#450000
16
b10000000000 5
b1110010000000000001000100 %
b1110010000000000001000100 -
b1110010000000000001000100 0
b10 &
b10 /
b10 8
b101011111001100111101110011100 #
b101011111001100111101110011100 4
b101011111001100111101110011100 :
b11111111111111111111110000000000 =
b10000100000000 $
b10000100000000 3
b10000100000000 <
1(
#460000
0(
#470000
06
b100000 5
b10 9
b101010000111100111101101011000 #
b101010000111100111101101011000 4
b101010000111100111101101011000 :
b100000 =
b10000110000000 $
b10000110000000 3
b10000110000000 <
17
b111001001110001010101001 %
b111001001110001010101001 -
b111001001110001010101001 0
b11 &
b11 /
b11 8
1(
#480000
0(
#490000
b1010000000000 +
b1010000000000 2
b11111111111111111111110000000000 *
b11111111111111111111110000000000 1
b1 9
16
b111111000 5
1"
1!
b10 ;
07
b110101001000010100111001100 %
b110101001000010100111001100 -
b110101001000010100111001100 0
b0 &
b0 /
b0 8
b101011000000110101111000000001 #
b101011000000110101111000000001 4
b101011000000110101111000000001 :
b11111111111111111111111000001000 =
b10000110000010 $
b10000110000010 3
b10000110000010 <
1(
#500000
0(
#510000
b1000000000000 5
b100001110000000000000000000000 #
b100001110000000000000000000000 4
b100001110000000000000000000000 :
b11111111111111111111000000000000 =
b1100000000000 $
b1100000000000 3
b1100000000000 <
0"
0!
b1 ;
1(
#520000
0(
#530000
b10000000000 5
b11100000100101000111010000 %
b11100000100101000111010000 -
b11100000100101000111010000 0
b1 &
b1 /
b1 8
b11011000110111101011000110100 #
b11011000110111101011000110100 4
b11011000110111101011000110100 :
b11111111111111111111110000000000 =
b10000000000000 $
b10000000000000 3
b10000000000000 <
1(
#540000
0(
#550000
06
b10000000000 5
b10111100110011000010001100100 #
b10111100110011000010001100100 4
b10111100110011000010001100100 :
b10000000000 =
b10000100000000 $
b10000100000000 3
b10000100000000 <
b1110010000000000001000100 %
b1110010000000000001000100 -
b1110010000000000001000100 0
b10 &
b10 /
b10 8
1(
#560000
0(
#570000
b10 9
16
b100000 5
17
b111001001110001010101001 %
b111001001110001010101001 -
b111001001110001010101001 0
b11 &
b11 /
b11 8
b11001011000011000010010101000 #
b11001011000011000010010101000 4
b11001011000011000010010101000 :
b11111111111111111111111111100000 =
b10000110000000 $
b10000110000000 3
b10000110000000 <
1(
#580000
0(
#590000
b11111111111111111111110000000000 +
b11111111111111111111110000000000 2
b11111111111111111110110000000000 *
b11111111111111111110110000000000 1
06
b111111000 5
b1 9
b11000011111001010000111111111 #
b11000011111001010000111111111 4
b11000011111001010000111111111 :
b111111000 =
b10000110000010 $
b10000110000010 3
b10000110000010 <
07
b110101001000010100111001100 %
b110101001000010100111001100 -
b110101001000010100111001100 0
b0 &
b0 /
b0 8
1"
1!
b10 ;
1(
#600000
0(
#610000
16
b1000000000000 5
0"
0!
b1 ;
b111000010000000000000000000000 #
b111000010000000000000000000000 4
b111000010000000000000000000000 :
b11111111111111111111000000000000 =
b1100000000000 $
b1100000000000 3
b1100000000000 <
1(
#620000
0(
#630000
b10000000000 5
b110001100110111101011000110100 #
b110001100110111101011000110100 4
b110001100110111101011000110100 :
b11111111111111111111110000000000 =
b10000000000000 $
b10000000000000 3
b10000000000000 <
b11100000100101000111010000 %
b11100000100101000111010000 -
b11100000100101000111010000 0
b1 &
b1 /
b1 8
1(
#640000
0(
#650000
06
b10000000000 5
b1110010000000000001000100 %
b1110010000000000001000100 -
b1110010000000000001000100 0
b10 &
b10 /
b10 8
b101110000110011000010001100100 #
b101110000110011000010001100100 4
b101110000110011000010001100100 :
b10000000000 =
b10000100000000 $
b10000100000000 3
b10000100000000 <
1(
#660000
0(
#670000
16
b100000 5
b10 9
b101111111000011000010010101000 #
b101111111000011000010010101000 4
b101111111000011000010010101000 :
b11111111111111111111111111100000 =
b10000110000000 $
b10000110000000 3
b10000110000000 <
17
b111001001110001010101001 %
b111001001110001010101001 -
b111001001110001010101001 0
b11 &
b11 /
b11 8
1(
#680000
0(
#690000
b11111111111111111110110000000000 +
b11111111111111111110110000000000 2
b11111111111111111111110000000000 *
b11111111111111111111110000000000 1
b1 9
06
b111111000 5
1"
1!
b10 ;
07
b110101001000010100111001100 %
b110101001000010100111001100 -
b110101001000010100111001100 0
b0 &
b0 /
b0 8
b101110111111001010000111111111 #
b101110111111001010000111111111 4
b101110111111001010000111111111 :
b111111000 =
b10000110000010 $
b10000110000010 3
b10000110000010 <
1(
#700000
0(
#710000
b1000000000000 5
b111000010000000000000000000000 #
b111000010000000000000000000000 4
b111000010000000000000000000000 :
b1000000000000 =
b1100000000000 $
b1100000000000 3
b1100000000000 <
0"
0!
b1 ;
1(
#720000
0(
#730000
b10000000000 5
b11100000100101000111010000 %
b11100000100101000111010000 -
b11100000100101000111010000 0
b1 &
b1 /
b1 8
b111110111001000010100111001100 #
b111110111001000010100111001100 4
b111110111001000010100111001100 :
b10000000000 =
b10000000000000 $
b10000000000000 3
b10000000000000 <
1(
#740000
0(
#750000
16
b10000000000 5
b1000010011001100111101110011100 #
b1000010011001100111101110011100 4
b1000010011001100111101110011100 :
b11111111111111111111110000000000 =
b10000100000000 $
b10000100000000 3
b10000100000000 <
b1110010000000000001000100 %
b1110010000000000001000100 -
b1110010000000000001000100 0
b10 &
b10 /
b10 8
1(
#760000
0(
#770000
b10 9
06
b100000 5
17
b111001001110001010101001 %
b111001001110001010101001 -
b111001001110001010101001 0
b11 &
b11 /
b11 8
b1000000100111100111101101011000 #
b1000000100111100111101101011000 4
b1000000100111100111101101011000 :
b100000 =
b10000110000000 $
b10000110000000 3
b10000110000000 <
1(
#780000
0(
#790000
b11111111111111111111110000000000 +
b11111111111111111111110000000000 2
b1010000000000 *
b1010000000000 1
16
b111111000 5
b1 9
b1000001100000110101111000000001 #
b1000001100000110101111000000001 4
b1000001100000110101111000000001 :
b11111111111111111111111000001000 =
b10000110000010 $
b10000110000010 3
b10000110000010 <
07
b110101001000010100111001100 %
b110101001000010100111001100 -
b110101001000010100111001100 0
b0 &
b0 /
b0 8
1"
1!
b10 ;
1(
#800000
0(
#810000
06
b1000000000000 5
0"
0!
b1 ;
b1001110110000000000000000000000 #
b1001110110000000000000000000000 4
b1001110110000000000000000000000 :
b1000000000000 =
b1100000000000 $
b1100000000000 3
b1100000000000 <
1(
#820000
0(
#830000
b10000000000 5
b1010101011001000010100111001100 #
b1010101011001000010100111001100 4
b1010101011001000010100111001100 :
b10000000000 =
b10000000000000 $
b10000000000000 3
b10000000000000 <
b11100000100101000111010000 %
b11100000100101000111010000 -
b11100000100101000111010000 0
b1 &
b1 /
b1 8
1(
#840000
0(
#850000
16
b10000000000 5
b1110010000000000001000100 %
b1110010000000000001000100 -
b1110010000000000001000100 0
b10 &
b10 /
b10 8
b1011000111001100111101110011100 #
b1011000111001100111101110011100 4
b1011000111001100111101110011100 :
b11111111111111111111110000000000 =
b10000100000000 $
b10000100000000 3
b10000100000000 <
1(
#860000
0(
#870000
06
b100000 5
b10 9
b1010111000111100111101101011000 #
b1010111000111100111101101011000 4
b1010111000111100111101101011000 :
b100000 =
b10000110000000 $
b10000110000000 3
b10000110000000 <
17
b111001001110001010101001 %
b111001001110001010101001 -
b111001001110001010101001 0
b11 &
b11 /
b11 8
1(
#880000
0(
#890000
b11111111111111111110110000000000 +
b11111111111111111110110000000000 2
b10000000000 *
b10000000000 1
b1 9
16
b111111000 5
1"
1!
b10 ;
07
b110101001000010100111001100 %
b110101001000010100111001100 -
b110101001000010100111001100 0
b0 &
b0 /
b0 8
b1011000000000110101111000000001 #
b1011000000000110101111000000001 4
b1011000000000110101111000000001 :
b11111111111111111111111000001000 =
b10000110000010 $
b10000110000010 3
b10000110000010 <
1(
#900000
0(
#910000
b1000000000000 5
b1001110110000000000000000000000 #
b1001110110000000000000000000000 4
b1001110110000000000000000000000 :
b11111111111111111111000000000000 =
b1100000000000 $
b1100000000000 3
b1100000000000 <
0"
0!
b1 ;
1(
#920000
0(
#930000
b10000000000 5
b11100000100101000111010000 %
b11100000100101000111010000 -
b11100000100101000111010000 0
b1 &
b1 /
b1 8
b1001000000110111101011000110100 #
b1001000000110111101011000110100 4
b1001000000110111101011000110100 :
b11111111111111111111110000000000 =
b10000000000000 $
b10000000000000 3
b10000000000000 <
1(
#940000
0(
#950000
06
b10000000000 5
b1000100100110011000010001100100 #
b1000100100110011000010001100100 4
b1000100100110011000010001100100 :
b10000000000 =
b10000100000000 $
b10000100000000 3
b10000100000000 <
b1110010000000000001000100 %
b1110010000000000001000100 -
b1110010000000000001000100 0
b10 &
b10 /
b10 8
1(
#960000
0(
#970000
b10 9
16
b100000 5
17
b111001001110001010101001 %
b111001001110001010101001 -
b111001001110001010101001 0
b11 &
b11 /
b11 8
b1000110011000011000010010101000 #
b1000110011000011000010010101000 4
b1000110011000011000010010101000 :
b11111111111111111111111111100000 =
b10000110000000 $
b10000110000000 3
b10000110000000 <
1(
#980000
0(
#990000
06
b111111000 5
b1 9
b1000101011111001010000111111111 #
b1000101011111001010000111111111 4
b1000101011111001010000111111111 :
b111111000 =
b10000110000010 $
b10000110000010 3
b10000110000010 <
07
b110101001000010100111001100 %
b110101001000010100111001100 -
b110101001000010100111001100 0
b0 &
b0 /
b0 8
1"
1!
b10 ;
1(
#1000000
0(
#1010000
16
b1000000000000 5
0"
0!
b1 ;
b1001110110000000000000000000000 #
b1001110110000000000000000000000 4
b1001110110000000000000000000000 :
b11111111111111111111000000000000 =
b1100000000000 $
b1100000000000 3
b1100000000000 <
1(
#1020000
0(
#1030000
b10000000000 5
b1001000000110111101011000110100 #
b1001000000110111101011000110100 4
b1001000000110111101011000110100 :
b11111111111111111111110000000000 =
b10000000000000 $
b10000000000000 3
b10000000000000 <
b11100000100101000111010000 %
b11100000100101000111010000 -
b11100000100101000111010000 0
b1 &
b1 /
b1 8
1(
#1040000
0(
#1050000
06
b10000000000 5
b1110010000000000001000100 %
b1110010000000000001000100 -
b1110010000000000001000100 0
b10 &
b10 /
b10 8
b1000100100110011000010001100100 #
b1000100100110011000010001100100 4
b1000100100110011000010001100100 :
b10000000000 =
b10000100000000 $
b10000100000000 3
b10000100000000 <
1(
#1060000
0(
#1070000
16
b100000 5
b10 9
b1000110011000011000010010101000 #
b1000110011000011000010010101000 4
b1000110011000011000010010101000 :
b11111111111111111111111111100000 =
b10000110000000 $
b10000110000000 3
b10000110000000 <
17
b111001001110001010101001 %
b111001001110001010101001 -
b111001001110001010101001 0
b11 &
b11 /
b11 8
1(
#1080000
0(
#1090000
b1 9
06
b111111000 5
1"
1!
b10 ;
07
b110101001000010100111001100 %
b110101001000010100111001100 -
b110101001000010100111001100 0
b0 &
b0 /
b0 8
b1000101011111001010000111111111 #
b1000101011111001010000111111111 4
b1000101011111001010000111111111 :
b111111000 =
b10000110000010 $
b10000110000010 3
b10000110000010 <
1(
#1100000
0(
#1110000
16
b1000000000000 5
b1001110110000000000000000000000 #
b1001110110000000000000000000000 4
b1001110110000000000000000000000 :
b11111111111111111111000000000000 =
b1100000000000 $
b1100000000000 3
b1100000000000 <
0"
0!
b1 ;
1(
#1120000
0(
#1130000
b10000000000 5
b11100000100101000111010000 %
b11100000100101000111010000 -
b11100000100101000111010000 0
b1 &
b1 /
b1 8
b1001000000110111101011000110100 #
b1001000000110111101011000110100 4
b1001000000110111101011000110100 :
b11111111111111111111110000000000 =
b10000000000000 $
b10000000000000 3
b10000000000000 <
1(
#1140000
0(
#1150000
06
b10000000000 5
b1000100100110011000010001100100 #
b1000100100110011000010001100100 4
b1000100100110011000010001100100 :
b10000000000 =
b10000100000000 $
b10000100000000 3
b10000100000000 <
b1110010000000000001000100 %
b1110010000000000001000100 -
b1110010000000000001000100 0
b10 &
b10 /
b10 8
1(
#1160000
0(
#1170000
b10 9
16
b100000 5
17
b111001001110001010101001 %
b111001001110001010101001 -
b111001001110001010101001 0
b11 &
b11 /
b11 8
b1000110011000011000010010101000 #
b1000110011000011000010010101000 4
b1000110011000011000010010101000 :
b11111111111111111111111111100000 =
b10000110000000 $
b10000110000000 3
b10000110000000 <
1(
#1180000
0(
#1190000
06
b111111000 5
b1 9
b1000101011111001010000111111111 #
b1000101011111001010000111111111 4
b1000101011111001010000111111111 :
b111111000 =
b10000110000010 $
b10000110000010 3
b10000110000010 <
07
b110101001000010100111001100 %
b110101001000010100111001100 -
b110101001000010100111001100 0
b0 &
b0 /
b0 8
1"
1!
b10 ;
1(
#1200000
0(
#1210000
16
b1000000000000 5
0"
0!
b1 ;
b1001110110000000000000000000000 #
b1001110110000000000000000000000 4
b1001110110000000000000000000000 :
b11111111111111111111000000000000 =
b1100000000000 $
b1100000000000 3
b1100000000000 <
1(
#1220000
0(
#1230000
b10000000000 5
b1001000000110111101011000110100 #
b1001000000110111101011000110100 4
b1001000000110111101011000110100 :
b11111111111111111111110000000000 =
b10000000000000 $
b10000000000000 3
b10000000000000 <
b11100000100101000111010000 %
b11100000100101000111010000 -
b11100000100101000111010000 0
b1 &
b1 /
b1 8
1(
#1240000
0(
#1250000
06
b10000000000 5
b1110010000000000001000100 %
b1110010000000000001000100 -
b1110010000000000001000100 0
b10 &
b10 /
b10 8
b1000100100110011000010001100100 #
b1000100100110011000010001100100 4
b1000100100110011000010001100100 :
b10000000000 =
b10000100000000 $
b10000100000000 3
b10000100000000 <
1(
#1260000
0(
#1270000
16
b100000 5
b10 9
b1000110011000011000010010101000 #
b1000110011000011000010010101000 4
b1000110011000011000010010101000 :
b11111111111111111111111111100000 =
b10000110000000 $
b10000110000000 3
b10000110000000 <
17
b111001001110001010101001 %
b111001001110001010101001 -
b111001001110001010101001 0
b11 &
b11 /
b11 8
1(
#1280000
0(
#1290000
b1 9
06
b111111000 5
1"
1!
b10 ;
07
b110101001000010100111001100 %
b110101001000010100111001100 -
b110101001000010100111001100 0
b0 &
b0 /
b0 8
b1000101011111001010000111111111 #
b1000101011111001010000111111111 4
b1000101011111001010000111111111 :
b111111000 =
b10000110000010 $
b10000110000010 3
b10000110000010 <
1(
#1300000
0(
#1310000
16
b1000000000000 5
b1001110110000000000000000000000 #
b1001110110000000000000000000000 4
b1001110110000000000000000000000 :
b11111111111111111111000000000000 =
b1100000000000 $
b1100000000000 3
b1100000000000 <
0"
0!
b1 ;
1(
